Workbook

Sheet Goals 2026
L1: =SUBTOTAL(3,L19:L1192) -> 1169
B2: 2026 | Design Goals + Billing | G2: Billing [Cr.] | H2: Q1 | I2: Q2 | J2: Q3 | K2: Q4 | L2: Pkgs | M2: Q1 | N2: Q2 | O2: Q3 | P2: Q4 | T2: 2027 Q1 | U2: =213-O4 -> -62 | V2: 237
B4: Project | C4: Phase | D4: Discipline | E4: Design Lead | F4: Description | G4: =SUM(G6+G579) -> 286.58551 | H4: =SUM(H8,H20,H78,H95,H115,H173,H182,H192,H232,H261,H581,H1219,H305,H638,H308,H373,H758,H824,H851,H402,H432,H458,H1315,H877,H484,H508,H538, H528,H1242,H1581,H1193,H1294,H1415,H1437,H1272,H277,H947,H991,H1036,H1481,H1119,H1487,H1514,H1520,H1146,H1459,H1171,H1526,H1532,H1543,H1549,H1576,H1607,H568+H575+H674) -> 115.45647 | I4: =SUM(I8,I20,I78,I95,I115,I173,I182,I192,I232,I261,I581,I1219,I305,I638,I308,I373,I758,I824,I851,I402,I432,I458,I1315,I877,I484,I508,I538, I528,I1242,I1581,I1193,I1294,I1415,I1437,I1272,I277,I947,I991,I1036,I1481,I1119,I1487,I1514,I1520,I1146,I1459,I1171,I1526,I1532,I1543,I1549,I1576,I1607,I568+I575+I674) -> 60.026291 | J4: =SUM(J8,J20,J78,J95,J115,J173,J182,J192,J232,J261,J581,J1219,J305,J638,J308,J373,J758,J824,J851,J402,J432,J458,J1315,J877,J484,J508,J538, J528,J1242,J1581,J1193,J1294,J1415,J1437,J1272,J277,J947,J991,J1036,J1481,J1119,J1487,J1514,J1520,J1146,J1459,J1171,J1526,J1532,J1543,J1549,J1576,J1607,J568+J575+J674) -> 56.528406 | K4: =SUM(K8,K20,K78,K95,K115,K173,K182,K192,K232,K261,K581,K1219,K305,K638,K308,K373,K758,K824,K851,K402,K432,K458,K1315,K877,K484,K508,K538, K528,K1242,K1581,K1193,K1294,K1415,K1437,K1272,K277,K947,K991,K1036,K1481,K1119,K1487,K1514,K1520,K1146,K1459,K1171,K1526,K1532,K1543,K1549,K1576,K1607,K568+K575+K674) -> 54.840694 | L4: =SUM(L8,L20,L78,L95,L115,L173,L182,L192,L232,L261,L581,L1219,L305,L638,L308,L373,L758,L824,L851,L402,L432,L458,L1315,L877,L484,L508,L538, L528,L1242,L1581,L1193,L1294,L1415,L1437,L1272,L277,L947,L991,L1036,L1481,L1119,L1487,L1514,L1520,L1146,L1459,L1171,L1526,L1532,L1543,L1549,L1576,L1607,L568,L575,L674) -> 1143 | M4: =SUM(M8,M20,M78,M93,M95,M115,M173,M182,M192,M232,M261,M581,M1219,M305,M638,M308,M373,M758,M824,M851,M402,M432,M458,M1315,M877,M484,M508,M538, M528,M1242,M1581,M1193,M1294,M1415,M1437,M1272,M277,M947,M991,M1036,M1481,M1119,M1487,M1514,M1520,M1146,M1459,M1171,M1526,M1532,M1543,M1549,M1576,M1607,M568+M575+M674) -> 403 | N4: =SUM(N8,N20,N78,N95,N115,N173,N182,N192,N232,N261,N581,N1219,N305,N638,N308,N373,N758,N824,N851,N402,N432,N458,N1315,N877,N484,N508,N538, N528,N1242,N1581,N1193,N1294,N1415,N1437,N1272,N277,N947,N991,N1036,N1481,N1119,N1487,N1514,N1520,N1146,N1459,N1171,N1526,N1532,N1543,N1549,N1576,N1607,N568+N575+N674) -> 235 | O4: =SUM(O8,O20,O78,O95,O115,O173,O182,O192,O232,O261,O581,O1219,O305,O638,O308,O373,O758,O824,O851,O402,O432,O458,O1315,O877,O484,O508,O538, O528,O1242,O1581,O1193,O1294,O1415,O1437,O1272,O277,O947,O991,O1036,O1481,O1119,O1487,O1514,O1520,O1146,O1459,O1171,O1526,O1532,O1543,O1549,O1576,O1607,O568+O575+O674) -> 275 | P4: =SUM(P8,P20,P78,P95,P115,P173,P182,P192,P232,P261,P581,P1219,P305,P638,P308,P373,P758,P824,P851,P402,P432,P458,P1315,P877,P484,P508,P538, P528,P1242,P1581,P1193,P1294,P1415,P1437,P1272,P277,P947,P991,P1036,P1481,P1119,P1487,P1514,P1520,P1146,P1459,P1171,P1526,P1532,P1543,P1549,P1576,P1607,P568+P575+P674) -> 230 | R4: =IF(SUM(M4:P4)=L4,"T","F") -> T | X4: =M4/(22*3) -> 6.1060606
B6: Ongoing Projects | G6: =SUM(G8,G20,G78,G95,G115,G173,G182,G192,G232,G261,G277,G305,G308,G373,G402,,G432,G458,G484,G508,G528,G538,G568,G575,G93) -> 56.614312 | H6: =SUM(H8,H20,H78,H95,H115,H173,H182,H192,H232,H261,H277,H305,H308,H373,H402,,H432,H458,H484,H508,H528,H538,H568,H575,H93) -> 38.309869 | I6: =SUM(I8,I20,I78,I95,I115,I173,I182,I192,I232,I261,I277,I305,I308,I373,I402,,I432,I458,I484,I508,I528,I538,I568,I575,I93) -> 13.314982 | J6: =SUM(J8,J20,J78,J95,J115,J173,J182,J192,J232,J261,J277,J305,J308,J373,J402,,J432,J458,J484,J508,J528,J538,J568,J575,J93) -> 4.4936784 | K6: =SUM(K8,K20,K78,K95,K115,K173,K182,K192,K232,K261,K277,K305,K308,K373,K402,,K432,K458,K484,K508,K528,K538,K568,K575,K93) -> 0.49578224 | L6: =SUM(L8,L20,L78,L95,L115,L173,L182,L192,L232,L261,L277,L305,L308,L373,L402,,L432,L458,L484,L508,L528,L538,L568,L575,L93) -> 445 | M6: =SUM(M8,M20,M78,M95,M115,M173,M182,M192,M232,M261,M277,M305,M308,M373,M402,,M432,M458,M484,M508,M528,M538,M568,M575,M93) -> 253 | N6: =SUM(N8,N20,N78,N95,N115,N173,N182,N192,N232,N261,N277,N305,N308,N373,N402,,N432,N458,N484,N508,N528,N538,N568,N575,N93) -> 120 | ... P6: =SUM(P8,P20,P78,P95,P115,P173,P182,P192,P232,P261,P277,P305,P308,P373,P402,,P432,P458,P484,P508,P528,P538,P568,P575,P93) -> 10
B8: AtR | C8: Ph 1, 2a, 2b, 2c | F8: Package Release [Complete LoD 350 by Q1] | G8: =SUM(G9,G14,G18) -> 0.4327194 | H8: =SUM(H9,H14,H18) -> 0.4327194 | I8: =SUM(I9,I14,I18) -> 0 | J8: =SUM(J9,J14,J18) -> 0 | K8: =SUM(K9,K14,K18) -> 0 | L8: =SUM(M8:P8) -> 8 | M8: =SUM(M9,M14,M18) -> 8 | N8: =SUM(N9,N14,N18) -> 0 | O8: =SUM(O9,O14,O18) -> 0 | P8: =SUM(P9,P14,P18) -> 0 | R8: =IF(SUM(M8:P8)=L8,"T","F") -> T | T8: 1014 | U8: =T8-1077 -> -63
B9: AtR | C9: Ph 1, 2a, 2b, 2c | D9: Architecture | F9: Package Release [Complete LoD 350 by Q1] | G9: =SUM(G10:G13) -> 0.39703158 | H9: =SUM(H10:H13) -> 0.39703158 | I9: =SUM(I10:I13) -> 0 | J9: =SUM(J10:J13) -> 0 | K9: =SUM(K10:K13) -> 0 | L9: =SUM(M9:P9) -> 4 | M9: =SUM(M10:M13) -> 4 | N9: =SUM(N10:N13) -> 0 | O9: =SUM(O10:O13) -> 0 | P9: =SUM(P10:P13) -> 0 | R9: =IF(SUM(M9:P9)=L9,"T","F") -> T
B10: AtR | C10: Ph 1, 2a, 2b | D10: Architecture | E10: Saji A | F10: Clubhouse + Amenities - Clubhouse—Interiors and Facilities | G10: 0.27 | H10: =IF(M10=1,$G10,"") -> 0.27 | I10: =IF(N10=1,$G10,"") | J10: =IF(O10=1,$G10,"") | K10: =IF(P10=1,$G10,"") | L10: =SUM(M10:P10) -> 1 | M10: 1 | R10: =IF(SUM(M10:P10)=L10,"T","F") -> T
B11: AtR | C11: Ph 1, 2a, 2b | D11: Architecture | E11: Saji A | F11: Clubhouse + Amenities - Community spaces [Staff Lounge, Children play area] | G11: 0.045377036 | H11: =IF(M11=1,$G11,"") -> 0.045377036 | I11: =IF(N11=1,$G11,"") | J11: =IF(O11=1,$G11,"") | K11: =IF(P11=1,$G11,"") | L11: =SUM(M11:P11) -> 1 | M11: 1 | R11: =IF(SUM(M11:P11)=L11,"T","F") -> T
B12: AtR | C12: Ph 2c | D12: Architecture | E12: Saji A | F12: Master Plan - Site MEP | G12: 0.042238262 | H12: =IF(M12=1,$G12,"") -> 0.042238262 | I12: =IF(N12=1,$G12,"") | J12: =IF(O12=1,$G12,"") | K12: =IF(P12=1,$G12,"") | L12: =SUM(M12:P12) -> 1 | M12: 1 | R12: =IF(SUM(M12:P12)=L12,"T","F") -> T
B13: AtR | C13: Ph 2c | D13: Architecture | E13: Saji A | F13: Clubhouse + Amenities - Sporting Facilities | G13: 0.039416284 | H13: =IF(M13=1,$G13,"") -> 0.039416284 | I13: =IF(N13=1,$G13,"") | J13: =IF(O13=1,$G13,"") | K13: =IF(P13=1,$G13,"") | L13: =SUM(M13:P13) -> 1 | M13: 1 | R13: =IF(SUM(M13:P13)=L13,"T","F") -> T
B14: AtR | C14: Ph 1, 2a, 2b, 2c | D14: Structural | F14: Package Release [Complete LoD 350 by Q1] | G14: =SUM(G15:G17) -> 0.021350947 | H14: =SUM(H15:H17) -> 0.021350947 | I14: =SUM(I15:I18) -> 0 | J14: =SUM(J15:J18) -> 0 | K14: =SUM(K15:K18) -> 0 | L14: =SUM(M14:P14) -> 3 | M14: =SUM(M15:M17) -> 3 | N14: =SUM(N15:N17) -> 0 | O14: =SUM(O15:O17) -> 0 | P14: =SUM(P15:P17) -> 0 | R14: =IF(SUM(M14:P14)=L14,"T","F") -> T
B15: AtR | C15: Ph 1, 2a, 2b | D15: Structural | E15: Prakash C | F15: Clubhouse + Amenities - Community spaces [Staff Lounge, Children play area] | G15: 0.0052867303 | H15: =IF(M15=1,$G15,"") -> 0.0052867303 | I15: =IF(N15=1,$G15,"") | J15: =IF(O15=1,$G15,"") | K15: =IF(P15=1,$G15,"") | L15: =SUM(M15:P15) -> 1 | M15: 1 | R15: =IF(SUM(M15:P15)=L15,"T","F") -> T
B16: AtR | C16: Ph 2c | D16: Structural | E16: Prakash C | F16: Master Plan - Site MEP | G16: 0.010861268 | H16: =IF(M16=1,$G16,"") -> 0.010861268 | I16: =IF(N16=1,$G16,"") | J16: =IF(O16=1,$G16,"") | K16: =IF(P16=1,$G16,"") | L16: =SUM(M16:P16) -> 1 | M16: 1 | R16: =IF(SUM(M16:P16)=L16,"T","F") -> T
B17: AtR | C17: Ph 2c | D17: Structural | E17: Prakash C | F17: Clubhouse + Amenities - Sporting Facilities | G17: 0.0052029495 | H17: =IF(M17=1,$G17,"") -> 0.0052029495 | I17: =IF(N17=1,$G17,"") | J17: =IF(O17=1,$G17,"") | K17: =IF(P17=1,$G17,"") | L17: =SUM(M17:P17) -> 1 | M17: 1 | R17: =IF(SUM(M17:P17)=L17,"T","F") -> T
B18: AtR | C18: Ph 1, 2a, 2b, 2c | D18: MEP | F18: Package Release [Complete LoD 350 by Q1] | G18: =SUM(G19:G19) -> 0.014336873 | H18: =SUM(H19:H19) -> 0.014336873 | I18: =SUM(I19:I19) -> 0 | J18: =SUM(J19:J19) -> 0 | K18: =SUM(K19:K19) -> 0 | L18: =SUM(M18:P18) -> 1 | M18: =SUM(M19:M19) -> 1 | N18: =SUM(N19:N19) -> 0 | O18: =SUM(O19:O19) -> 0 | P18: =SUM(P19:P19) -> 0 | R18: =IF(SUM(M18:P18)=L18,"T","F") -> T
B19: AtR | C19: Ph 2c | D19: MEP | E19: Gagan | F19: Master Plan - Site MEP | G19: 0.014336873 | H19: =IF(M19=1,$G19,"") -> 0.014336873 | I19: =IF(N19=1,$G19,"") | J19: =IF(O19=1,$G19,"") | K19: =IF(P19=1,$G19,"") | L19: =SUM(M19:P19) -> 1 | M19: 1 | R19: =IF(SUM(M19:P19)=L19,"T","F") -> T
B20: AtR | C20: Ph 3 | F20: Package Release [Complete LoD 350 by Q1] | G20: =SUM(G21,G41,G61,G71) -> 3.2133416 | H20: =SUM(H21,H41,H61,H71) -> 2.5304736 | I20: =SUM(I21,I41,I61,I71) -> 0.68286799 | J20: =SUM(J21,J41,J61,J71) -> 0 | K20: =SUM(K21,K41,K61,K71) -> 0 | L20: =SUM(M20:P20) -> 53 | M20: =SUM(M21,M41,M61,M71) -> 42 | N20: =SUM(N21,N41,N61,N71) -> 11 | O20: =SUM(O21,O41,O61,O71) -> 0 | P20: =SUM(P21,P41,P61,P71) -> 0 | R20: =IF(SUM(M20:P20)=L20,"T","F") -> T
B21: AtR | C21: Ph 3 | D21: Architecture | F21: Package Release [Complete LoD 350 by Q1] | G21: =SUM(G22:G40) -> 2.2814903 | H21: =SUM(H22:H40) -> 1.8087698 | I21: =SUM(I22:I40) -> 0.47272049 | J21: =SUM(J22:J40) -> 0 | K21: =SUM(K22:K40) -> 0 | L21: =SUM(M21:P21) -> 19 | M21: =SUM(M22:M40) -> 15 | N21: =SUM(N22:N40) -> 4 | O21: =SUM(O22:O40) -> 0 | P21: =SUM(P22:P40) -> 0 | Q21: =SUM(Q22:Q40) -> 0 | R21: =IF(SUM(M21:P21)=L21,"T","F") -> T
B22: AtR | C22: Ph 3 | D22: Architecture | E22: Saji A | F22: Contract + Design brief | G22: 0.27398367 | H22: =IF(M22=1,$G22,"") -> 0.27398367 | I22: =IF(N22=1,$G22,"") | J22: =IF(O22=1,$G22,"") | K22: =IF(P22=1,$G22,"") | L22: =SUM(M22:P22) -> 1 | M22: 1 | R22: =IF(SUM(M22:P22)=L22,"T","F") -> T
B23: AtR | C23: Ph 3 | D23: Architecture | E23: Saji A | F23: Schematic Concept | G23: 0.27398367 | H23: =IF(M23=1,$G23,"") -> 0.27398367 | I23: =IF(N23=1,$G23,"") | J23: =IF(O23=1,$G23,"") | K23: =IF(P23=1,$G23,"") | L23: =SUM(M23:P23) -> 1 | M23: 1 | R23: =IF(SUM(M23:P23)=L23,"T","F") -> T
B24: AtR | C24: Ph 3 | D24: Architecture | E24: Saji A | F24: Approvals | G24: 0.13699183 | H24: =IF(M24=1,$G24,"") -> 0.13699183 | I24: =IF(N24=1,$G24,"") | J24: =IF(O24=1,$G24,"") | K24: =IF(P24=1,$G24,"") | L24: =SUM(M24:P24) -> 1 | M24: 1 | R24: =IF(SUM(M24:P24)=L24,"T","F") -> T
B25: AtR | C25: Ph 3 | D25: Architecture | E25: Saji A | F25: Pre Construction Set | G25: 0.27398367 | H25: =IF(M25=1,$G25,"") -> 0.27398367 | I25: =IF(N25=1,$G25,"") | J25: =IF(O25=1,$G25,"") | K25: =IF(P25=1,$G25,"") | L25: =SUM(M25:P25) -> 1 | M25: 1 | R25: =IF(SUM(M25:P25)=L25,"T","F") -> T
B26: AtR | C26: Ph 3 | D26: Architecture | E26: Saji A | F26: Home Products - V45 Default and it's variants | G26: 0.36 | H26: =IF(M26=1,$G26,"") -> 0.36 | I26: =IF(N26=1,$G26,"") | J26: =IF(O26=1,$G26,"") | K26: =IF(P26=1,$G26,"") | L26: =SUM(M26:P26) -> 1 | M26: 1 | R26: =IF(SUM(M26:P26)=L26,"T","F") -> T
B27: AtR | C27: Ph 3 | D27: Architecture | E27: Saji A | F27: Home Products - V80 Default and it's variants | G27: 0.36 | H27: =IF(M27=1,$G27,"") | I27: =IF(N27=1,$G27,"") -> 0.36 | J27: =IF(O27=1,$G27,"") | K27: =IF(P27=1,$G27,"") | L27: =SUM(N27:P27) -> 1 | N27: 1 | R27: =IF(SUM(N27:P27)=L27,"T","F") -> T
B28: AtR | C28: Ph 3 | D28: Architecture | E28: Saji A | F28: Villa Block 33 - Foundations and Sub-Grade Structure | G28: 0.043982696 | H28: =IF(M28=1,$G28,"") -> 0.043982696 | I28: =IF(N28=1,$G28,"") | J28: =IF(O28=1,$G28,"") | K28: =IF(P28=1,$G28,"") | L28: =SUM(M28:P28) -> 1 | M28: 1 | R28: =IF(SUM(M28:P28)=L28,"T","F") -> T
B29: AtR | C29: Ph 3 | D29: Architecture | E29: Saji A | F29: Villa Block 34 - Foundations and Sub-Grade Structure | G29: 0.043982696 | H29: =IF(M29=1,$G29,"") -> 0.043982696 | I29: =IF(N29=1,$G29,"") | J29: =IF(O29=1,$G29,"") | K29: =IF(P29=1,$G29,"") | L29: =SUM(M29:P29) -> 1 | M29: 1 | R29: =IF(SUM(M29:P29)=L29,"T","F") -> T
B30: AtR | C30: Ph 3 | D30: Architecture | E30: Saji A | F30: Villa Block 29 - Foundations and Sub-Grade Structure | G30: 0.065974043 | H30: =IF(M30=1,$G30,"") -> 0.065974043 | L30: =SUM(M30:P30) -> 1 | M30: 1
B31: AtR | C31: Ph 3 | D31: Architecture | E31: Saji A | F31: Villa Block 29 - Building Envelope + Plot Development | G31: 0.065974043 | H31: =IF(M31=1,$G31,"") -> 0.065974043 | I31: =IF(N31=1,$G31,"") | J31: =IF(O31=1,$G31,"") | K31: =IF(P31=1,$G31,"") | L31: =SUM(M31:P31) -> 1 | M31: 1 | R31: =IF(SUM(M31:P31)=L31,"T","F") -> T
B32: AtR | C32: Ph 3 | D32: Architecture | E32: Saji A | F32: Villa Block 30 - Foundations and Sub-Grade Structure | G32: 0.065974043 | H32: =IF(M32=1,$G32,"") -> 0.065974043 | L32: =SUM(M32:P32) -> 1 | M32: 1
B33: AtR | C33: Ph 3 | D33: Architecture | E33: Saji A | F33: Villa Block 30 - Building Envelope + Plot Development | G33: 0.065974043 | H33: =IF(M33=1,$G33,"") -> 0.065974043 | I33: =IF(N33=1,$G33,"") | J33: =IF(O33=1,$G33,"") | K33: =IF(P33=1,$G33,"") | L33: =SUM(M33:P33) -> 1 | M33: 1 | R33: =IF(SUM(M33:P33)=L33,"T","F") -> T
B34: AtR | C34: Ph 3 | D34: Architecture | E34: Saji A | F34: Villa Block 31 - Building Envelope + Plot Development | G34: 0.014660899 | H34: =IF(M34=1,$G34,"") -> 0.014660899 | I34: =IF(N34=1,$G34,"") | J34: =IF(O34=1,$G34,"") | K34: =IF(P34=1,$G34,"") | L34: =SUM(M34:P34) -> 1 | M34: 1 | R34: =IF(SUM(M34:P34)=L34,"T","F") -> T
B35: AtR | C35: Ph 3 | D35: Architecture | E35: Saji A | F35: Villa Block 32 - Building Envelope + Plot Development | G35: 0.029321797 | H35: =IF(M35=1,$G35,"") -> 0.029321797 | I35: =IF(N35=1,$G35,"") | J35: =IF(O35=1,$G35,"") | K35: =IF(P35=1,$G35,"") | L35: =SUM(M35:P35) -> 1 | M35: 1 | R35: =IF(SUM(M35:P35)=L35,"T","F") -> T
B36: AtR | C36: Ph 3 | D36: Architecture | E36: Saji A | F36: Villa Block 33 - Building Envelope + Plot Development | G36: 0.043982696 | H36: =IF(M36=1,$G36,"") | I36: =IF(N36=1,$G36,"") -> 0.043982696 | J36: =IF(O36=1,$G36,"") | K36: =IF(P36=1,$G36,"") | L36: =SUM(M36:P36) -> 1 | N36: 1 | R36: =IF(SUM(M36:P36)=L36,"T","F") -> T
B37: AtR | C37: Ph 3 | D37: Architecture | E37: Saji A | F37: Villa Block 34 - Building Envelope + Plot Development | G37: 0.043982696 | H37: =IF(M37=1,$G37,"") -> 0.043982696 | I37: =IF(N37=1,$G37,"") | J37: =IF(O37=1,$G37,"") | K37: =IF(P37=1,$G37,"") | L37: =SUM(M37:P37) -> 1 | M37: 1 | R37: =IF(SUM(M37:P37)=L37,"T","F") -> T
B38: AtR | C38: Ph 3 | D38: Architecture | E38: Saji A | F38: Master Plan - Master Plan | G38: 0.05 | H38: =IF(M38=1,$G38,"") -> 0.05 | I38: =IF(N38=1,$G38,"") | J38: =IF(O38=1,$G38,"") | K38: =IF(P38=1,$G38,"") | L38: =SUM(M38:P38) -> 1 | M38: 1 | R38: =IF(SUM(M38:P38)=L38,"T","F") -> T
B39: AtR | C39: Ph 3 | D39: Architecture | E39: Saji A | F39: Site Development - 02 Road Works | G39: 0.05 | H39: =IF(M39=1,$G39,"") | I39: =IF(N39=1,$G39,"") -> 0.05 | J39: =IF(O39=1,$G39,"") | K39: =IF(P39=1,$G39,"") | L39: =SUM(M39:P39) -> 1 | N39: 1 | R39: =IF(SUM(M39:P39)=L39,"T","F") -> T
B40: AtR | C40: Ph 3 | D40: Architecture | E40: Saji A | F40: Site Development - 06 Landscape | G40: 0.018737796 | H40: =IF(M40=1,$G40,"") | I40: =IF(N40=1,$G40,"") -> 0.018737796 | J40: =IF(O40=1,$G40,"") | K40: =IF(P40=1,$G40,"") | L40: =SUM(M40:P40) -> 1 | N40: 1 | R40: =IF(SUM(M40:P40)=L40,"T","F") -> T
B41: AtR | C41: Ph 3 | D41: Structural | F41: Package Release [Complete LoD 350 by Q1] | G41: =SUM(G42:G60) -> 0.43466801 | H41: =SUM(H42:H60) -> 0.35597209 | I41: =SUM(I42:I60) -> 0.07869592 | J41: =SUM(J42:J60) -> 0 | K41: =SUM(K42:K60) -> 0 | L41: =SUM(M41:P41) -> 19 | M41: =SUM(M42:M60) -> 15 | N41: =SUM(N42:N60) -> 4 | O41: =SUM(O42:O60) -> 0 | P41: =SUM(P42:P60) -> 0 | R41: =IF(SUM(M41:P41)=L41,"T","F") -> T
B42: AtR | C42: Ph 3 | D42: Structural | E42: Prakash C | F42: Schematic Concept | G42: 0.093421604 | H42: =IF(M42=1,$G42,"") -> 0.093421604 | I42: =IF(N42=1,$G42,"") | J42: =IF(O42=1,$G42,"") | K42: =IF(P42=1,$G42,"") | L42: =SUM(M42:P42) -> 1 | M42: 1 | R42: =IF(SUM(M42:P42)=L42,"T","F") -> T
B43: AtR | C43: Ph 3 | D43: Structural | E43: Prakash C | F43: Pre Construction Set | G43: 0.093421604 | H43: =IF(M43=1,$G43,"") -> 0.093421604 | I43: =IF(N43=1,$G43,"") | J43: =IF(O43=1,$G43,"") | K43: =IF(P43=1,$G43,"") | L43: =SUM(M43:P43) -> 1 | M43: 1 | R43: =IF(SUM(M43:P43)=L43,"T","F") -> T
B44: AtR | C44: Ph 3 | D44: Structural | E44: Prakash C | F44: Villa Block 29 - Foundations and Sub-Grade Structure | G44: 0.021106865 | H44: =IF(M44=1,$G44,"") -> 0.021106865 | I44: =IF(N44=1,$G44,"") | J44: =IF(O44=1,$G44,"") | K44: =IF(P44=1,$G44,"") | L44: =SUM(M44:P44) -> 1 | M44: 1 | R44: =IF(SUM(M44:P44)=L44,"T","F") -> T
B45: AtR | C45: Ph 3 | D45: Structural | E45: Prakash C | F45: Villa Block 29 - Super Structure | G45: 0.031660298 | H45: =IF(M45=1,$G45,"") -> 0.031660298 | I45: =IF(N45=1,$G45,"") | J45: =IF(O45=1,$G45,"") | K45: =IF(P45=1,$G45,"") | L45: =SUM(M45:P45) -> 1 | M45: 1 | R45: =IF(SUM(M45:P45)=L45,"T","F") -> T
B46: AtR | C46: Ph 3 | D46: Structural | E46: Prakash C | F46: Villa Block 29 - Building Envelope + Plot Development | G46: 0.0052767164 | H46: =IF(M46=1,$G46,"") -> 0.0052767164 | I46: =IF(N46=1,$G46,"") | J46: =IF(O46=1,$G46,"") | K46: =IF(P46=1,$G46,"") | L46: =SUM(M46:P46) -> 1 | M46: 1 | R46: =IF(SUM(M46:P46)=L46,"T","F") -> T
B47: AtR | C47: Ph 3 | D47: Structural | E47: Prakash C | F47: Villa Block 30 - Foundations and Sub-Grade Structure | G47: 0.021106865 | H47: =IF(M47=1,$G47,"") -> 0.021106865 | I47: =IF(N47=1,$G47,"") | J47: =IF(O47=1,$G47,"") | K47: =IF(P47=1,$G47,"") | L47: =SUM(M47:P47) -> 1 | M47: 1 | R47: =IF(SUM(M47:P47)=L47,"T","F") -> T
B48: AtR | C48: Ph 3 | D48: Structural | E48: Prakash C | F48: Villa Block 30 - Super Structure | G48: 0.031660298 | H48: =IF(M48=1,$G48,"") -> 0.031660298 | I48: =IF(N48=1,$G48,"") | J48: =IF(O48=1,$G48,"") | K48: =IF(P48=1,$G48,"") | L48: =SUM(M48:P48) -> 1 | M48: 1 | R48: =IF(SUM(M48:P48)=L48,"T","F") -> T
B49: AtR | C49: Ph 3 | D49: Structural | E49: Prakash C | F49: Villa Block 30 - Building Envelope + Plot Development | G49: 0.0052767164 | H49: =IF(M49=1,$G49,"") -> 0.0052767164 | I49: =IF(N49=1,$G49,"") | J49: =IF(O49=1,$G49,"") | K49: =IF(P49=1,$G49,"") | L49: =SUM(M49:P49) -> 1 | M49: 1 | R49: =IF(SUM(M49:P49)=L49,"T","F") -> T
B50: AtR | C50: Ph 3 | D50: Structural | E50: Prakash C | F50: Villa Block 31 - Foundations and Sub-Grade Structure | G50: 0.004 | H50: =IF(M50=1,$G50,"") -> 0.004 | I50: =IF(N50=1,$G50,"") | J50: =IF(O50=1,$G50,"") | K50: =IF(P50=1,$G50,"") | L50: =SUM(M50:P50) -> 1 | M50: 1 | R50: =IF(SUM(M50:P50)=L50,"T","F") -> T
B51: AtR | C51: Ph 3 | D51: Structural | E51: Prakash C | F51: Villa Block 31 - Super Structure | G51: 0.007 | H51: =IF(M51=1,$G51,"") -> 0.007 | I51: =IF(N51=1,$G51,"") | J51: =IF(O51=1,$G51,"") | K51: =IF(P51=1,$G51,"") | L51: =SUM(M51:P51) -> 1 | M51: 1 | R51: =IF(SUM(M51:P51)=L51,"T","F") -> T
B52: AtR | C52: Ph 3 | D52: Structural | E52: Prakash C | F52: Villa Block 31 - Building Envelope + Plot Development | G52: 0.001 | H52: =IF(M52=1,$G52,"") -> 0.001 | I52: =IF(N52=1,$G52,"") | J52: =IF(O52=1,$G52,"") | K52: =IF(P52=1,$G52,"") | L52: =SUM(M52:P52) -> 1 | M52: 1 | R52: =IF(SUM(M52:P52)=L52,"T","F") -> T
B53: AtR | C53: Ph 3 | D53: Structural | E53: Prakash C | F53: Villa Block 32 - Building Envelope + Plot Development | G53: 0.0023452073 | H53: =IF(M53=1,$G53,"") -> 0.0023452073 | I53: =IF(N53=1,$G53,"") | J53: =IF(O53=1,$G53,"") | K53: =IF(P53=1,$G53,"") | L53: =SUM(M53:P53) -> 1 | M53: 1 | R53: =IF(SUM(M53:P53)=L53,"T","F") -> T
B54: AtR | C54: Ph 3 | D54: Structural | E54: Prakash C | F54: Villa Block 33 - Foundations and Sub-Grade Structure | G54: 0.014071244 | H54: =IF(M54=1,$G54,"") | I54: =IF(N54=1,$G54,"") -> 0.014071244 | J54: =IF(O54=1,$G54,"") | K54: =IF(P54=1,$G54,"") | L54: =SUM(M54:P54) -> 1 | N54: 1 | R54: =IF(SUM(M54:P54)=L54,"T","F") -> T
B55: AtR | C55: Ph 3 | D55: Structural | E55: Prakash C | F55: Villa Block 33 - Super Structure | G55: 0.021106865 | H55: =IF(M55=1,$G55,"") | I55: =IF(N55=1,$G55,"") -> 0.021106865 | J55: =IF(O55=1,$G55,"") | K55: =IF(P55=1,$G55,"") | L55: =SUM(M55:P55) -> 1 | N55: 1 | R55: =IF(SUM(M55:P55)=L55,"T","F") -> T
B56: AtR | C56: Ph 3 | D56: Structural | E56: Prakash C | F56: Villa Block 33 - Building Envelope + Plot Development | G56: 0.0035178109 | H56: =IF(M56=1,$G56,"") | I56: =IF(N56=1,$G56,"") -> 0.0035178109 | J56: =IF(O56=1,$G56,"") | K56: =IF(P56=1,$G56,"") | L56: =SUM(M56:P56) -> 1 | N56: 1 | R56: =IF(SUM(M56:P56)=L56,"T","F") -> T
B57: AtR | C57: Ph 3 | D57: Structural | E57: Prakash C | F57: Villa Block 34 - Foundations and Sub-Grade Structure | G57: 0.014071244 | H57: =IF(M57=1,$G57,"") -> 0.014071244 | I57: =IF(N57=1,$G57,"") | J57: =IF(O57=1,$G57,"") | K57: =IF(P57=1,$G57,"") | L57: =SUM(M57:P57) -> 1 | M57: 1 | R57: =IF(SUM(M57:P57)=L57,"T","F") -> T
B58: AtR | C58: Ph 3 | D58: Structural | E58: Prakash C | F58: Villa Block 34 - Super Structure | G58: 0.021106865 | H58: =IF(M58=1,$G58,"") -> 0.021106865 | I58: =IF(N58=1,$G58,"") | J58: =IF(O58=1,$G58,"") | K58: =IF(P58=1,$G58,"") | L58: =SUM(M58:P58) -> 1 | M58: 1 | R58: =IF(SUM(M58:P58)=L58,"T","F") -> T
B59: AtR | C59: Ph 3 | D59: Structural | E59: Prakash C | F59: Villa Block 34 - Building Envelope + Plot Development | G59: 0.0035178109 | H59: =IF(M59=1,$G59,"") -> 0.0035178109 | I59: =IF(N59=1,$G59,"") | J59: =IF(O59=1,$G59,"") | K59: =IF(P59=1,$G59,"") | L59: =SUM(M59:P59) -> 1 | M59: 1 | R59: =IF(SUM(M59:P59)=L59,"T","F") -> T
B60: AtR | C60: Ph 3 | D60: Structural | E60: Prakash C | F60: Site Development - 02 Road Works | G60: 0.04 | H60: =IF(M60=1,$G60,"") | I60: =IF(N60=1,$G60,"") -> 0.04 | J60: =IF(O60=1,$G60,"") | K60: =IF(P60=1,$G60,"") | L60: =SUM(M60:P60) -> 1 | N60: 1 | R60: =IF(SUM(M60:P60)=L60,"T","F") -> T
B61: AtR | C61: Ph 3 | D61: MEP | F61: Package Release [Complete LoD 350 by Q1] | G61: =SUM(G62:G70) -> 0.28638112 | H61: =SUM(H62:H70) -> 0.19360007 | I61: =SUM(I62:I70) -> 0.092781044 | J61: =SUM(J62:J70) -> 0 | K61: =SUM(K62:K70) -> 0 | L61: =SUM(M61:P61) -> 9 | M61: =SUM(M62:M70) -> 7 | N61: =SUM(N62:N70) -> 2 | O61: =SUM(O62:O70) -> 0 | P61: =SUM(P62:P70) -> 0 | R61: =IF(SUM(M61:P61)=L61,"T","F") -> T
B62: AtR | C62: Ph 3 | D62: MEP | E62: Gagan | F62: Schematic Concept [V80] | G62: 0.021499694 | H62: =IF(M62=1,$G62,"") -> 0.021499694 | I62: =IF(N62=1,$G62,"") | J62: =IF(O62=1,$G62,"") | K62: =IF(P62=1,$G62,"") | L62: =SUM(M62:P62) -> 1 | M62: 1 | R62: =IF(SUM(M62:P62)=L62,"T","F") -> T
B63: AtR | C63: Ph 3 | D63: MEP | E63: Gagan | F63: PreConstruction Set | G63: 0.021499694 | H63: =IF(M63=1,$G63,"") -> 0.021499694 | I63: =IF(N63=1,$G63,"") | J63: =IF(O63=1,$G63,"") | K63: =IF(P63=1,$G63,"") | L63: =SUM(M63:P63) -> 1 | M63: 1 | R63: =IF(SUM(M63:P63)=L63,"T","F") -> T
B64: AtR | C64: Ph 3 | D64: MEP | E64: Gagan | F64: Villa Block 31 - Foundations and Sub-Grade Structure | G64: 0.00094245303 | H64: =IF(M64=1,$G64,"") -> 0.00094245303 | I64: =IF(N64=1,$G64,"") | J64: =IF(O64=1,$G64,"") | K64: =IF(P64=1,$G64,"") | L64: =SUM(M64:P64) -> 1 | M64: 1 | R64: =IF(SUM(M64:P64)=L64,"T","F") -> T
B65: AtR | C65: Ph 3 | D65: MEP | E65: Gagan | F65: Villa Block 32 - Foundations and Sub-Grade Structure | G65: 0.0018849061 | H65: =IF(M65=1,$G65,"") -> 0.0018849061 | I65: =IF(N65=1,$G65,"") | J65: =IF(O65=1,$G65,"") | K65: =IF(P65=1,$G65,"") | L65: =SUM(M65:P65) -> 1 | M65: 1 | R65: =IF(SUM(M65:P65)=L65,"T","F") -> T
B66: AtR | C66: Ph 3 | D66: MEP | E66: Gagan | F66: Villa Block 33 - Foundations and Sub-Grade Structure | G66: 0.0028273591 | H66: =IF(M66=1,$G66,"") | I66: =IF(N66=1,$G66,"") -> 0.0028273591 | J66: =IF(O66=1,$G66,"") | K66: =IF(P66=1,$G66,"") | L66: =SUM(M66:P66) -> 1 | N66: 1 | R66: =IF(SUM(M66:P66)=L66,"T","F") -> T
B67: AtR | C67: Ph 3 | D67: MEP | E67: Gagan | F67: Villa Block 34 - Foundations and Sub-Grade Structure | G67: 0.0028273591 | H67: =IF(M67=1,$G67,"") -> 0.0028273591 | I67: =IF(N67=1,$G67,"") | J67: =IF(O67=1,$G67,"") | K67: =IF(P67=1,$G67,"") | L67: =SUM(M67:P67) -> 1 | M67: 1 | R67: =IF(SUM(M67:P67)=L67,"T","F") -> T
B68: AtR | C68: Ph 3 | D68: MEP | E68: Gagan | F68: Home Products - V45 Default and it's variants | G68: 0.10494597 | H68: =IF(M68=1,$G68,"") -> 0.10494597 | I68: =IF(N68=1,$G68,"") | J68: =IF(O68=1,$G68,"") | K68: =IF(P68=1,$G68,"") | L68: =SUM(M68:P68) -> 1 | M68: 1 | R68: =IF(SUM(M68:P68)=L68,"T","F") -> T
B69: AtR | C69: Ph 3 | D69: MEP | E69: Gagan | F69: Home Products - V80 Default and it's variants | G69: 0.089953685 | H69: =IF(M69=1,$G69,"") | I69: =IF(N69=1,$G69,"") -> 0.089953685 | J69: =IF(O69=1,$G69,"") | K69: =IF(P69=1,$G69,"") | L69: =SUM(M69:P69) -> 1 | N69: 1 | R69: =IF(SUM(M69:P69)=L69,"T","F") -> T
B70: AtR | C70: Ph 3 | D70: MEP | E70: Gagan | F70: Master Plan - Master Plan | G70: 0.04 | H70: =IF(M70=1,$G70,"") -> 0.04 | I70: =IF(N70=1,$G70,"") | J70: =IF(O70=1,$G70,"") | K70: =IF(P70=1,$G70,"") | L70: =SUM(M70:P70) -> 1 | M70: 1 | R70: =IF(SUM(M70:P70)=L70,"T","F") -> T
B71: AtR | C71: Ph 3 | D71: Landscape | F71: Package Release [Complete LoD 350 by Q1] | G71: =SUM(G72:G77) -> 0.21080222 | H71: =SUM(H72:H77) -> 0.17213169 | I71: =SUM(I72:I77) -> 0.038670538 | J71: =SUM(J72:J77) -> 0 | K71: =SUM(K72:K77) -> 0 | L71: =SUM(M71:P71) -> 6 | M71: =SUM(M72:M77) -> 5 | N71: =SUM(N72:N77) -> 1 | O71: =SUM(O72:O77) -> 0 | P71: =SUM(P72:P77) -> 0 | R71: =IF(SUM(M71:P71)=L71,"T","F") -> T
B72: AtR | C72: Ph 3 | D72: Landscape | E72: Gagan | F72: Schematic Concept | G72: 0.04786352 | H72: =IF(M72=1,$G72,"") -> 0.04786352 | I72: =IF(N72=1,$G72,"") | J72: =IF(O72=1,$G72,"") | K72: =IF(P72=1,$G72,"") | L72: =SUM(M72:P72) -> 1 | M72: 1 | R72: =IF(SUM(M72:P72)=L72,"T","F") -> T | S72: will be closed by Q4 2025
B73: AtR | C73: Ph 3 | D73: Landscape | E73: Gagan | F73: Preconstruction Set | G73: 0.04786352 | H73: =IF(M73=1,$G73,"") -> 0.04786352 | I73: =IF(N73=1,$G73,"") | J73: =IF(O73=1,$G73,"") | K73: =IF(P73=1,$G73,"") | L73: =SUM(M73:P73) -> 1 | M73: 1 | R73: =IF(SUM(M73:P73)=L73,"T","F") -> T
B74: AtR | C74: Ph 3 | D74: Landscape | E74: Gagan | F74: Home Products - V45 Default | G74: 0.046404646 | H74: =IF(M74=1,$G74,"") -> 0.046404646 | I74: =IF(N74=1,$G74,"") | J74: =IF(O74=1,$G74,"") | K74: =IF(P74=1,$G74,"") | L74: =SUM(M74:P74) -> 1 | M74: 1 | R74: =IF(SUM(M74:P74)=L74,"T","F") -> T
B75: AtR | C75: Ph 3 | D75: Landscape | E75: Gagan | F75: Home Products - V80 Default | G75: 0.038670538 | H75: =IF(M75=1,$G75,"") | I75: =IF(N75=1,$G75,"") -> 0.038670538 | J75: =IF(O75=1,$G75,"") | K75: =IF(P75=1,$G75,"") | L75: =SUM(M75:P75) -> 1 | N75: 1 | R75: =IF(SUM(M75:P75)=L75,"T","F") -> T
B76: AtR | C76: Ph 3 | D76: Landscape | E76: Gagan | F76: Master Plan | G76: 0.02 | H76: =IF(M76=1,$G76,"") -> 0.02 | I76: =IF(N76=1,$G76,"") | J76: =IF(O76=1,$G76,"") | K76: =IF(P76=1,$G76,"") | L76: =SUM(M76:P76) -> 1 | M76: 1 | R76: =IF(SUM(M76:P76)=L76,"T","F") -> T
B77: AtR | C77: Ph 3 | D77: Landscape | E77: Gagan | F77: Site Development - 06 Landscape | G77: 0.01 | H77: =IF(M77=1,$G77,"") -> 0.01 | I77: =IF(N77=1,$G77,"") | J77: =IF(O77=1,$G77,"") | K77: =IF(P77=1,$G77,"") | L77: =SUM(M77:P77) -> 1 | M77: 1 | R77: =IF(SUM(M77:P77)=L77,"T","F") -> T
B78: AtR - C | C78: Com | F78: Package Release [Complete LoD 350 by Q1] | G78: =SUM(G79,G83,G90) -> 1.3329594 | H78: =SUM(H79,H83,H90) -> 0.94561876 | I78: =SUM(I79,I83,I90) -> 0.25822711 | J78: =SUM(J79,J83,J90) -> 0.12911356 | K78: =SUM(K79,K83,K90) -> 0 | L78: =SUM(M78:P78) -> 11 | M78: =SUM(M79,M83,M90) -> 9 | N78: =SUM(N79,N83,N90) -> 1 | O78: =SUM(O79,O83,O90) -> 1 | P78: =SUM(P79,P83,P90) -> 0 | R78: =IF(SUM(M78:P78)=L78,"T","F") -> T
B79: AtR - C | C79: Com | D79: Architecture | F79: Package Release [Complete LoD 350 by Q1] | G79: =SUM(G80:G82) -> 0.36421477 | H79: =SUM(H80:H82) -> 0.36421477 | I79: =SUM(I80:I82) -> 0 | J79: =SUM(J80:J82) -> 0 | K79: =SUM(K80:K82) -> 0 | L79: =SUM(M79:P79) -> 3 | M79: =SUM(M80:M82) -> 3 | N79: =SUM(N80:N82) -> 0 | O79: =SUM(O80:O82) -> 0 | P79: =SUM(P80:P82) -> 0 | R79: =IF(SUM(M79:P79)=L79,"T","F") -> T
B80: AtR - C | C80: Com | D80: Architecture | E80: Naveen Y | F80: Master Plan - Site Development | G80: 0.13658054 | H80: =IF(M80=1,$G80,"") -> 0.13658054 | I80: =IF(N80=1,$G80,"") | J80: =IF(O80=1,$G80,"") | K80: =IF(P80=1,$G80,"") | L80: =SUM(M80:P80) -> 1 | M80: 1 | R80: =IF(SUM(M80:P80)=L80,"T","F") -> T
B81: AtR - C | C81: Com | D81: Architecture | E81: Naveen Y | F81: Master Plan - Site MEP | G81: 0.18210739 | H81: =IF(M81=1,$G81,"") -> 0.18210739 | I81: =IF(N81=1,$G81,"") | J81: =IF(O81=1,$G81,"") | K81: =IF(P81=1,$G81,"") | L81: =SUM(M81:P81) -> 1 | M81: 1 | R81: =IF(SUM(M81:P81)=L81,"T","F") -> T
B82: AtR - C | C82: Com | D82: Architecture | E82: Naveen Y | F82: Master Plan - Landscaping | G82: 0.045526847 | H82: =IF(M82=1,$G82,"") -> 0.045526847 | I82: =IF(N82=1,$G82,"") | J82: =IF(O82=1,$G82,"") | K82: =IF(P82=1,$G82,"") | L82: =SUM(M82:P82) -> 1 | M82: 1 | R82: =IF(SUM(M82:P82)=L82,"T","F") -> T
B83: AtR - C | C83: Com | D83: Structural | F83: Package Release [Complete LoD 350 by Q1] | G83: =SUM(G84:G89) -> 0.80123917 | H83: =SUM(H84:H89) -> 0.4138985 | I83: =SUM(I84:I89) -> 0.25822711 | J83: =SUM(J84:J89) -> 0.12911356 | K83: =SUM(K84:K89) -> 0 | L83: =SUM(M83:P83) -> 6 | M83: =SUM(M84:M89) -> 4 | N83: =SUM(N84:N89) -> 1 | O83: =SUM(O84:O89) -> 1 | P83: =SUM(P84:P89) -> 0 | R83: =IF(SUM(M83:P83)=L83,"T","F") -> T
B84: AtR - C | C84: Com | D84: Structural | E84: Prakash C | F84: Tower-[Commercial] - Habitable Level 1-2 | G84: 0.12911356 | H84: =IF(M84=1,$G84,"") -> 0.12911356 | I84: =IF(N84=1,$G84,"") | J84: =IF(O84=1,$G84,"") | K84: =IF(P84=1,$G84,"") | L84: =SUM(M84:P84) -> 1 | M84: 1 | R84: =IF(SUM(M84:P84)=L84,"T","F") -> T
B85: AtR - C | C85: Com | D85: Structural | E85: Prakash C | F85: Tower-[Commercial] - Habitable Level 3-5 | G85: 0.25822711 | H85: =IF(M85=1,$G85,"") -> 0.25822711 | I85: =IF(N85=1,$G85,"") | J85: =IF(O85=1,$G85,"") | K85: =IF(P85=1,$G85,"") | L85: =SUM(M85:P85) -> 1 | M85: 1 | R85: =IF(SUM(M85:P85)=L85,"T","F") -> T
B86: AtR - C | C86: Com | D86: Structural | E86: Prakash C | F86: Tower-[Commercial] - Habitable Level 6-10 | G86: 0.25822711 | H86: =IF(M86=1,$G86,"") | I86: =IF(N86=1,$G86,"") -> 0.25822711 | J86: =IF(O86=1,$G86,"") | K86: =IF(P86=1,$G86,"") | L86: =SUM(M86:P86) -> 1 | N86: 1 | R86: =IF(SUM(M86:P86)=L86,"T","F") -> T
B87: AtR - C | C87: Com | D87: Structural | E87: Prakash C | F87: Tower-[Commercial] - Terrace Level | G87: 0.12911356 | H87: =IF(M87=1,$G87,"") | I87: =IF(N87=1,$G87,"") | J87: =IF(O87=1,$G87,"") -> 0.12911356 | K87: =IF(P87=1,$G87,"") | L87: =SUM(M87:P87) -> 1 | O87: 1 | R87: =IF(SUM(M87:P87)=L87,"T","F") -> T
B88: AtR - C | C88: Com | D88: Structural | E88: Prakash C | F88: Master Plan - Site Development | G88: 0.014486093 | H88: =IF(M88=1,$G88,"") -> 0.014486093 | I88: =IF(N88=1,$G88,"") | J88: =IF(O88=1,$G88,"") | K88: =IF(P88=1,$G88,"") | L88: =SUM(M88:P88) -> 1 | M88: 1 | R88: =IF(SUM(M88:P88)=L88,"T","F") -> T
B89: AtR - C | C89: Com | D89: Structural | E89: Prakash C | F89: Master Plan - Site MEP | G89: 0.012071744 | H89: =IF(M89=1,$G89,"") -> 0.012071744 | I89: =IF(N89=1,$G89,"") | J89: =IF(O89=1,$G89,"") | K89: =IF(P89=1,$G89,"") | L89: =SUM(M89:P89) -> 1 | M89: 1 | R89: =IF(SUM(M89:P89)=L89,"T","F") -> T
B90: AtR - C | C90: Com | D90: MEP | F90: Package Release [Complete LoD 350 by Q1] | G90: =SUM(G91:G92) -> 0.16750548 | H90: =SUM(H91:H92) -> 0.16750548 | I90: =SUM(I91:I92) -> 0 | J90: =SUM(J91:J92) -> 0 | K90: =SUM(K91:K92) -> 0 | L90: =SUM(M90:P90) -> 2 | M90: =SUM(M91:M92) -> 2 | N90: =SUM(N91:N92) -> 0 | O90: =SUM(O91:O92) -> 0 | P90: =SUM(P91:P92) -> 0 | R90: =IF(SUM(M90:P90)=L90,"T","F") -> T
B91: AtR - C | C91: Com | D91: MEP | E91: Gagan | F91: Master Plan - Master Plan | G91: 0.038655112 | H91: =IF(M91=1,$G91,"") -> 0.038655112 | I91: =IF(N91=1,$G91,"") | J91: =IF(O91=1,$G91,"") | K91: =IF(P91=1,$G91,"") | L91: =SUM(M91:P91) -> 1 | M91: 1 | R91: =IF(SUM(M91:P91)=L91,"T","F") -> T
B92: AtR - C | C92: Com | D92: MEP | E92: Gagan | F92: Master Plan - Site MEP | G92: 0.12885037 | H92: =IF(M92=1,$G92,"") -> 0.12885037 | I92: =IF(N92=1,$G92,"") | J92: =IF(O92=1,$G92,"") | K92: =IF(P92=1,$G92,"") | L92: =SUM(M92:P92) -> 1 | M92: 1 | R92: =IF(SUM(M92:P92)=L92,"T","F") -> T
B93: TMD Ph2 | C93: Ph 2 | F93: Childern play area [Complete by Q2] | G93: - | H93: =SUM(H94) -> 0 | I93: =SUM(I94) -> 0 | J93: =SUM(J94) -> 0 | K93: =SUM(K94) -> 0 | L93: =SUM(M93:P93) -> 0 | M93: =SUM(M94) -> 0 | N93: =SUM(N94) -> 0 | O93: =SUM(O94) -> 0 | P93: =SUM(P94) -> 0 | R93: =IF(SUM(M93:P93)=L93,"T","F") -> T
B94: TMD Ph2 | C94: Ph 2 | F94: Childern play area | G94: -
B95: PoaRR-Res | C95: Res | F95: Package Release [Complete the project by Q1] | G95: =SUM(G96+G105+G109+G113) -> 3.7669915 | H95: =SUM(H96,H105,H109,H113) -> 3.7669915 | I95: =SUM(I96,I105,I109,I113) -> 0 | J95: =SUM(J96,J105,J109,J113) -> 0 | K95: =SUM(K96,K105,K109,K113) -> 0 | L95: =SUM(M95:P95) -> 15 | M95: =SUM(M96,M105,M109,M113) -> 15 | N95: =SUM(N96,N105,N109,N113) -> 0 | O95: =SUM(O96,O105,O109,O113) -> 0 | P95: =SUM(P96,P105,P109,P113) -> 0 | R95: =IF(SUM(M95:P95)=L95,"T","F") -> T
B96: PoaRR-Res | C96: Res | D96: Architecture | F96: Complete the project | G96: =SUM(G97:G104) -> 3.3659 | H96: =SUM(H97:H104) -> 3.3659 | I96: =SUM(I97:I104) -> 0 | J96: =SUM(J97:J104) -> 0 | K96: =SUM(K97:K104) -> 0 | L96: =SUM(M96:P96) -> 8 | M96: =SUM(M97:M104) -> 8 | N96: =SUM(N97:N104) -> 0 | O96: =SUM(O97:O104) -> 0 | P96: =SUM(P97:P104) -> 0 | R96: =IF(SUM(M96:P96)=L96,"T","F") -> T
B97: PoaRR-Res | C97: Res | D97: Architecture | E97: Saji A | F97: Villa Cluster 3 - All Levels | G97: 0.17 | H97: =IF(M97=1,$G97,"") -> 0.17 | I97: =IF(N97=1,$G97,"") | J97: =IF(O97=1,$G97,"") | K97: =IF(P97=1,$G97,"") | L97: =SUM(M97:P97) -> 1 | M97: 1 | R97: =IF(SUM(M97:P97)=L97,"T","F") -> T
B98: PoaRR-Res | C98: Res | D98: Architecture | E98: Saji A | F98: Villa Cluster 3 - Building Envelope and Common Areas | G98: 0.17 | H98: =IF(M98=1,$G98,"") -> 0.17 | I98: =IF(N98=1,$G98,"") | J98: =IF(O98=1,$G98,"") | K98: =IF(P98=1,$G98,"") | L98: =SUM(M98:P98) -> 1 | M98: 1 | R98: =IF(SUM(M98:P98)=L98,"T","F") -> T
B99: PoaRR-Res | C99: Res | D99: Architecture | E99: Saji A | F99: V40 Default and it's variants | G99: 1.18 | H99: =IF(M99=1,$G99,"") -> 1.18 | I99: =IF(N99=1,$G99,"") | J99: =IF(O99=1,$G99,"") | K99: =IF(P99=1,$G99,"") | L99: =SUM(M99:P99) -> 1 | M99: 1 | R99: =IF(SUM(M99:P99)=L99,"T","F") -> T
B100: PoaRR-Res | C100: Res | D100: Architecture | E100: Saji A | F100: ISS Building Envelope and Common Areas | G100: =10659000/10^7 -> 1.0659 | H100: =IF(M100=1,$G100,"") -> 1.0659 | I100: =IF(N100=1,$G100,"") | J100: =IF(O100=1,$G100,"") | K100: =IF(P100=1,$G100,"") | L100: =SUM(M100:P100) -> 1 | M100: 1 | R100: =IF(SUM(M100:P100)=L100,"T","F") -> T
B101: PoaRR-Res | C101: Res | D101: Architecture | E101: Saji A | F101: Residential - Site Development | G101: 0.45 | H101: =IF(M101=1,$G101,"") -> 0.45 | I101: =IF(N101=1,$G101,"") | J101: =IF(O101=1,$G101,"") | K101: =IF(P101=1,$G101,"") | L101: =SUM(M101:P101) -> 1 | M101: 1 | R101: =IF(SUM(M101:P101)=L101,"T","F") -> T
B102: PoaRR-Res | C102: Res | D102: Architecture | E102: Saji A | F102: Masterplan - Site MEP | G102: 0.15 | H102: =IF(M102=1,$G102,"") -> 0.15 | I102: =IF(N102=1,$G102,"") | J102: =IF(O102=1,$G102,"") | K102: =IF(P102=1,$G102,"") | L102: =SUM(M102:P102) -> 1 | M102: 1 | R102: =IF(SUM(M102:P102)=L102,"T","F") -> T
B103: PoaRR-Res | C103: Res | D103: Architecture | E103: Saji A | F103: Masterplan - Landscaping | G103: 0.15 | H103: =IF(M103=1,$G103,"") -> 0.15 | I103: =IF(N103=1,$G103,"") | J103: =IF(O103=1,$G103,"") | K103: =IF(P103=1,$G103,"") | L103: =SUM(M103:P103) -> 1 | M103: 1 | R103: =IF(SUM(M103:P103)=L103,"T","F") -> T
...

Sheet Smry
B4: Design Lead | D4: Project | F4: Phase | H4: Pkgs [2026] | I4: Q1 | J4: Q2 | K4: Q3 | L4: Q4 | N4: Billing [2026] | O4: Q1 | P4: Q2 | Q4: Q3 | R4: Q4
B8: Total Packages | H8: =SUM(I8+J8+K8+L8) -> 1143 | I8: =SUM(I10+I19+I62+I100+I110+I124+I140+I147+I155) -> 403 | J8: =SUM(J10+J19+J62+J100+J110+J124+J140+J147+J155) -> 235 | K8: =SUM(K10+K19+K62+K100+K110+K124+K140+K147+K155) -> 275 | L8: =SUM(L10+L19+L62+L100+L110+L124+L140+L147+L155) -> 230 | N8: =SUM(O8+P8+Q8+R8) -> 287.21484 | O8: =SUM(O10+O19+O62+O100+O110+O124+O140+O147+O155) -> 115.81945 | P8: =SUM(P10+P19+P62+P100+P110+P124+P140+P147+P155) -> 60.026291 | Q8: =SUM(Q10+Q19+Q62+Q100+Q110+Q124+Q140+Q147+Q155) -> 56.528406 | R8: =SUM(R10+R19+R62+R100+R110+R124+R140+R147+R155) -> 54.840694
B10: Saji A | H10: =SUM(I10:L10) -> 60 | I10: =SUM(I12:I17) -> 45 | J10: =SUM(J12:J17) -> 7 | K10: =SUM(K12:K17) -> 5 | L10: =SUM(L12:L17) -> 3 | N10: =SUM(O10:R10) -> 39.650772 | O10: =SUM(O12:O17) -> 12.655551 | P10: =SUM(P12:P17) -> 6.5577205 | Q10: =SUM(Q12:Q17) -> 8.83 | R10: =SUM(R12:R17) -> 11.6075
B12: Saji A | D12: AtR | F12: Ph 1, 2a, 2b | H12: =SUM(I12:L12) -> 2 | I12: =SUMIFS('Goals 2026'!M:M,'Goals 2026'!B:B,Smry!D12,'Goals 2026'!C:C,Smry!F12,'Goals 2026'!E:E,Smry!$B$10) -> 2 | J12: =SUMIFS('Goals 2026'!N:N,'Goals 2026'!B:B,Smry!D12,'Goals 2026'!C:C,Smry!F12,'Goals 2026'!E:E,Smry!$B$10) -> 0 | K12: =SUMIFS('Goals 2026'!O:O,'Goals 2026'!B:B,Smry!D12,'Goals 2026'!C:C,Smry!F12,'Goals 2026'!E:E,Smry!$B$10) -> 0 | L12: =SUMIFS('Goals 2026'!P:P,'Goals 2026'!B:B,Smry!D12,'Goals 2026'!C:C,Smry!F12,'Goals 2026'!E:E,Smry!$B$10) -> 0 | N12: =SUM(O12:R12) -> 0.31537704 | O12: =SUMIFS('Goals 2026'!H:H,'Goals 2026'!B:B,Smry!D12,'Goals 2026'!C:C,Smry!F12,'Goals 2026'!E:E,Smry!$B$10) -> 0.31537704 | P12: =SUMIFS('Goals 2026'!I:I,'Goals 2026'!B:B,Smry!D12,'Goals 2026'!C:C,Smry!F12,'Goals 2026'!E:E,Smry!$B$10) -> 0 | Q12: =SUMIFS('Goals 2026'!J:J,'Goals 2026'!B:B,Smry!D12,'Goals 2026'!C:C,Smry!F12,'Goals 2026'!E:E,Smry!$B$10) -> 0 | R12: =SUMIFS('Goals 2026'!K:K,'Goals 2026'!B:B,Smry!D12,'Goals 2026'!C:C,Smry!F12,'Goals 2026'!E:E,Smry!$B$10) -> 0
B13: Saji A | D13: AtR | F13: Ph 2c | H13: =SUM(I13:L13) -> 2 | I13: =SUMIFS('Goals 2026'!M:M,'Goals 2026'!B:B,Smry!D13,'Goals 2026'!C:C,Smry!F13,'Goals 2026'!E:E,Smry!$B$10) -> 2 | J13: =SUMIFS('Goals 2026'!N:N,'Goals 2026'!B:B,Smry!D13,'Goals 2026'!C:C,Smry!F13,'Goals 2026'!E:E,Smry!$B$10) -> 0 | K13: =SUMIFS('Goals 2026'!O:O,'Goals 2026'!B:B,Smry!D13,'Goals 2026'!C:C,Smry!F13,'Goals 2026'!E:E,Smry!$B$10) -> 0 | L13: =SUMIFS('Goals 2026'!P:P,'Goals 2026'!B:B,Smry!D13,'Goals 2026'!C:C,Smry!F13,'Goals 2026'!E:E,Smry!$B$10) -> 0 | N13: =SUM(O13:R13) -> 0.081654546 | O13: =SUMIFS('Goals 2026'!H:H,'Goals 2026'!B:B,Smry!D13,'Goals 2026'!C:C,Smry!F13,'Goals 2026'!E:E,Smry!$B$10) -> 0.081654546 | P13: =SUMIFS('Goals 2026'!I:I,'Goals 2026'!B:B,Smry!D13,'Goals 2026'!C:C,Smry!F13,'Goals 2026'!E:E,Smry!$B$10) -> 0 | Q13: =SUMIFS('Goals 2026'!J:J,'Goals 2026'!B:B,Smry!D13,'Goals 2026'!C:C,Smry!F13,'Goals 2026'!E:E,Smry!$B$10) -> 0 | R13: =SUMIFS('Goals 2026'!K:K,'Goals 2026'!B:B,Smry!D13,'Goals 2026'!C:C,Smry!F13,'Goals 2026'!E:E,Smry!$B$10) -> 0
B14: Saji A | D14: AtR | F14: Ph 3 | H14: =SUM(I14:L14) -> 19 | I14: =SUMIFS('Goals 2026'!M:M,'Goals 2026'!B:B,Smry!D14,'Goals 2026'!C:C,Smry!F14,'Goals 2026'!E:E,Smry!$B$10) -> 15 | J14: =SUMIFS('Goals 2026'!N:N,'Goals 2026'!B:B,Smry!D14,'Goals 2026'!C:C,Smry!F14,'Goals 2026'!E:E,Smry!$B$10) -> 4 | K14: =SUMIFS('Goals 2026'!O:O,'Goals 2026'!B:B,Smry!D14,'Goals 2026'!C:C,Smry!F14,'Goals 2026'!E:E,Smry!$B$10) -> 0 | L14: =SUMIFS('Goals 2026'!P:P,'Goals 2026'!B:B,Smry!D14,'Goals 2026'!C:C,Smry!F14,'Goals 2026'!E:E,Smry!$B$10) -> 0 | N14: =SUM(O14:R14) -> 2.2814903 | O14: =SUMIFS('Goals 2026'!H:H,'Goals 2026'!B:B,Smry!D14,'Goals 2026'!C:C,Smry!F14,'Goals 2026'!E:E,Smry!$B$10) -> 1.8087698 | P14: =SUMIFS('Goals 2026'!I:I,'Goals 2026'!B:B,Smry!D14,'Goals 2026'!C:C,Smry!F14,'Goals 2026'!E:E,Smry!$B$10) -> 0.47272049 | Q14: =SUMIFS('Goals 2026'!J:J,'Goals 2026'!B:B,Smry!D14,'Goals 2026'!C:C,Smry!F14,'Goals 2026'!E:E,Smry!$B$10) -> 0 | R14: =SUMIFS('Goals 2026'!K:K,'Goals 2026'!B:B,Smry!D14,'Goals 2026'!C:C,Smry!F14,'Goals 2026'!E:E,Smry!$B$10) -> 0
B15: Saji A | D15: PoaRR-Res | F15: Res | H15: =SUM(I15:L15) -> 8 | I15: =SUMIFS('Goals 2026'!M:M,'Goals 2026'!B:B,Smry!D15,'Goals 2026'!C:C,Smry!F15,'Goals 2026'!E:E,Smry!$B$10) -> 8 | J15: =SUMIFS('Goals 2026'!N:N,'Goals 2026'!B:B,Smry!D15,'Goals 2026'!C:C,Smry!F15,'Goals 2026'!E:E,Smry!$B$10) -> 0 | K15: =SUMIFS('Goals 2026'!O:O,'Goals 2026'!B:B,Smry!D15,'Goals 2026'!C:C,Smry!F15,'Goals 2026'!E:E,Smry!$B$10) -> 0 | L15: =SUMIFS('Goals 2026'!P:P,'Goals 2026'!B:B,Smry!D15,'Goals 2026'!C:C,Smry!F15,'Goals 2026'!E:E,Smry!$B$10) -> 0 | N15: =SUM(O15:R15) -> 3.3659 | O15: =SUMIFS('Goals 2026'!H:H,'Goals 2026'!B:B,Smry!D15,'Goals 2026'!C:C,Smry!F15,'Goals 2026'!E:E,Smry!$B$10) -> 3.3659 | P15: =SUMIFS('Goals 2026'!I:I,'Goals 2026'!B:B,Smry!D15,'Goals 2026'!C:C,Smry!F15,'Goals 2026'!E:E,Smry!$B$10) -> 0 | Q15: =SUMIFS('Goals 2026'!J:J,'Goals 2026'!B:B,Smry!D15,'Goals 2026'!C:C,Smry!F15,'Goals 2026'!E:E,Smry!$B$10) -> 0 | R15: =SUMIFS('Goals 2026'!K:K,'Goals 2026'!B:B,Smry!D15,'Goals 2026'!C:C,Smry!F15,'Goals 2026'!E:E,Smry!$B$10) -> 0
B16: Saji A | D16: PoaRR-T08 | F16: T08 | H16: =SUM(I16:L16) -> 23 | I16: =SUMIFS('Goals 2026'!M:M,'Goals 2026'!B:B,Smry!D16,'Goals 2026'!C:C,Smry!F16,'Goals 2026'!E:E,Smry!$B$10) -> 18 | J16: =SUMIFS('Goals 2026'!N:N,'Goals 2026'!B:B,Smry!D16,'Goals 2026'!C:C,Smry!F16,'Goals 2026'!E:E,Smry!$B$10) -> 2 | K16: =SUMIFS('Goals 2026'!O:O,'Goals 2026'!B:B,Smry!D16,'Goals 2026'!C:C,Smry!F16,'Goals 2026'!E:E,Smry!$B$10) -> 3 | L16: =SUMIFS('Goals 2026'!P:P,'Goals 2026'!B:B,Smry!D16,'Goals 2026'!C:C,Smry!F16,'Goals 2026'!E:E,Smry!$B$10) -> 0 | N16: =SUM(O16:R16) -> 7.30385 | O16: =SUMIFS('Goals 2026'!H:H,'Goals 2026'!B:B,Smry!D16,'Goals 2026'!C:C,Smry!F16,'Goals 2026'!E:E,Smry!$B$10) -> 7.08385 | P16: =SUMIFS('Goals 2026'!I:I,'Goals 2026'!B:B,Smry!D16,'Goals 2026'!C:C,Smry!F16,'Goals 2026'!E:E,Smry!$B$10) -> 0.12 | Q16: =SUMIFS('Goals 2026'!J:J,'Goals 2026'!B:B,Smry!D16,'Goals 2026'!C:C,Smry!F16,'Goals 2026'!E:E,Smry!$B$10) -> 0.1 | R16: =SUMIFS('Goals 2026'!K:K,'Goals 2026'!B:B,Smry!D16,'Goals 2026'!C:C,Smry!F16,'Goals 2026'!E:E,Smry!$B$10) -> 0
B17: Saji A | D17: TR Mills | F17: TR Mills | H17: =SUM(I17:L17) -> 6 | I17: =SUMIFS('Goals 2026'!M:M,'Goals 2026'!B:B,Smry!D17,'Goals 2026'!C:C,Smry!F17,'Goals 2026'!E:E,Smry!$B$10) -> 0 | J17: =SUMIFS('Goals 2026'!N:N,'Goals 2026'!B:B,Smry!D17,'Goals 2026'!C:C,Smry!F17,'Goals 2026'!E:E,Smry!$B$10) -> 1 | K17: =SUMIFS('Goals 2026'!O:O,'Goals 2026'!B:B,Smry!D17,'Goals 2026'!C:C,Smry!F17,'Goals 2026'!E:E,Smry!$B$10) -> 2 | L17: =SUMIFS('Goals 2026'!P:P,'Goals 2026'!B:B,Smry!D17,'Goals 2026'!C:C,Smry!F17,'Goals 2026'!E:E,Smry!$B$10) -> 3 | N17: =SUM(O17:R17) -> 26.3025 | O17: =SUMIFS('Goals 2026'!H:H,'Goals 2026'!B:B,Smry!D17,'Goals 2026'!C:C,Smry!F17,'Goals 2026'!E:E,Smry!$B$10) -> 0 | P17: =SUMIFS('Goals 2026'!I:I,'Goals 2026'!B:B,Smry!D17,'Goals 2026'!C:C,Smry!F17,'Goals 2026'!E:E,Smry!$B$10) -> 5.965 | Q17: =SUMIFS('Goals 2026'!J:J,'Goals 2026'!B:B,Smry!D17,'Goals 2026'!C:C,Smry!F17,'Goals 2026'!E:E,Smry!$B$10) -> 8.73 | R17: =SUMIFS('Goals 2026'!K:K,'Goals 2026'!B:B,Smry!D17,'Goals 2026'!C:C,Smry!F17,'Goals 2026'!E:E,Smry!$B$10) -> 11.6075
B19: Prakash C | H19: =SUM(I19:L19) -> 309 | I19: =SUM(I21:I60) -> 114 | J19: =SUM(J21:J60) -> 64 | K19: =SUM(K21:K60) -> 72 | L19: =SUM(L21:L60) -> 59 | N19: =SUM(O19:R19) -> 54.59763 | O19: =SUM(O21:O60) -> 21.01135 | P19: =SUM(P21:P60) -> 12.567651 | Q19: =SUM(Q21:Q60) -> 10.472304 | R19: =SUM(R21:R60) -> 10.546325
B21: Prakash C | D21: AtR | F21: Ph 1, 2a, 2b | H21: =SUM(I21:L21) -> 1 | I21: =SUMIFS('Goals 2026'!M:M,'Goals 2026'!B:B,Smry!D21,'Goals 2026'!C:C,Smry!F21,'Goals 2026'!E:E,Smry!$B$19) -> 1 | J21: =SUMIFS('Goals 2026'!N:N,'Goals 2026'!B:B,Smry!D21,'Goals 2026'!C:C,Smry!F21,'Goals 2026'!E:E,Smry!$B$19) -> 0 | K21: =SUMIFS('Goals 2026'!O:O,'Goals 2026'!B:B,Smry!D21,'Goals 2026'!C:C,Smry!F21,'Goals 2026'!E:E,Smry!$B$19) -> 0 | L21: =SUMIFS('Goals 2026'!P:P,'Goals 2026'!B:B,Smry!D21,'Goals 2026'!C:C,Smry!F21,'Goals 2026'!E:E,Smry!$B$19) -> 0 | N21: =SUM(O21:R21) -> 0.0052867303 | O21: =SUMIFS('Goals 2026'!H:H,'Goals 2026'!B:B,Smry!D21,'Goals 2026'!C:C,Smry!F21,'Goals 2026'!E:E,Smry!$B$19) -> 0.0052867303 | P21: =SUMIFS('Goals 2026'!I:I,'Goals 2026'!B:B,Smry!D21,'Goals 2026'!C:C,Smry!F21,'Goals 2026'!E:E,Smry!$B$19) -> 0 | Q21: =SUMIFS('Goals 2026'!J:J,'Goals 2026'!B:B,Smry!D21,'Goals 2026'!C:C,Smry!F21,'Goals 2026'!E:E,Smry!$B$19) -> 0 | R21: =SUMIFS('Goals 2026'!K:K,'Goals 2026'!B:B,Smry!D21,'Goals 2026'!C:C,Smry!F21,'Goals 2026'!E:E,Smry!$B$19) -> 0
B22: Prakash C | D22: AtR | F22: Ph 2c | H22: =SUM(I22:L22) -> 2 | I22: =SUMIFS('Goals 2026'!M:M,'Goals 2026'!B:B,Smry!D22,'Goals 2026'!C:C,Smry!F22,'Goals 2026'!E:E,Smry!$B$19) -> 2 | J22: =SUMIFS('Goals 2026'!N:N,'Goals 2026'!B:B,Smry!D22,'Goals 2026'!C:C,Smry!F22,'Goals 2026'!E:E,Smry!$B$19) -> 0 | K22: =SUMIFS('Goals 2026'!O:O,'Goals 2026'!B:B,Smry!D22,'Goals 2026'!C:C,Smry!F22,'Goals 2026'!E:E,Smry!$B$19) -> 0 | L22: =SUMIFS('Goals 2026'!P:P,'Goals 2026'!B:B,Smry!D22,'Goals 2026'!C:C,Smry!F22,'Goals 2026'!E:E,Smry!$B$19) -> 0 | N22: =SUM(O22:R22) -> 0.016064217 | O22: =SUMIFS('Goals 2026'!H:H,'Goals 2026'!B:B,Smry!D22,'Goals 2026'!C:C,Smry!F22,'Goals 2026'!E:E,Smry!$B$19) -> 0.016064217 | P22: =SUMIFS('Goals 2026'!I:I,'Goals 2026'!B:B,Smry!D22,'Goals 2026'!C:C,Smry!F22,'Goals 2026'!E:E,Smry!$B$19) -> 0 | Q22: =SUMIFS('Goals 2026'!J:J,'Goals 2026'!B:B,Smry!D22,'Goals 2026'!C:C,Smry!F22,'Goals 2026'!E:E,Smry!$B$19) -> 0 | R22: =SUMIFS('Goals 2026'!K:K,'Goals 2026'!B:B,Smry!D22,'Goals 2026'!C:C,Smry!F22,'Goals 2026'!E:E,Smry!$B$19) -> 0
B23: Prakash C | D23: AtR | F23: Ph 3 | H23: =SUM(I23:L23) -> 19 | I23: =SUMIFS('Goals 2026'!M:M,'Goals 2026'!B:B,Smry!D23,'Goals 2026'!C:C,Smry!F23,'Goals 2026'!E:E,Smry!$B$19) -> 15 | J23: =SUMIFS('Goals 2026'!N:N,'Goals 2026'!B:B,Smry!D23,'Goals 2026'!C:C,Smry!F23,'Goals 2026'!E:E,Smry!$B$19) -> 4 | K23: =SUMIFS('Goals 2026'!O:O,'Goals 2026'!B:B,Smry!D23,'Goals 2026'!C:C,Smry!F23,'Goals 2026'!E:E,Smry!$B$19) -> 0 | L23: =SUMIFS('Goals 2026'!P:P,'Goals 2026'!B:B,Smry!D23,'Goals 2026'!C:C,Smry!F23,'Goals 2026'!E:E,Smry!$B$19) -> 0 | N23: =SUM(O23:R23) -> 0.43466801 | O23: =SUMIFS('Goals 2026'!H:H,'Goals 2026'!B:B,Smry!D23,'Goals 2026'!C:C,Smry!F23,'Goals 2026'!E:E,Smry!$B$19) -> 0.35597209 | P23: =SUMIFS('Goals 2026'!I:I,'Goals 2026'!B:B,Smry!D23,'Goals 2026'!C:C,Smry!F23,'Goals 2026'!E:E,Smry!$B$19) -> 0.07869592 | Q23: =SUMIFS('Goals 2026'!J:J,'Goals 2026'!B:B,Smry!D23,'Goals 2026'!C:C,Smry!F23,'Goals 2026'!E:E,Smry!$B$19) -> 0 | R23: =SUMIFS('Goals 2026'!K:K,'Goals 2026'!B:B,Smry!D23,'Goals 2026'!C:C,Smry!F23,'Goals 2026'!E:E,Smry!$B$19) -> 0
B24: Prakash C | D24: AtR - C | F24: Com | H24: =SUM(I24:L24) -> 6 | I24: =SUMIFS('Goals 2026'!M:M,'Goals 2026'!B:B,Smry!D24,'Goals 2026'!C:C,Smry!F24,'Goals 2026'!E:E,Smry!$B$19) -> 4 | J24: =SUMIFS('Goals 2026'!N:N,'Goals 2026'!B:B,Smry!D24,'Goals 2026'!C:C,Smry!F24,'Goals 2026'!E:E,Smry!$B$19) -> 1 | K24: =SUMIFS('Goals 2026'!O:O,'Goals 2026'!B:B,Smry!D24,'Goals 2026'!C:C,Smry!F24,'Goals 2026'!E:E,Smry!$B$19) -> 1 | L24: =SUMIFS('Goals 2026'!P:P,'Goals 2026'!B:B,Smry!D24,'Goals 2026'!C:C,Smry!F24,'Goals 2026'!E:E,Smry!$B$19) -> 0 | N24: =SUM(O24:R24) -> 0.80123917 | O24: =SUMIFS('Goals 2026'!H:H,'Goals 2026'!B:B,Smry!D24,'Goals 2026'!C:C,Smry!F24,'Goals 2026'!E:E,Smry!$B$19) -> 0.4138985 | P24: =SUMIFS('Goals 2026'!I:I,'Goals 2026'!B:B,Smry!D24,'Goals 2026'!C:C,Smry!F24,'Goals 2026'!E:E,Smry!$B$19) -> 0.25822711 | Q24: =SUMIFS('Goals 2026'!J:J,'Goals 2026'!B:B,Smry!D24,'Goals 2026'!C:C,Smry!F24,'Goals 2026'!E:E,Smry!$B$19) -> 0.12911356 | R24: =SUMIFS('Goals 2026'!K:K,'Goals 2026'!B:B,Smry!D24,'Goals 2026'!C:C,Smry!F24,'Goals 2026'!E:E,Smry!$B$19) -> 0
B25: Prakash C | D25: PoaRR-Res | F25: Res | H25: =SUM(I25:L25) -> 3 | I25: =SUMIFS('Goals 2026'!M:M,'Goals 2026'!B:B,Smry!D25,'Goals 2026'!C:C,Smry!F25,'Goals 2026'!E:E,Smry!$B$19) -> 3 | J25: =SUMIFS('Goals 2026'!N:N,'Goals 2026'!B:B,Smry!D25,'Goals 2026'!C:C,Smry!F25,'Goals 2026'!E:E,Smry!$B$19) -> 0 | K25: =SUMIFS('Goals 2026'!O:O,'Goals 2026'!B:B,Smry!D25,'Goals 2026'!C:C,Smry!F25,'Goals 2026'!E:E,Smry!$B$19) -> 0 | L25: =SUMIFS('Goals 2026'!P:P,'Goals 2026'!B:B,Smry!D25,'Goals 2026'!C:C,Smry!F25,'Goals 2026'!E:E,Smry!$B$19) -> 0 | N25: =SUM(O25:R25) -> 0.36 | O25: =SUMIFS('Goals 2026'!H:H,'Goals 2026'!B:B,Smry!D25,'Goals 2026'!C:C,Smry!F25,'Goals 2026'!E:E,Smry!$B$19) -> 0.36 | P25: =SUMIFS('Goals 2026'!I:I,'Goals 2026'!B:B,Smry!D25,'Goals 2026'!C:C,Smry!F25,'Goals 2026'!E:E,Smry!$B$19) -> 0 | Q25: =SUMIFS('Goals 2026'!J:J,'Goals 2026'!B:B,Smry!D25,'Goals 2026'!C:C,Smry!F25,'Goals 2026'!E:E,Smry!$B$19) -> 0 | R25: =SUMIFS('Goals 2026'!K:K,'Goals 2026'!B:B,Smry!D25,'Goals 2026'!C:C,Smry!F25,'Goals 2026'!E:E,Smry!$B$19) -> 0
B26: Prakash C | D26: PoaRR-T08 | F26: T08 | H26: =SUM(I26:L26) -> 8 | I26: =SUMIFS('Goals 2026'!M:M,'Goals 2026'!B:B,Smry!D26,'Goals 2026'!C:C,Smry!F26,'Goals 2026'!E:E,Smry!$B$19) -> 8 | J26: =SUMIFS('Goals 2026'!N:N,'Goals 2026'!B:B,Smry!D26,'Goals 2026'!C:C,Smry!F26,'Goals 2026'!E:E,Smry!$B$19) -> 0 | K26: =SUMIFS('Goals 2026'!O:O,'Goals 2026'!B:B,Smry!D26,'Goals 2026'!C:C,Smry!F26,'Goals 2026'!E:E,Smry!$B$19) -> 0 | L26: =SUMIFS('Goals 2026'!P:P,'Goals 2026'!B:B,Smry!D26,'Goals 2026'!C:C,Smry!F26,'Goals 2026'!E:E,Smry!$B$19) -> 0 | N26: =SUM(O26:R26) -> 2.1 | O26: =SUMIFS('Goals 2026'!H:H,'Goals 2026'!B:B,Smry!D26,'Goals 2026'!C:C,Smry!F26,'Goals 2026'!E:E,Smry!$B$19) -> 2.1 | P26: =SUMIFS('Goals 2026'!I:I,'Goals 2026'!B:B,Smry!D26,'Goals 2026'!C:C,Smry!F26,'Goals 2026'!E:E,Smry!$B$19) -> 0 | Q26: =SUMIFS('Goals 2026'!J:J,'Goals 2026'!B:B,Smry!D26,'Goals 2026'!C:C,Smry!F26,'Goals 2026'!E:E,Smry!$B$19) -> 0 | R26: =SUMIFS('Goals 2026'!K:K,'Goals 2026'!B:B,Smry!D26,'Goals 2026'!C:C,Smry!F26,'Goals 2026'!E:E,Smry!$B$19) -> 0
B27: Prakash C | D27: ITQE-Ph1 | F27: Ph 1 | H27: =SUM(I27:L27) -> 3 | I27: =SUMIFS('Goals 2026'!M:M,'Goals 2026'!B:B,Smry!D27,'Goals 2026'!C:C,Smry!F27,'Goals 2026'!E:E,Smry!$B$19) -> 3 | J27: =SUMIFS('Goals 2026'!N:N,'Goals 2026'!B:B,Smry!D27,'Goals 2026'!C:C,Smry!F27,'Goals 2026'!E:E,Smry!$B$19) -> 0 | K27: =SUMIFS('Goals 2026'!O:O,'Goals 2026'!B:B,Smry!D27,'Goals 2026'!C:C,Smry!F27,'Goals 2026'!E:E,Smry!$B$19) -> 0 | L27: =SUMIFS('Goals 2026'!P:P,'Goals 2026'!B:B,Smry!D27,'Goals 2026'!C:C,Smry!F27,'Goals 2026'!E:E,Smry!$B$19) -> 0 | N27: =SUM(O27:R27) -> 0.084072168 | O27: =SUMIFS('Goals 2026'!H:H,'Goals 2026'!B:B,Smry!D27,'Goals 2026'!C:C,Smry!F27,'Goals 2026'!E:E,Smry!$B$19) -> 0.084072168 | P27: =SUMIFS('Goals 2026'!I:I,'Goals 2026'!B:B,Smry!D27,'Goals 2026'!C:C,Smry!F27,'Goals 2026'!E:E,Smry!$B$19) -> 0 | Q27: =SUMIFS('Goals 2026'!J:J,'Goals 2026'!B:B,Smry!D27,'Goals 2026'!C:C,Smry!F27,'Goals 2026'!E:E,Smry!$B$19) -> 0 | R27: =SUMIFS('Goals 2026'!K:K,'Goals 2026'!B:B,Smry!D27,'Goals 2026'!C:C,Smry!F27,'Goals 2026'!E:E,Smry!$B$19) -> 0
B28: Prakash C | D28: ITQE-Ph2a | F28: Ph 2a | H28: =SUM(I28:L28) -> 3 | I28: =SUMIFS('Goals 2026'!M:M,'Goals 2026'!B:B,Smry!D28,'Goals 2026'!C:C,Smry!F28,'Goals 2026'!E:E,Smry!$B$19) -> 3 | J28: =SUMIFS('Goals 2026'!N:N,'Goals 2026'!B:B,Smry!D28,'Goals 2026'!C:C,Smry!F28,'Goals 2026'!E:E,Smry!$B$19) -> 0 | K28: =SUMIFS('Goals 2026'!O:O,'Goals 2026'!B:B,Smry!D28,'Goals 2026'!C:C,Smry!F28,'Goals 2026'!E:E,Smry!$B$19) -> 0 | L28: =SUMIFS('Goals 2026'!P:P,'Goals 2026'!B:B,Smry!D28,'Goals 2026'!C:C,Smry!F28,'Goals 2026'!E:E,Smry!$B$19) -> 0 | N28: =SUM(O28:R28) -> 0.16918995 | O28: =SUMIFS('Goals 2026'!H:H,'Goals 2026'!B:B,Smry!D28,'Goals 2026'!C:C,Smry!F28,'Goals 2026'!E:E,Smry!$B$19) -> 0.16918995 | P28: =SUMIFS('Goals 2026'!I:I,'Goals 2026'!B:B,Smry!D28,'Goals 2026'!C:C,Smry!F28,'Goals 2026'!E:E,Smry!$B$19) -> 0 | Q28: =SUMIFS('Goals 2026'!J:J,'Goals 2026'!B:B,Smry!D28,'Goals 2026'!C:C,Smry!F28,'Goals 2026'!E:E,Smry!$B$19) -> 0 | R28: =SUMIFS('Goals 2026'!K:K,'Goals 2026'!B:B,Smry!D28,'Goals 2026'!C:C,Smry!F28,'Goals 2026'!E:E,Smry!$B$19) -> 0
B29: Prakash C | D29: ITQE-Ph2b | F29: Ph 2b | H29: =SUM(I29:L29) -> 16 | I29: =SUMIFS('Goals 2026'!M:M,'Goals 2026'!B:B,Smry!D29,'Goals 2026'!C:C,Smry!F29,'Goals 2026'!E:E,Smry!$B$19) -> 11 | J29: =SUMIFS('Goals 2026'!N:N,'Goals 2026'!B:B,Smry!D29,'Goals 2026'!C:C,Smry!F29,'Goals 2026'!E:E,Smry!$B$19) -> 3 | K29: =SUMIFS('Goals 2026'!O:O,'Goals 2026'!B:B,Smry!D29,'Goals 2026'!C:C,Smry!F29,'Goals 2026'!E:E,Smry!$B$19) -> 2 | L29: =SUMIFS('Goals 2026'!P:P,'Goals 2026'!B:B,Smry!D29,'Goals 2026'!C:C,Smry!F29,'Goals 2026'!E:E,Smry!$B$19) -> 0 | N29: =SUM(O29:R29) -> 1.397 | O29: =SUMIFS('Goals 2026'!H:H,'Goals 2026'!B:B,Smry!D29,'Goals 2026'!C:C,Smry!F29,'Goals 2026'!E:E,Smry!$B$19) -> 1.12 | P29: =SUMIFS('Goals 2026'!I:I,'Goals 2026'!B:B,Smry!D29,'Goals 2026'!C:C,Smry!F29,'Goals 2026'!E:E,Smry!$B$19) -> 0.27 | Q29: =SUMIFS('Goals 2026'!J:J,'Goals 2026'!B:B,Smry!D29,'Goals 2026'!C:C,Smry!F29,'Goals 2026'!E:E,Smry!$B$19) -> 0.007 | R29: =SUMIFS('Goals 2026'!K:K,'Goals 2026'!B:B,Smry!D29,'Goals 2026'!C:C,Smry!F29,'Goals 2026'!E:E,Smry!$B$19) -> 0
B30: Prakash C | D30: ItQE-Ph2c [T9] | F30: Ph 2c | H30: =SUM(I30:L30) -> 9 | I30: =SUMIFS('Goals 2026'!M:M,'Goals 2026'!B:B,Smry!D30,'Goals 2026'!C:C,Smry!F30,'Goals 2026'!E:E,Smry!$B$19) -> 4 | J30: =SUMIFS('Goals 2026'!N:N,'Goals 2026'!B:B,Smry!D30,'Goals 2026'!C:C,Smry!F30,'Goals 2026'!E:E,Smry!$B$19) -> 3 | K30: =SUMIFS('Goals 2026'!O:O,'Goals 2026'!B:B,Smry!D30,'Goals 2026'!C:C,Smry!F30,'Goals 2026'!E:E,Smry!$B$19) -> 2 | L30: =SUMIFS('Goals 2026'!P:P,'Goals 2026'!B:B,Smry!D30,'Goals 2026'!C:C,Smry!F30,'Goals 2026'!E:E,Smry!$B$19) -> 0 | N30: =SUM(O30:R30) -> 0.57936247 | O30: =SUMIFS('Goals 2026'!H:H,'Goals 2026'!B:B,Smry!D30,'Goals 2026'!C:C,Smry!F30,'Goals 2026'!E:E,Smry!$B$19) -> 0.28480034 | P30: =SUMIFS('Goals 2026'!I:I,'Goals 2026'!B:B,Smry!D30,'Goals 2026'!C:C,Smry!F30,'Goals 2026'!E:E,Smry!$B$19) -> 0.17656641 | Q30: =SUMIFS('Goals 2026'!J:J,'Goals 2026'!B:B,Smry!D30,'Goals 2026'!C:C,Smry!F30,'Goals 2026'!E:E,Smry!$B$19) -> 0.11799572 | R30: =SUMIFS('Goals 2026'!K:K,'Goals 2026'!B:B,Smry!D30,'Goals 2026'!C:C,Smry!F30,'Goals 2026'!E:E,Smry!$B$19) -> 0
B31: Prakash C | D31: ItQE-Ph3a [T10-12 & 31 Villas] | F31: Ph 3a | H31: =SUM(I31:L31) -> 26 | I31: =SUMIFS('Goals 2026'!M:M,'Goals 2026'!B:B,Smry!D31,'Goals 2026'!C:C,Smry!F31,'Goals 2026'!E:E,Smry!$B$19) -> 2 | J31: =SUMIFS('Goals 2026'!N:N,'Goals 2026'!B:B,Smry!D31,'Goals 2026'!C:C,Smry!F31,'Goals 2026'!E:E,Smry!$B$19) -> 4 | K31: =SUMIFS('Goals 2026'!O:O,'Goals 2026'!B:B,Smry!D31,'Goals 2026'!C:C,Smry!F31,'Goals 2026'!E:E,Smry!$B$19) -> 11 | L31: =SUMIFS('Goals 2026'!P:P,'Goals 2026'!B:B,Smry!D31,'Goals 2026'!C:C,Smry!F31,'Goals 2026'!E:E,Smry!$B$19) -> 9 | N31: =SUM(O31:R31) -> 6.0390319 | O31: =SUMIFS('Goals 2026'!H:H,'Goals 2026'!B:B,Smry!D31,'Goals 2026'!C:C,Smry!F31,'Goals 2026'!E:E,Smry!$B$19) -> 3.2578975 | P31: =SUMIFS('Goals 2026'!I:I,'Goals 2026'!B:B,Smry!D31,'Goals 2026'!C:C,Smry!F31,'Goals 2026'!E:E,Smry!$B$19) -> 0.61867009 | Q31: =SUMIFS('Goals 2026'!J:J,'Goals 2026'!B:B,Smry!D31,'Goals 2026'!C:C,Smry!F31,'Goals 2026'!E:E,Smry!$B$19) -> 1.2870246 | R31: =SUMIFS('Goals 2026'!K:K,'Goals 2026'!B:B,Smry!D31,'Goals 2026'!C:C,Smry!F31,'Goals 2026'!E:E,Smry!$B$19) -> 0.87543981
B32: Prakash C | D32: ITQE-T05 | F32: T05 | H32: =SUM(I32:L32) -> 1 | I32: =SUMIFS('Goals 2026'!M:M,'Goals 2026'!B:B,Smry!D32,'Goals 2026'!C:C,Smry!F32,'Goals 2026'!E:E,Smry!$B$19) -> 0 | J32: =SUMIFS('Goals 2026'!N:N,'Goals 2026'!B:B,Smry!D32,'Goals 2026'!C:C,Smry!F32,'Goals 2026'!E:E,Smry!$B$19) -> 1 | K32: =SUMIFS('Goals 2026'!O:O,'Goals 2026'!B:B,Smry!D32,'Goals 2026'!C:C,Smry!F32,'Goals 2026'!E:E,Smry!$B$19) -> 0 | L32: =SUMIFS('Goals 2026'!P:P,'Goals 2026'!B:B,Smry!D32,'Goals 2026'!C:C,Smry!F32,'Goals 2026'!E:E,Smry!$B$19) -> 0 | N32: =SUM(O32:R32) -> 0.04 | O32: =SUMIFS('Goals 2026'!H:H,'Goals 2026'!B:B,Smry!D32,'Goals 2026'!C:C,Smry!F32,'Goals 2026'!E:E,Smry!$B$19) -> 0 | P32: =SUMIFS('Goals 2026'!I:I,'Goals 2026'!B:B,Smry!D32,'Goals 2026'!C:C,Smry!F32,'Goals 2026'!E:E,Smry!$B$19) -> 0.04 | Q32: =SUMIFS('Goals 2026'!J:J,'Goals 2026'!B:B,Smry!D32,'Goals 2026'!C:C,Smry!F32,'Goals 2026'!E:E,Smry!$B$19) -> 0 | R32: =SUMIFS('Goals 2026'!K:K,'Goals 2026'!B:B,Smry!D32,'Goals 2026'!C:C,Smry!F32,'Goals 2026'!E:E,Smry!$B$19) -> 0
... B60: Prakash C | D60: DonaPaula | F60: DP | H60: =SUM(I60:L60) -> 26 | I60: =SUMIFS('Goals 2026'!M:M,'Goals 2026'!B:B,Smry!D60,'Goals 2026'!C:C,Smry!F60,'Goals 2026'!E:E,Smry!$B$19) -> 2 | J60: =SUMIFS('Goals 2026'!N:N,'Goals 2026'!B:B,Smry!D60,'Goals 2026'!C:C,Smry!F60,'Goals 2026'!E:E,Smry!$B$19) -> 1 | K60: =SUMIFS('Goals 2026'!O:O,'Goals 2026'!B:B,Smry!D60,'Goals 2026'!C:C,Smry!F60,'Goals 2026'!E:E,Smry!$B$19) -> 8 | L60: =SUMIFS('Goals 2026'!P:P,'Goals 2026'!B:B,Smry!D60,'Goals 2026'!C:C,Smry!F60,'Goals 2026'!E:E,Smry!$B$19) -> 15 | N60: =SUM(O60:R60) -> 1.3982982 | O60: =SUMIFS('Goals 2026'!H:H,'Goals 2026'!B:B,Smry!D60,'Goals 2026'!C:C,Smry!F60,'Goals 2026'!E:E,Smry!$B$19) -> 0.62984501 | P60: =SUMIFS('Goals 2026'!I:I,'Goals 2026'!B:B,Smry!D60,'Goals 2026'!C:C,Smry!F60,'Goals 2026'!E:E,Smry!$B$19) -> 0.09 | Q60: =SUMIFS('Goals 2026'!J:J,'Goals 2026'!B:B,Smry!D60,'Goals 2026'!C:C,Smry!F60,'Goals 2026'!E:E,Smry!$B$19) -> 0.32685348 | R60: =SUMIFS('Goals 2026'!K:K,'Goals 2026'!B:B,Smry!D60,'Goals 2026'!C:C,Smry!F60,'Goals 2026'!E:E,Smry!$B$19) -> 0.35159975
B62: Gagan | H62: =SUM(I62:L62) -> 436 | I62: =SUM(I64:I98) -> 127 | J62: =SUM(J64:J98) -> 92 | K62: =SUM(K64:K98) -> 122 | L62: =SUM(L64:L98) -> 95 | N62: =SUM(O62:R62) -> 64.837967 | O62: =SUM(O64:O98) -> 18.674601 | P62: =SUM(P64:P98) -> 11.051107 | Q62: =SUM(Q64:Q98) -> 19.8534 | R62: =SUM(R64:R98) -> 15.258859
B64: Gagan | D64: AtR | F64: Ph 2c | H64: =SUM(I64:L64) -> 1 | I64: =SUMIFS('Goals 2026'!M:M,'Goals 2026'!B:B,Smry!D64,'Goals 2026'!C:C,Smry!F64,'Goals 2026'!E:E,Smry!$B$62) -> 1 | J64: =SUMIFS('Goals 2026'!N:N,'Goals 2026'!B:B,Smry!D64,'Goals 2026'!C:C,Smry!F64,'Goals 2026'!E:E,Smry!$B$62) -> 0 | K64: =SUMIFS('Goals 2026'!O:O,'Goals 2026'!B:B,Smry!D64,'Goals 2026'!C:C,Smry!F64,'Goals 2026'!E:E,Smry!$B$62) -> 0 | L64: =SUMIFS('Goals 2026'!P:P,'Goals 2026'!B:B,Smry!D64,'Goals 2026'!C:C,Smry!F64,'Goals 2026'!E:E,Smry!$B$62) -> 0 | N64: =SUM(O64:R64) -> 0.014336873 | O64: =SUMIFS('Goals 2026'!H:H,'Goals 2026'!B:B,Smry!D64,'Goals 2026'!C:C,Smry!F64,'Goals 2026'!E:E,Smry!$B$62) -> 0.014336873 | P64: =SUMIFS('Goals 2026'!I:I,'Goals 2026'!B:B,Smry!D64,'Goals 2026'!C:C,Smry!F64,'Goals 2026'!E:E,Smry!$B$62) -> 0 | Q64: =SUMIFS('Goals 2026'!J:J,'Goals 2026'!B:B,Smry!D64,'Goals 2026'!C:C,Smry!F64,'Goals 2026'!E:E,Smry!$B$62) -> 0 | R64: =SUMIFS('Goals 2026'!K:K,'Goals 2026'!B:B,Smry!D64,'Goals 2026'!C:C,Smry!F64,'Goals 2026'!E:E,Smry!$B$62) -> 0
B65: Gagan | D65: AtR | F65: Ph 3 | H65: =SUM(I65:L65) -> 15 | I65: =SUMIFS('Goals 2026'!M:M,'Goals 2026'!B:B,Smry!D65,'Goals 2026'!C:C,Smry!F65,'Goals 2026'!E:E,Smry!$B$62) -> 12 | J65: =SUMIFS('Goals 2026'!N:N,'Goals 2026'!B:B,Smry!D65,'Goals 2026'!C:C,Smry!F65,'Goals 2026'!E:E,Smry!$B$62) -> 3 | K65: =SUMIFS('Goals 2026'!O:O,'Goals 2026'!B:B,Smry!D65,'Goals 2026'!C:C,Smry!F65,'Goals 2026'!E:E,Smry!$B$62) -> 0 | L65: =SUMIFS('Goals 2026'!P:P,'Goals 2026'!B:B,Smry!D65,'Goals 2026'!C:C,Smry!F65,'Goals 2026'!E:E,Smry!$B$62) -> 0 | N65: =SUM(O65:R65) -> 0.49718334 | O65: =SUMIFS('Goals 2026'!H:H,'Goals 2026'!B:B,Smry!D65,'Goals 2026'!C:C,Smry!F65,'Goals 2026'!E:E,Smry!$B$62) -> 0.36573176 | P65: =SUMIFS('Goals 2026'!I:I,'Goals 2026'!B:B,Smry!D65,'Goals 2026'!C:C,Smry!F65,'Goals 2026'!E:E,Smry!$B$62) -> 0.13145158 | Q65: =SUMIFS('Goals 2026'!J:J,'Goals 2026'!B:B,Smry!D65,'Goals 2026'!C:C,Smry!F65,'Goals 2026'!E:E,Smry!$B$62) -> 0 | R65: =SUMIFS('Goals 2026'!K:K,'Goals 2026'!B:B,Smry!D65,'Goals 2026'!C:C,Smry!F65,'Goals 2026'!E:E,Smry!$B$62) -> 0
B66: Gagan | D66: AtR - C | F66: Com | H66: =SUM(I66:L66) -> 2 | I66: =SUMIFS('Goals 2026'!M:M,'Goals 2026'!B:B,Smry!D66,'Goals 2026'!C:C,Smry!F66,'Goals 2026'!E:E,Smry!$B$62) -> 2 | J66: =SUMIFS('Goals 2026'!N:N,'Goals 2026'!B:B,Smry!D66,'Goals 2026'!C:C,Smry!F66,'Goals 2026'!E:E,Smry!$B$62) -> 0 | K66: =SUMIFS('Goals 2026'!O:O,'Goals 2026'!B:B,Smry!D66,'Goals 2026'!C:C,Smry!F66,'Goals 2026'!E:E,Smry!$B$62) -> 0 | L66: =SUMIFS('Goals 2026'!P:P,'Goals 2026'!B:B,Smry!D66,'Goals 2026'!C:C,Smry!F66,'Goals 2026'!E:E,Smry!$B$62) -> 0 | N66: =SUM(O66:R66) -> 0.16750548 | O66: =SUMIFS('Goals 2026'!H:H,'Goals 2026'!B:B,Smry!D66,'Goals 2026'!C:C,Smry!F66,'Goals 2026'!E:E,Smry!$B$62) -> 0.16750548 | P66: =SUMIFS('Goals 2026'!I:I,'Goals 2026'!B:B,Smry!D66,'Goals 2026'!C:C,Smry!F66,'Goals 2026'!E:E,Smry!$B$62) -> 0 | Q66: =SUMIFS('Goals 2026'!J:J,'Goals 2026'!B:B,Smry!D66,'Goals 2026'!C:C,Smry!F66,'Goals 2026'!E:E,Smry!$B$62) -> 0 | R66: =SUMIFS('Goals 2026'!K:K,'Goals 2026'!B:B,Smry!D66,'Goals 2026'!C:C,Smry!F66,'Goals 2026'!E:E,Smry!$B$62) -> 0
B67: Gagan | D67: PoaRR-Res | F67: Res | H67: =SUM(I67:L67) -> 4 | I67: =SUMIFS('Goals 2026'!M:M,'Goals 2026'!B:B,Smry!D67,'Goals 2026'!C:C,Smry!F67,'Goals 2026'!E:E,Smry!$B$62) -> 4 | J67: =SUMIFS('Goals 2026'!N:N,'Goals 2026'!B:B,Smry!D67,'Goals 2026'!C:C,Smry!F67,'Goals 2026'!E:E,Smry!$B$62) -> 0 | K67: =SUMIFS('Goals 2026'!O:O,'Goals 2026'!B:B,Smry!D67,'Goals 2026'!C:C,Smry!F67,'Goals 2026'!E:E,Smry!$B$62) -> 0 | L67: =SUMIFS('Goals 2026'!P:P,'Goals 2026'!B:B,Smry!D67,'Goals 2026'!C:C,Smry!F67,'Goals 2026'!E:E,Smry!$B$62) -> 0 | N67: =SUM(O67:R67) -> 0.4032745 | O67: =SUMIFS('Goals 2026'!H:H,'Goals 2026'!B:B,Smry!D67,'Goals 2026'!C:C,Smry!F67,'Goals 2026'!E:E,Smry!$B$62) -> 0.4032745 | P67: =SUMIFS('Goals 2026'!I:I,'Goals 2026'!B:B,Smry!D67,'Goals 2026'!C:C,Smry!F67,'Goals 2026'!E:E,Smry!$B$62) -> 0 | Q67: =SUMIFS('Goals 2026'!J:J,'Goals 2026'!B:B,Smry!D67,'Goals 2026'!C:C,Smry!F67,'Goals 2026'!E:E,Smry!$B$62) -> 0 | R67: =SUMIFS('Goals 2026'!K:K,'Goals 2026'!B:B,Smry!D67,'Goals 2026'!C:C,Smry!F67,'Goals 2026'!E:E,Smry!$B$62) -> 0
B68: Gagan | D68: PoaRR-T08 | F68: T08 | H68: =SUM(I68:L68) -> 23 | I68: =SUMIFS('Goals 2026'!M:M,'Goals 2026'!B:B,Smry!D68,'Goals 2026'!C:C,Smry!F68,'Goals 2026'!E:E,Smry!$B$62) -> 3 | J68: =SUMIFS('Goals 2026'!N:N,'Goals 2026'!B:B,Smry!D68,'Goals 2026'!C:C,Smry!F68,'Goals 2026'!E:E,Smry!$B$62) -> 9 | K68: =SUMIFS('Goals 2026'!O:O,'Goals 2026'!B:B,Smry!D68,'Goals 2026'!C:C,Smry!F68,'Goals 2026'!E:E,Smry!$B$62) -> 11 | L68: =SUMIFS('Goals 2026'!P:P,'Goals 2026'!B:B,Smry!D68,'Goals 2026'!C:C,Smry!F68,'Goals 2026'!E:E,Smry!$B$62) -> 0 | N68: =SUM(O68:R68) -> 1.28828 | O68: =SUMIFS('Goals 2026'!H:H,'Goals 2026'!B:B,Smry!D68,'Goals 2026'!C:C,Smry!F68,'Goals 2026'!E:E,Smry!$B$62) -> 0.14 | P68: =SUMIFS('Goals 2026'!I:I,'Goals 2026'!B:B,Smry!D68,'Goals 2026'!C:C,Smry!F68,'Goals 2026'!E:E,Smry!$B$62) -> 0.65548 | Q68: =SUMIFS('Goals 2026'!J:J,'Goals 2026'!B:B,Smry!D68,'Goals 2026'!C:C,Smry!F68,'Goals 2026'!E:E,Smry!$B$62) -> 0.4928 | R68: =SUMIFS('Goals 2026'!K:K,'Goals 2026'!B:B,Smry!D68,'Goals 2026'!C:C,Smry!F68,'Goals 2026'!E:E,Smry!$B$62) -> 0
B69: Gagan | D69: ITQE-Ph2b | F69: Ph 2b | H69: =SUM(I69:L69) -> 3 | I69: =SUMIFS('Goals 2026'!M:M,'Goals 2026'!B:B,Smry!D69,'Goals 2026'!C:C,Smry!F69,'Goals 2026'!E:E,Smry!$B$62) -> 2 | J69: =SUMIFS('Goals 2026'!N:N,'Goals 2026'!B:B,Smry!D69,'Goals 2026'!C:C,Smry!F69,'Goals 2026'!E:E,Smry!$B$62) -> 0 | K69: =SUMIFS('Goals 2026'!O:O,'Goals 2026'!B:B,Smry!D69,'Goals 2026'!C:C,Smry!F69,'Goals 2026'!E:E,Smry!$B$62) -> 1 | L69: =SUMIFS('Goals 2026'!P:P,'Goals 2026'!B:B,Smry!D69,'Goals 2026'!C:C,Smry!F69,'Goals 2026'!E:E,Smry!$B$62) -> 0 | N69: =SUM(O69:R69) -> 0.049857313 | O69: =SUMIFS('Goals 2026'!H:H,'Goals 2026'!B:B,Smry!D69,'Goals 2026'!C:C,Smry!F69,'Goals 2026'!E:E,Smry!$B$62) -> 0.031655887 | P69: =SUMIFS('Goals 2026'!I:I,'Goals 2026'!B:B,Smry!D69,'Goals 2026'!C:C,Smry!F69,'Goals 2026'!E:E,Smry!$B$62) -> 0 | Q69: =SUMIFS('Goals 2026'!J:J,'Goals 2026'!B:B,Smry!D69,'Goals 2026'!C:C,Smry!F69,'Goals 2026'!E:E,Smry!$B$62) -> 0.018201425 | R69: =SUMIFS('Goals 2026'!K:K,'Goals 2026'!B:B,Smry!D69,'Goals 2026'!C:C,Smry!F69,'Goals 2026'!E:E,Smry!$B$62) -> 0
B70: Gagan | D70: ItQE-Ph2c [T9] | F70: Ph 2c | H70: =SUM(I70:L70) -> 6 | I70: =SUMIFS('Goals 2026'!M:M,'Goals 2026'!B:B,Smry!D70,'Goals 2026'!C:C,Smry!F70,'Goals 2026'!E:E,Smry!$B$62) -> 2 | J70: =SUMIFS('Goals 2026'!N:N,'Goals 2026'!B:B,Smry!D70,'Goals 2026'!C:C,Smry!F70,'Goals 2026'!E:E,Smry!$B$62) -> 3 | K70: =SUMIFS('Goals 2026'!O:O,'Goals 2026'!B:B,Smry!D70,'Goals 2026'!C:C,Smry!F70,'Goals 2026'!E:E,Smry!$B$62) -> 1 | L70: =SUMIFS('Goals 2026'!P:P,'Goals 2026'!B:B,Smry!D70,'Goals 2026'!C:C,Smry!F70,'Goals 2026'!E:E,Smry!$B$62) -> 0 | N70: =SUM(O70:R70) -> 0.14769089 | O70: =SUMIFS('Goals 2026'!H:H,'Goals 2026'!B:B,Smry!D70,'Goals 2026'!C:C,Smry!F70,'Goals 2026'!E:E,Smry!$B$62) -> 0.04712278 | P70: =SUMIFS('Goals 2026'!I:I,'Goals 2026'!B:B,Smry!D70,'Goals 2026'!C:C,Smry!F70,'Goals 2026'!E:E,Smry!$B$62) -> 0.08426778 | Q70: =SUMIFS('Goals 2026'!J:J,'Goals 2026'!B:B,Smry!D70,'Goals 2026'!C:C,Smry!F70,'Goals 2026'!E:E,Smry!$B$62) -> 0.016300333 | R70: =SUMIFS('Goals 2026'!K:K,'Goals 2026'!B:B,Smry!D70,'Goals 2026'!C:C,Smry!F70,'Goals 2026'!E:E,Smry!$B$62) -> 0
B71: Gagan | D71: ItQE-Ph3a [T10-12 & 31 Villas] | F71: Ph 3a | H71: =SUM(I71:L71) -> 23 | I71: =SUMIFS('Goals 2026'!M:M,'Goals 2026'!B:B,Smry!D71,'Goals 2026'!C:C,Smry!F71,'Goals 2026'!E:E,Smry!$B$62) -> 5 | J71: =SUMIFS('Goals 2026'!N:N,'Goals 2026'!B:B,Smry!D71,'Goals 2026'!C:C,Smry!F71,'Goals 2026'!E:E,Smry!$B$62) -> 2 | K71: =SUMIFS('Goals 2026'!O:O,'Goals 2026'!B:B,Smry!D71,'Goals 2026'!C:C,Smry!F71,'Goals 2026'!E:E,Smry!$B$62) -> 9 | L71: =SUMIFS('Goals 2026'!P:P,'Goals 2026'!B:B,Smry!D71,'Goals 2026'!C:C,Smry!F71,'Goals 2026'!E:E,Smry!$B$62) -> 7 | N71: =SUM(O71:R71) -> 2.9539608 | O71: =SUMIFS('Goals 2026'!H:H,'Goals 2026'!B:B,Smry!D71,'Goals 2026'!C:C,Smry!F71,'Goals 2026'!E:E,Smry!$B$62) -> 2.1646138 | P71: =SUMIFS('Goals 2026'!I:I,'Goals 2026'!B:B,Smry!D71,'Goals 2026'!C:C,Smry!F71,'Goals 2026'!E:E,Smry!$B$62) -> 0.10236453 | Q71: =SUMIFS('Goals 2026'!J:J,'Goals 2026'!B:B,Smry!D71,'Goals 2026'!C:C,Smry!F71,'Goals 2026'!E:E,Smry!$B$62) -> 0.40148764 | R71: =SUMIFS('Goals 2026'!K:K,'Goals 2026'!B:B,Smry!D71,'Goals 2026'!C:C,Smry!F71,'Goals 2026'!E:E,Smry!$B$62) -> 0.28549481
B72: Gagan | D72: OTR-Ph01 | F72: Ph 1 | H72: =SUM(I72:L72) -> 1 | I72: =SUMIFS('Goals 2026'!M:M,'Goals 2026'!B:B,Smry!D72,'Goals 2026'!C:C,Smry!F72,'Goals 2026'!E:E,Smry!$B$62) -> 1 | J72: =SUMIFS('Goals 2026'!N:N,'Goals 2026'!B:B,Smry!D72,'Goals 2026'!C:C,Smry!F72,'Goals 2026'!E:E,Smry!$B$62) -> 0 | K72: =SUMIFS('Goals 2026'!O:O,'Goals 2026'!B:B,Smry!D72,'Goals 2026'!C:C,Smry!F72,'Goals 2026'!E:E,Smry!$B$62) -> 0 | L72: =SUMIFS('Goals 2026'!P:P,'Goals 2026'!B:B,Smry!D72,'Goals 2026'!C:C,Smry!F72,'Goals 2026'!E:E,Smry!$B$62) -> 0 | N72: =SUM(O72:R72) -> 0.04 | O72: =SUMIFS('Goals 2026'!H:H,'Goals 2026'!B:B,Smry!D72,'Goals 2026'!C:C,Smry!F72,'Goals 2026'!E:E,Smry!$B$62) -> 0.04 | P72: =SUMIFS('Goals 2026'!I:I,'Goals 2026'!B:B,Smry!D72,'Goals 2026'!C:C,Smry!F72,'Goals 2026'!E:E,Smry!$B$62) -> 0 | Q72: =SUMIFS('Goals 2026'!J:J,'Goals 2026'!B:B,Smry!D72,'Goals 2026'!C:C,Smry!F72,'Goals 2026'!E:E,Smry!$B$62) -> 0 | R72: =SUMIFS('Goals 2026'!K:K,'Goals 2026'!B:B,Smry!D72,'Goals 2026'!C:C,Smry!F72,'Goals 2026'!E:E,Smry!$B$62) -> 0
B73: Gagan | D73: TuiG | F73: TuiG | H73: =SUM(I73:L73) -> 6 | I73: =SUMIFS('Goals 2026'!M:M,'Goals 2026'!B:B,Smry!D73,'Goals 2026'!C:C,Smry!F73,'Goals 2026'!E:E,Smry!$B$62) -> 4 | J73: =SUMIFS('Goals 2026'!N:N,'Goals 2026'!B:B,Smry!D73,'Goals 2026'!C:C,Smry!F73,'Goals 2026'!E:E,Smry!$B$62) -> 2 | K73: =SUMIFS('Goals 2026'!O:O,'Goals 2026'!B:B,Smry!D73,'Goals 2026'!C:C,Smry!F73,'Goals 2026'!E:E,Smry!$B$62) -> 0 | L73: =SUMIFS('Goals 2026'!P:P,'Goals 2026'!B:B,Smry!D73,'Goals 2026'!C:C,Smry!F73,'Goals 2026'!E:E,Smry!$B$62) -> 0 | N73: =SUM(O73:R73) -> 0.49857202 | O73: =SUMIFS('Goals 2026'!H:H,'Goals 2026'!B:B,Smry!D73,'Goals 2026'!C:C,Smry!F73,'Goals 2026'!E:E,Smry!$B$62) -> 0.32421104 | P73: =SUMIFS('Goals 2026'!I:I,'Goals 2026'!B:B,Smry!D73,'Goals 2026'!C:C,Smry!F73,'Goals 2026'!E:E,Smry!$B$62) -> 0.17436098 | Q73: =SUMIFS('Goals 2026'!J:J,'Goals 2026'!B:B,Smry!D73,'Goals 2026'!C:C,Smry!F73,'Goals 2026'!E:E,Smry!$B$62) -> 0 | R73: =SUMIFS('Goals 2026'!K:K,'Goals 2026'!B:B,Smry!D73,'Goals 2026'!C:C,Smry!F73,'Goals 2026'!E:E,Smry!$B$62) -> 0
B74: Gagan | D74: DBTW | F74: DBTW | H74: =SUM(I74:L74) -> 11 | I74: =SUMIFS('Goals 2026'!M:M,'Goals 2026'!B:B,Smry!D74,'Goals 2026'!C:C,Smry!F74,'Goals 2026'!E:E,Smry!$B$62) -> 1 | J74: =SUMIFS('Goals 2026'!N:N,'Goals 2026'!B:B,Smry!D74,'Goals 2026'!C:C,Smry!F74,'Goals 2026'!E:E,Smry!$B$62) -> 1 | K74: =SUMIFS('Goals 2026'!O:O,'Goals 2026'!B:B,Smry!D74,'Goals 2026'!C:C,Smry!F74,'Goals 2026'!E:E,Smry!$B$62) -> 1 | L74: =SUMIFS('Goals 2026'!P:P,'Goals 2026'!B:B,Smry!D74,'Goals 2026'!C:C,Smry!F74,'Goals 2026'!E:E,Smry!$B$62) -> 8 | N74: =SUM(O74:R74) -> 0.53636436 | O74: =SUMIFS('Goals 2026'!H:H,'Goals 2026'!B:B,Smry!D74,'Goals 2026'!C:C,Smry!F74,'Goals 2026'!E:E,Smry!$B$62) -> 0.036853335 | P74: =SUMIFS('Goals 2026'!I:I,'Goals 2026'!B:B,Smry!D74,'Goals 2026'!C:C,Smry!F74,'Goals 2026'!E:E,Smry!$B$62) -> 0.12284445 | Q74: =SUMIFS('Goals 2026'!J:J,'Goals 2026'!B:B,Smry!D74,'Goals 2026'!C:C,Smry!F74,'Goals 2026'!E:E,Smry!$B$62) -> 0.10269917 | R74: =SUMIFS('Goals 2026'!K:K,'Goals 2026'!B:B,Smry!D74,'Goals 2026'!C:C,Smry!F74,'Goals 2026'!E:E,Smry!$B$62) -> 0.2739674
B75: Gagan | D75: SftW | F75: SftW | H75: =SUM(I75:L75) -> 3 | I75: =SUMIFS('Goals 2026'!M:M,'Goals 2026'!B:B,Smry!D75,'Goals 2026'!C:C,Smry!F75,'Goals 2026'!E:E,Smry!$B$62) -> 2 | J75: =SUMIFS('Goals 2026'!N:N,'Goals 2026'!B:B,Smry!D75,'Goals 2026'!C:C,Smry!F75,'Goals 2026'!E:E,Smry!$B$62) -> 1 | K75: =SUMIFS('Goals 2026'!O:O,'Goals 2026'!B:B,Smry!D75,'Goals 2026'!C:C,Smry!F75,'Goals 2026'!E:E,Smry!$B$62) -> 0 | L75: =SUMIFS('Goals 2026'!P:P,'Goals 2026'!B:B,Smry!D75,'Goals 2026'!C:C,Smry!F75,'Goals 2026'!E:E,Smry!$B$62) -> 0 | N75: =SUM(O75:R75) -> 0.064478719 | O75: =SUMIFS('Goals 2026'!H:H,'Goals 2026'!B:B,Smry!D75,'Goals 2026'!C:C,Smry!F75,'Goals 2026'!E:E,Smry!$B$62) -> 0.021397858 | P75: =SUMIFS('Goals 2026'!I:I,'Goals 2026'!B:B,Smry!D75,'Goals 2026'!C:C,Smry!F75,'Goals 2026'!E:E,Smry!$B$62) -> 0.043080861 | Q75: =SUMIFS('Goals 2026'!J:J,'Goals 2026'!B:B,Smry!D75,'Goals 2026'!C:C,Smry!F75,'Goals 2026'!E:E,Smry!$B$62) -> 0 | R75: =SUMIFS('Goals 2026'!K:K,'Goals 2026'!B:B,Smry!D75,'Goals 2026'!C:C,Smry!F75,'Goals 2026'!E:E,Smry!$B$62) -> 0
... B98: Gagan | D98: DonaPaula | F98: DP | H98: =SUM(I98:L98) -> 30 | I98: =SUMIFS('Goals 2026'!M:M,'Goals 2026'!B:B,Smry!D98,'Goals 2026'!C:C,Smry!F98,'Goals 2026'!E:E,Smry!$B$62) -> 5 | J98: =SUMIFS('Goals 2026'!N:N,'Goals 2026'!B:B,Smry!D98,'Goals 2026'!C:C,Smry!F98,'Goals 2026'!E:E,Smry!$B$62) -> 3 | K98: =SUMIFS('Goals 2026'!O:O,'Goals 2026'!B:B,Smry!D98,'Goals 2026'!C:C,Smry!F98,'Goals 2026'!E:E,Smry!$B$62) -> 12 | L98: =SUMIFS('Goals 2026'!P:P,'Goals 2026'!B:B,Smry!D98,'Goals 2026'!C:C,Smry!F98,'Goals 2026'!E:E,Smry!$B$62) -> 10 | N98: =SUM(O98:R98) -> 1.1097676 | O98: =SUMIFS('Goals 2026'!H:H,'Goals 2026'!B:B,Smry!D98,'Goals 2026'!C:C,Smry!F98,'Goals 2026'!E:E,Smry!$B$62) -> 0.45 | P98: =SUMIFS('Goals 2026'!I:I,'Goals 2026'!B:B,Smry!D98,'Goals 2026'!C:C,Smry!F98,'Goals 2026'!E:E,Smry!$B$62) -> 0.25 | Q98: =SUMIFS('Goals 2026'!J:J,'Goals 2026'!B:B,Smry!D98,'Goals 2026'!C:C,Smry!F98,'Goals 2026'!E:E,Smry!$B$62) -> 0.32451895 | R98: =SUMIFS('Goals 2026'!K:K,'Goals 2026'!B:B,Smry!D98,'Goals 2026'!C:C,Smry!F98,'Goals 2026'!E:E,Smry!$B$62) -> 0.085248666
J99: =SUMIFS('Goals 2026'!N:N,'Goals 2026'!B:B,Smry!D99,'Goals 2026'!C:C,Smry!F99,'Goals 2026'!E:E,Smry!$B$62) -> 0
B100: Naveen Y | H100: =SUM(I100:L100) -> 87 | I100: =SUM(I102:I108) -> 24 | J100: =SUM(J102:J108) -> 13 | K100: =SUM(K102:K108) -> 22 | L100: =SUM(L102:L108) -> 28 | N100: =SUM(O100:R100) -> 46.454737 | O100: =SUM(O102:O108) -> 23.432421 | P100: =SUM(P102:P108) -> 11.134149 | Q100: =SUM(Q102:Q108) -> 6.1257662 | R100: =SUM(R102:R108) -> 5.7624015
B102: Naveen Y | D102: AtR - C | F102: Com | H102: =SUM(I102:L102) -> 3 | I102: =SUMIFS('Goals 2026'!M:M,'Goals 2026'!B:B,Smry!D102,'Goals 2026'!C:C,Smry!F102,'Goals 2026'!E:E,Smry!$B$100) -> 3 | J102: =SUMIFS('Goals 2026'!N:N,'Goals 2026'!B:B,Smry!D102,'Goals 2026'!C:C,Smry!F102,'Goals 2026'!E:E,Smry!$B$100) -> 0 | K102: =SUMIFS('Goals 2026'!O:O,'Goals 2026'!B:B,Smry!D102,'Goals 2026'!C:C,Smry!F102,'Goals 2026'!E:E,Smry!$B$100) -> 0 | L102: =SUMIFS('Goals 2026'!P:P,'Goals 2026'!B:B,Smry!D102,'Goals 2026'!C:C,Smry!F102,'Goals 2026'!E:E,Smry!$B$100) -> 0 | N102: =SUM(O102:R102) -> 0.36421477 | O102: =SUMIFS('Goals 2026'!H:H,'Goals 2026'!B:B,Smry!D102,'Goals 2026'!C:C,Smry!F102,'Goals 2026'!E:E,Smry!$B$100) -> 0.36421477 | P102: =SUMIFS('Goals 2026'!I:I,'Goals 2026'!B:B,Smry!D102,'Goals 2026'!C:C,Smry!F102,'Goals 2026'!E:E,Smry!$B$100) -> 0 | Q102: =SUMIFS('Goals 2026'!J:J,'Goals 2026'!B:B,Smry!D102,'Goals 2026'!C:C,Smry!F102,'Goals 2026'!E:E,Smry!$B$100) -> 0 | R102: =SUMIFS('Goals 2026'!K:K,'Goals 2026'!B:B,Smry!D102,'Goals 2026'!C:C,Smry!F102,'Goals 2026'!E:E,Smry!$B$100) -> 0
B103: Naveen Y | D103: Imagine Campus | F103: Imgn | H103: =SUM(I103:L103) -> 6 | I103: =SUMIFS('Goals 2026'!M:M,'Goals 2026'!B:B,Smry!D103,'Goals 2026'!C:C,Smry!F103,'Goals 2026'!E:E,Smry!$B$100) -> 3 | J103: =SUMIFS('Goals 2026'!N:N,'Goals 2026'!B:B,Smry!D103,'Goals 2026'!C:C,Smry!F103,'Goals 2026'!E:E,Smry!$B$100) -> 1 | K103: =SUMIFS('Goals 2026'!O:O,'Goals 2026'!B:B,Smry!D103,'Goals 2026'!C:C,Smry!F103,'Goals 2026'!E:E,Smry!$B$100) -> 1 | L103: =SUMIFS('Goals 2026'!P:P,'Goals 2026'!B:B,Smry!D103,'Goals 2026'!C:C,Smry!F103,'Goals 2026'!E:E,Smry!$B$100) -> 1 | N103: =SUM(O103:R103) -> 3.28 | O103: =SUMIFS('Goals 2026'!H:H,'Goals 2026'!B:B,Smry!D103,'Goals 2026'!C:C,Smry!F103,'Goals 2026'!E:E,Smry!$B$100) -> 1.61 | P103: =SUMIFS('Goals 2026'!I:I,'Goals 2026'!B:B,Smry!D103,'Goals 2026'!C:C,Smry!F103,'Goals 2026'!E:E,Smry!$B$100) -> 0.46 | Q103: =SUMIFS('Goals 2026'!J:J,'Goals 2026'!B:B,Smry!D103,'Goals 2026'!C:C,Smry!F103,'Goals 2026'!E:E,Smry!$B$100) -> 0.81 | R103: =SUMIFS('Goals 2026'!K:K,'Goals 2026'!B:B,Smry!D103,'Goals 2026'!C:C,Smry!F103,'Goals 2026'!E:E,Smry!$B$100) -> 0.4
B104: Naveen Y | D104: TMFT-Ph 3 | F104: Ph 3 | H104: =SUM(I104:L104) -> 12 | I104: =SUMIFS('Goals 2026'!M:M,'Goals 2026'!B:B,Smry!D104,'Goals 2026'!C:C,Smry!F104,'Goals 2026'!E:E,Smry!$B$100) -> 3 | J104: =SUMIFS('Goals 2026'!N:N,'Goals 2026'!B:B,Smry!D104,'Goals 2026'!C:C,Smry!F104,'Goals 2026'!E:E,Smry!$B$100) -> 3 | K104: =SUMIFS('Goals 2026'!O:O,'Goals 2026'!B:B,Smry!D104,'Goals 2026'!C:C,Smry!F104,'Goals 2026'!E:E,Smry!$B$100) -> 2 | L104: =SUMIFS('Goals 2026'!P:P,'Goals 2026'!B:B,Smry!D104,'Goals 2026'!C:C,Smry!F104,'Goals 2026'!E:E,Smry!$B$100) -> 4 | N104: =SUM(O104:R104) -> 1.587432 | O104: =SUMIFS('Goals 2026'!H:H,'Goals 2026'!B:B,Smry!D104,'Goals 2026'!C:C,Smry!F104,'Goals 2026'!E:E,Smry!$B$100) -> 0.6182 | P104: =SUMIFS('Goals 2026'!I:I,'Goals 2026'!B:B,Smry!D104,'Goals 2026'!C:C,Smry!F104,'Goals 2026'!E:E,Smry!$B$100) -> 0.49456 | Q104: =SUMIFS('Goals 2026'!J:J,'Goals 2026'!B:B,Smry!D104,'Goals 2026'!C:C,Smry!F104,'Goals 2026'!E:E,Smry!$B$100) -> 0.133584 | R104: =SUMIFS('Goals 2026'!K:K,'Goals 2026'!B:B,Smry!D104,'Goals 2026'!C:C,Smry!F104,'Goals 2026'!E:E,Smry!$B$100) -> 0.341088
B105: Naveen Y | D105: Srjp - C - NB | F105: Srjp - C - NB | H105: =SUM(I105:L105) -> 9 | I105: =SUMIFS('Goals 2026'!M:M,'Goals 2026'!B:B,Smry!D105,'Goals 2026'!C:C,Smry!F105,'Goals 2026'!E:E,Smry!$B$100) -> 3 | J105: =SUMIFS('Goals 2026'!N:N,'Goals 2026'!B:B,Smry!D105,'Goals 2026'!C:C,Smry!F105,'Goals 2026'!E:E,Smry!$B$100) -> 2 | K105: =SUMIFS('Goals 2026'!O:O,'Goals 2026'!B:B,Smry!D105,'Goals 2026'!C:C,Smry!F105,'Goals 2026'!E:E,Smry!$B$100) -> 2 | L105: =SUMIFS('Goals 2026'!P:P,'Goals 2026'!B:B,Smry!D105,'Goals 2026'!C:C,Smry!F105,'Goals 2026'!E:E,Smry!$B$100) -> 2 | N105: =SUM(O105:R105) -> 6.8495648 | O105: =SUMIFS('Goals 2026'!H:H,'Goals 2026'!B:B,Smry!D105,'Goals 2026'!C:C,Smry!F105,'Goals 2026'!E:E,Smry!$B$100) -> 3.6843765 | P105: =SUMIFS('Goals 2026'!I:I,'Goals 2026'!B:B,Smry!D105,'Goals 2026'!C:C,Smry!F105,'Goals 2026'!E:E,Smry!$B$100) -> 1.8421883 | Q105: =SUMIFS('Goals 2026'!J:J,'Goals 2026'!B:B,Smry!D105,'Goals 2026'!C:C,Smry!F105,'Goals 2026'!E:E,Smry!$B$100) -> 0.7056 | R105: =SUMIFS('Goals 2026'!K:K,'Goals 2026'!B:B,Smry!D105,'Goals 2026'!C:C,Smry!F105,'Goals 2026'!E:E,Smry!$B$100) -> 0.6174
B106: Naveen Y | D106: OTF | F106: OTF | H106: =SUM(I106:L106) -> 17 | I106: =SUMIFS('Goals 2026'!M:M,'Goals 2026'!B:B,Smry!D106,'Goals 2026'!C:C,Smry!F106,'Goals 2026'!E:E,Smry!$B$100) -> 6 | J106: =SUMIFS('Goals 2026'!N:N,'Goals 2026'!B:B,Smry!D106,'Goals 2026'!C:C,Smry!F106,'Goals 2026'!E:E,Smry!$B$100) -> 3 | K106: =SUMIFS('Goals 2026'!O:O,'Goals 2026'!B:B,Smry!D106,'Goals 2026'!C:C,Smry!F106,'Goals 2026'!E:E,Smry!$B$100) -> 5 | L106: =SUMIFS('Goals 2026'!P:P,'Goals 2026'!B:B,Smry!D106,'Goals 2026'!C:C,Smry!F106,'Goals 2026'!E:E,Smry!$B$100) -> 3 | N106: =SUM(O106:R106) -> 5.6525 | O106: =SUMIFS('Goals 2026'!H:H,'Goals 2026'!B:B,Smry!D106,'Goals 2026'!C:C,Smry!F106,'Goals 2026'!E:E,Smry!$B$100) -> 2.7525 | P106: =SUMIFS('Goals 2026'!I:I,'Goals 2026'!B:B,Smry!D106,'Goals 2026'!C:C,Smry!F106,'Goals 2026'!E:E,Smry!$B$100) -> 1.45 | Q106: =SUMIFS('Goals 2026'!J:J,'Goals 2026'!B:B,Smry!D106,'Goals 2026'!C:C,Smry!F106,'Goals 2026'!E:E,Smry!$B$100) -> 0.87 | R106: =SUMIFS('Goals 2026'!K:K,'Goals 2026'!B:B,Smry!D106,'Goals 2026'!C:C,Smry!F106,'Goals 2026'!E:E,Smry!$B$100) -> 0.58
B107: Naveen Y | D107: Srjp - C - SB | F107: Srjp - C - SB | H107: =SUM(I107:L107) -> 10 | I107: =SUMIFS('Goals 2026'!M:M,'Goals 2026'!B:B,Smry!D107,'Goals 2026'!C:C,Smry!F107,'Goals 2026'!E:E,Smry!$B$100) -> 3 | J107: =SUMIFS('Goals 2026'!N:N,'Goals 2026'!B:B,Smry!D107,'Goals 2026'!C:C,Smry!F107,'Goals 2026'!E:E,Smry!$B$100) -> 2 | K107: =SUMIFS('Goals 2026'!O:O,'Goals 2026'!B:B,Smry!D107,'Goals 2026'!C:C,Smry!F107,'Goals 2026'!E:E,Smry!$B$100) -> 2 | L107: =SUMIFS('Goals 2026'!P:P,'Goals 2026'!B:B,Smry!D107,'Goals 2026'!C:C,Smry!F107,'Goals 2026'!E:E,Smry!$B$100) -> 3 | N107: =SUM(O107:R107) -> 21.871694 | O107: =SUMIFS('Goals 2026'!H:H,'Goals 2026'!B:B,Smry!D107,'Goals 2026'!C:C,Smry!F107,'Goals 2026'!E:E,Smry!$B$100) -> 11.05313 | P107: =SUMIFS('Goals 2026'!I:I,'Goals 2026'!B:B,Smry!D107,'Goals 2026'!C:C,Smry!F107,'Goals 2026'!E:E,Smry!$B$100) -> 5.5265648 | Q107: =SUMIFS('Goals 2026'!J:J,'Goals 2026'!B:B,Smry!D107,'Goals 2026'!C:C,Smry!F107,'Goals 2026'!E:E,Smry!$B$100) -> 2.1168 | R107: =SUMIFS('Goals 2026'!K:K,'Goals 2026'!B:B,Smry!D107,'Goals 2026'!C:C,Smry!F107,'Goals 2026'!E:E,Smry!$B$100) -> 3.1752
B108: Naveen Y | D108: DonaPaula | F108: DP | H108: =SUM(I108:L108) -> 30 | I108: =SUMIFS('Goals 2026'!M:M,'Goals 2026'!B:B,Smry!D108,'Goals 2026'!C:C,Smry!F108,'Goals 2026'!E:E,Smry!$B$100) -> 3 | J108: =SUMIFS('Goals 2026'!N:N,'Goals 2026'!B:B,Smry!D108,'Goals 2026'!C:C,Smry!F108,'Goals 2026'!E:E,Smry!$B$100) -> 2 | K108: =SUMIFS('Goals 2026'!O:O,'Goals 2026'!B:B,Smry!D108,'Goals 2026'!C:C,Smry!F108,'Goals 2026'!E:E,Smry!$B$100) -> 10 | L108: =SUMIFS('Goals 2026'!P:P,'Goals 2026'!B:B,Smry!D108,'Goals 2026'!C:C,Smry!F108,'Goals 2026'!E:E,Smry!$B$100) -> 15 | N108: =SUM(O108:R108) -> 6.8493316 | O108: =SUMIFS('Goals 2026'!H:H,'Goals 2026'!B:B,Smry!D108,'Goals 2026'!C:C,Smry!F108,'Goals 2026'!E:E,Smry!$B$100) -> 3.35 | P108: =SUMIFS('Goals 2026'!I:I,'Goals 2026'!B:B,Smry!D108,'Goals 2026'!C:C,Smry!F108,'Goals 2026'!E:E,Smry!$B$100) -> 1.3608358 | Q108: =SUMIFS('Goals 2026'!J:J,'Goals 2026'!B:B,Smry!D108,'Goals 2026'!C:C,Smry!F108,'Goals 2026'!E:E,Smry!$B$100) -> 1.4897822 | R108: =SUMIFS('Goals 2026'!K:K,'Goals 2026'!B:B,Smry!D108,'Goals 2026'!C:C,Smry!F108,'Goals 2026'!E:E,Smry!$B$100) -> 0.64871352
B110: Cijey M | H110: =SUM(I110:L110) -> 118 | I110: =SUM(I112:I122) -> 32 | J110: =SUM(J112:J122) -> 29 | K110: =SUM(K112:K122) -> 27 | L110: =SUM(L112:L122) -> 30 | N110: =SUM(O110:R110) -> 54.482878 | O110: =SUM(O112:O122) -> 28.98326 | P110: =SUM(P112:P122) -> 12.006115 | Q110: =SUM(Q112:Q122) -> 5.3386186 | R110: =SUM(R112:R122) -> 8.1548845
B112: Cijey M | D112: ITQE-Ph1 | F112: Ph 1 | H112: =SUM(I112:L112) -> 0 | I112: =SUMIFS('Goals 2026'!M:M,'Goals 2026'!B:B,Smry!D112,'Goals 2026'!C:C,Smry!F112,'Goals 2026'!E:E,Smry!$B$110) -> 0 | J112: =SUMIFS('Goals 2026'!N:N,'Goals 2026'!B:B,Smry!D112,'Goals 2026'!C:C,Smry!F112,'Goals 2026'!E:E,Smry!$B$110) -> 0 | K112: =SUMIFS('Goals 2026'!O:O,'Goals 2026'!B:B,Smry!D112,'Goals 2026'!C:C,Smry!F112,'Goals 2026'!E:E,Smry!$B$110) -> 0 | L112: =SUMIFS('Goals 2026'!P:P,'Goals 2026'!B:B,Smry!D112,'Goals 2026'!C:C,Smry!F112,'Goals 2026'!E:E,Smry!$B$110) -> 0 | N112: =SUM(O112:R112) -> 0 | O112: =SUMIFS('Goals 2026'!H:H,'Goals 2026'!B:B,Smry!D112,'Goals 2026'!C:C,Smry!F112,'Goals 2026'!E:E,Smry!$B$110) -> 0 | P112: =SUMIFS('Goals 2026'!I:I,'Goals 2026'!B:B,Smry!D112,'Goals 2026'!C:C,Smry!F112,'Goals 2026'!E:E,Smry!$B$110) -> 0 | Q112: =SUMIFS('Goals 2026'!J:J,'Goals 2026'!B:B,Smry!D112,'Goals 2026'!C:C,Smry!F112,'Goals 2026'!E:E,Smry!$B$110) -> 0 | R112: =SUMIFS('Goals 2026'!K:K,'Goals 2026'!B:B,Smry!D112,'Goals 2026'!C:C,Smry!F112,'Goals 2026'!E:E,Smry!$B$110) -> 0
B113: Cijey M | D113: ITQE-Ph2a | F113: Ph 2a | H113: =SUM(I113:L113) -> 2 | I113: =SUMIFS('Goals 2026'!M:M,'Goals 2026'!B:B,Smry!D113,'Goals 2026'!C:C,Smry!F113,'Goals 2026'!E:E,Smry!$B$110) -> 2 | J113: =SUMIFS('Goals 2026'!N:N,'Goals 2026'!B:B,Smry!D113,'Goals 2026'!C:C,Smry!F113,'Goals 2026'!E:E,Smry!$B$110) -> 0 | K113: =SUMIFS('Goals 2026'!O:O,'Goals 2026'!B:B,Smry!D113,'Goals 2026'!C:C,Smry!F113,'Goals 2026'!E:E,Smry!$B$110) -> 0 | L113: =SUMIFS('Goals 2026'!P:P,'Goals 2026'!B:B,Smry!D113,'Goals 2026'!C:C,Smry!F113,'Goals 2026'!E:E,Smry!$B$110) -> 0 | N113: =SUM(O113:R113) -> 0.25 | O113: =SUMIFS('Goals 2026'!H:H,'Goals 2026'!B:B,Smry!D113,'Goals 2026'!C:C,Smry!F113,'Goals 2026'!E:E,Smry!$B$110) -> 0.25 | P113: =SUMIFS('Goals 2026'!I:I,'Goals 2026'!B:B,Smry!D113,'Goals 2026'!C:C,Smry!F113,'Goals 2026'!E:E,Smry!$B$110) -> 0 | Q113: =SUMIFS('Goals 2026'!J:J,'Goals 2026'!B:B,Smry!D113,'Goals 2026'!C:C,Smry!F113,'Goals 2026'!E:E,Smry!$B$110) -> 0 | R113: =SUMIFS('Goals 2026'!K:K,'Goals 2026'!B:B,Smry!D113,'Goals 2026'!C:C,Smry!F113,'Goals 2026'!E:E,Smry!$B$110) -> 0
B114: Cijey M | D114: ITQE-Ph2b | F114: Ph 2b | H114: =SUM(I114:L114) -> 16 | I114: =SUMIFS('Goals 2026'!M:M,'Goals 2026'!B:B,Smry!D114,'Goals 2026'!C:C,Smry!F114,'Goals 2026'!E:E,Smry!$B$110) -> 4 | J114: =SUMIFS('Goals 2026'!N:N,'Goals 2026'!B:B,Smry!D114,'Goals 2026'!C:C,Smry!F114,'Goals 2026'!E:E,Smry!$B$110) -> 11 | K114: =SUMIFS('Goals 2026'!O:O,'Goals 2026'!B:B,Smry!D114,'Goals 2026'!C:C,Smry!F114,'Goals 2026'!E:E,Smry!$B$110) -> 1 | L114: =SUMIFS('Goals 2026'!P:P,'Goals 2026'!B:B,Smry!D114,'Goals 2026'!C:C,Smry!F114,'Goals 2026'!E:E,Smry!$B$110) -> 0 | N114: =SUM(O114:R114) -> 4.4553571 | O114: =SUMIFS('Goals 2026'!H:H,'Goals 2026'!B:B,Smry!D114,'Goals 2026'!C:C,Smry!F114,'Goals 2026'!E:E,Smry!$B$110) -> 2.3753571 | P114: =SUMIFS('Goals 2026'!I:I,'Goals 2026'!B:B,Smry!D114,'Goals 2026'!C:C,Smry!F114,'Goals 2026'!E:E,Smry!$B$110) -> 2.07 | Q114: =SUMIFS('Goals 2026'!J:J,'Goals 2026'!B:B,Smry!D114,'Goals 2026'!C:C,Smry!F114,'Goals 2026'!E:E,Smry!$B$110) -> 0.01 | R114: =SUMIFS('Goals 2026'!K:K,'Goals 2026'!B:B,Smry!D114,'Goals 2026'!C:C,Smry!F114,'Goals 2026'!E:E,Smry!$B$110) -> 0
B115: Cijey M | D115: ItQE-Ph2c [T9] | F115: Ph 2c | H115: =SUM(I115:L115) -> 10 | I115: =SUMIFS('Goals 2026'!M:M,'Goals 2026'!B:B,Smry!D115,'Goals 2026'!C:C,Smry!F115,'Goals 2026'!E:E,Smry!$B$110) -> 3 | J115: =SUMIFS('Goals 2026'!N:N,'Goals 2026'!B:B,Smry!D115,'Goals 2026'!C:C,Smry!F115,'Goals 2026'!E:E,Smry!$B$110) -> 4 | K115: =SUMIFS('Goals 2026'!O:O,'Goals 2026'!B:B,Smry!D115,'Goals 2026'!C:C,Smry!F115,'Goals 2026'!E:E,Smry!$B$110) -> 3 | L115: =SUMIFS('Goals 2026'!P:P,'Goals 2026'!B:B,Smry!D115,'Goals 2026'!C:C,Smry!F115,'Goals 2026'!E:E,Smry!$B$110) -> 0 | N115: =SUM(O115:R115) -> 1.0220568 | O115: =SUMIFS('Goals 2026'!H:H,'Goals 2026'!B:B,Smry!D115,'Goals 2026'!C:C,Smry!F115,'Goals 2026'!E:E,Smry!$B$110) -> 0.30105802 | P115: =SUMIFS('Goals 2026'!I:I,'Goals 2026'!B:B,Smry!D115,'Goals 2026'!C:C,Smry!F115,'Goals 2026'!E:E,Smry!$B$110) -> 0.39315029 | Q115: =SUMIFS('Goals 2026'!J:J,'Goals 2026'!B:B,Smry!D115,'Goals 2026'!C:C,Smry!F115,'Goals 2026'!E:E,Smry!$B$110) -> 0.3278485 | R115: =SUMIFS('Goals 2026'!K:K,'Goals 2026'!B:B,Smry!D115,'Goals 2026'!C:C,Smry!F115,'Goals 2026'!E:E,Smry!$B$110) -> 0
B116: Cijey M | D116: ItQE-Ph3a [T10-12 & 31 Villas] | F116: Ph 3a | H116: =SUM(I116:L116) -> 30 | I116: =SUMIFS('Goals 2026'!M:M,'Goals 2026'!B:B,Smry!D116,'Goals 2026'!C:C,Smry!F116,'Goals 2026'!E:E,Smry!$B$110) -> 3 | J116: =SUMIFS('Goals 2026'!N:N,'Goals 2026'!B:B,Smry!D116,'Goals 2026'!C:C,Smry!F116,'Goals 2026'!E:E,Smry!$B$110) -> 3 | K116: =SUMIFS('Goals 2026'!O:O,'Goals 2026'!B:B,Smry!D116,'Goals 2026'!C:C,Smry!F116,'Goals 2026'!E:E,Smry!$B$110) -> 10 | L116: =SUMIFS('Goals 2026'!P:P,'Goals 2026'!B:B,Smry!D116,'Goals 2026'!C:C,Smry!F116,'Goals 2026'!E:E,Smry!$B$110) -> 14 | N116: =SUM(O116:R116) -> 13.894856 | O116: =SUMIFS('Goals 2026'!H:H,'Goals 2026'!B:B,Smry!D116,'Goals 2026'!C:C,Smry!F116,'Goals 2026'!E:E,Smry!$B$110) -> 8.7813948 | P116: =SUMIFS('Goals 2026'!I:I,'Goals 2026'!B:B,Smry!D116,'Goals 2026'!C:C,Smry!F116,'Goals 2026'!E:E,Smry!$B$110) -> 0.65398654 | Q116: =SUMIFS('Goals 2026'!J:J,'Goals 2026'!B:B,Smry!D116,'Goals 2026'!C:C,Smry!F116,'Goals 2026'!E:E,Smry!$B$110) -> 1.8090826 | R116: =SUMIFS('Goals 2026'!K:K,'Goals 2026'!B:B,Smry!D116,'Goals 2026'!C:C,Smry!F116,'Goals 2026'!E:E,Smry!$B$110) -> 2.6503923
B117: Cijey M | D117: OTR-Ph01 | F117: Ph 1 | H117: =SUM(I117:L117) -> 5 | I117: =SUMIFS('Goals 2026'!M:M,'Goals 2026'!B:B,Smry!D117,'Goals 2026'!C:C,Smry!F117,'Goals 2026'!E:E,Smry!$B$110) -> 5 | J117: =SUMIFS('Goals 2026'!N:N,'Goals 2026'!B:B,Smry!D117,'Goals 2026'!C:C,Smry!F117,'Goals 2026'!E:E,Smry!$B$110) -> 0 | K117: =SUMIFS('Goals 2026'!O:O,'Goals 2026'!B:B,Smry!D117,'Goals 2026'!C:C,Smry!F117,'Goals 2026'!E:E,Smry!$B$110) -> 0 | L117: =SUMIFS('Goals 2026'!P:P,'Goals 2026'!B:B,Smry!D117,'Goals 2026'!C:C,Smry!F117,'Goals 2026'!E:E,Smry!$B$110) -> 0 | N117: =SUM(O117:R117) -> 0.96 | O117: =SUMIFS('Goals 2026'!H:H,'Goals 2026'!B:B,Smry!D117,'Goals 2026'!C:C,Smry!F117,'Goals 2026'!E:E,Smry!$B$110) -> 0.96 | P117: =SUMIFS('Goals 2026'!I:I,'Goals 2026'!B:B,Smry!D117,'Goals 2026'!C:C,Smry!F117,'Goals 2026'!E:E,Smry!$B$110) -> 0 | Q117: =SUMIFS('Goals 2026'!J:J,'Goals 2026'!B:B,Smry!D117,'Goals 2026'!C:C,Smry!F117,'Goals 2026'!E:E,Smry!$B$110) -> 0 | R117: =SUMIFS('Goals 2026'!K:K,'Goals 2026'!B:B,Smry!D117,'Goals 2026'!C:C,Smry!F117,'Goals 2026'!E:E,Smry!$B$110) -> 0
B118: Cijey M | D118: MeenaSai Res | F118: MS Res | H118: =SUM(I118:L118) -> 6 | I118: =SUMIFS('Goals 2026'!M:M,'Goals 2026'!B:B,Smry!D118,'Goals 2026'!C:C,Smry!F118,'Goals 2026'!E:E,Smry!$B$110) -> 2 | J118: =SUMIFS('Goals 2026'!N:N,'Goals 2026'!B:B,Smry!D118,'Goals 2026'!C:C,Smry!F118,'Goals 2026'!E:E,Smry!$B$110) -> 3 | K118: =SUMIFS('Goals 2026'!O:O,'Goals 2026'!B:B,Smry!D118,'Goals 2026'!C:C,Smry!F118,'Goals 2026'!E:E,Smry!$B$110) -> 1 | L118: =SUMIFS('Goals 2026'!P:P,'Goals 2026'!B:B,Smry!D118,'Goals 2026'!C:C,Smry!F118,'Goals 2026'!E:E,Smry!$B$110) -> 0 | N118: =SUM(O118:R118) -> 0.357 | O118: =SUMIFS('Goals 2026'!H:H,'Goals 2026'!B:B,Smry!D118,'Goals 2026'!C:C,Smry!F118,'Goals 2026'!E:E,Smry!$B$110) -> 0.105 | P118: =SUMIFS('Goals 2026'!I:I,'Goals 2026'!B:B,Smry!D118,'Goals 2026'!C:C,Smry!F118,'Goals 2026'!E:E,Smry!$B$110) -> 0.189 | Q118: =SUMIFS('Goals 2026'!J:J,'Goals 2026'!B:B,Smry!D118,'Goals 2026'!C:C,Smry!F118,'Goals 2026'!E:E,Smry!$B$110) -> 0.063 | R118: =SUMIFS('Goals 2026'!K:K,'Goals 2026'!B:B,Smry!D118,'Goals 2026'!C:C,Smry!F118,'Goals 2026'!E:E,Smry!$B$110) -> 0
B119: Cijey M | D119: NH Homestay | F119: NH HS | H119: =SUM(I119:L119) -> 4 | I119: =SUMIFS('Goals 2026'!M:M,'Goals 2026'!B:B,Smry!D119,'Goals 2026'!C:C,Smry!F119,'Goals 2026'!E:E,Smry!$B$110) -> 4 | J119: =SUMIFS('Goals 2026'!N:N,'Goals 2026'!B:B,Smry!D119,'Goals 2026'!C:C,Smry!F119,'Goals 2026'!E:E,Smry!$B$110) -> 0 | K119: =SUMIFS('Goals 2026'!O:O,'Goals 2026'!B:B,Smry!D119,'Goals 2026'!C:C,Smry!F119,'Goals 2026'!E:E,Smry!$B$110) -> 0 | L119: =SUMIFS('Goals 2026'!P:P,'Goals 2026'!B:B,Smry!D119,'Goals 2026'!C:C,Smry!F119,'Goals 2026'!E:E,Smry!$B$110) -> 0 | N119: =SUM(O119:R119) -> 0.77994 | O119: =SUMIFS('Goals 2026'!H:H,'Goals 2026'!B:B,Smry!D119,'Goals 2026'!C:C,Smry!F119,'Goals 2026'!E:E,Smry!$B$110) -> 0.77994 | P119: =SUMIFS('Goals 2026'!I:I,'Goals 2026'!B:B,Smry!D119,'Goals 2026'!C:C,Smry!F119,'Goals 2026'!E:E,Smry!$B$110) -> 0 | Q119: =SUMIFS('Goals 2026'!J:J,'Goals 2026'!B:B,Smry!D119,'Goals 2026'!C:C,Smry!F119,'Goals 2026'!E:E,Smry!$B$110) -> 0 | R119: =SUMIFS('Goals 2026'!K:K,'Goals 2026'!B:B,Smry!D119,'Goals 2026'!C:C,Smry!F119,'Goals 2026'!E:E,Smry!$B$110) -> 0
B120: Cijey M | D120: OTR Museum | F120: OTR Mus | H120: =SUM(I120:L120) -> 8 | I120: =SUMIFS('Goals 2026'!M:M,'Goals 2026'!B:B,Smry!D120,'Goals 2026'!C:C,Smry!F120,'Goals 2026'!E:E,Smry!$B$110) -> 2 | J120: =SUMIFS('Goals 2026'!N:N,'Goals 2026'!B:B,Smry!D120,'Goals 2026'!C:C,Smry!F120,'Goals 2026'!E:E,Smry!$B$110) -> 3 | K120: =SUMIFS('Goals 2026'!O:O,'Goals 2026'!B:B,Smry!D120,'Goals 2026'!C:C,Smry!F120,'Goals 2026'!E:E,Smry!$B$110) -> 3 | L120: =SUMIFS('Goals 2026'!P:P,'Goals 2026'!B:B,Smry!D120,'Goals 2026'!C:C,Smry!F120,'Goals 2026'!E:E,Smry!$B$110) -> 0 | N120: =SUM(O120:R120) -> 1.6718481 | O120: =SUMIFS('Goals 2026'!H:H,'Goals 2026'!B:B,Smry!D120,'Goals 2026'!C:C,Smry!F120,'Goals 2026'!E:E,Smry!$B$110) -> 0.43996002 | P120: =SUMIFS('Goals 2026'!I:I,'Goals 2026'!B:B,Smry!D120,'Goals 2026'!C:C,Smry!F120,'Goals 2026'!E:E,Smry!$B$110) -> 0.67046802 | Q120: =SUMIFS('Goals 2026'!J:J,'Goals 2026'!B:B,Smry!D120,'Goals 2026'!C:C,Smry!F120,'Goals 2026'!E:E,Smry!$B$110) -> 0.56142005 | R120: =SUMIFS('Goals 2026'!K:K,'Goals 2026'!B:B,Smry!D120,'Goals 2026'!C:C,Smry!F120,'Goals 2026'!E:E,Smry!$B$110) -> 0
B121: Cijey M | D121: OTR-Ph02 | F121: Ph 2 | H121: =SUM(I121:L121) -> 12 | I121: =SUMIFS('Goals 2026'!M:M,'Goals 2026'!B:B,Smry!D121,'Goals 2026'!C:C,Smry!F121,'Goals 2026'!E:E,Smry!$B$110) -> 3 | J121: =SUMIFS('Goals 2026'!N:N,'Goals 2026'!B:B,Smry!D121,'Goals 2026'!C:C,Smry!F121,'Goals 2026'!E:E,Smry!$B$110) -> 2 | K121: =SUMIFS('Goals 2026'!O:O,'Goals 2026'!B:B,Smry!D121,'Goals 2026'!C:C,Smry!F121,'Goals 2026'!E:E,Smry!$B$110) -> 3 | L121: =SUMIFS('Goals 2026'!P:P,'Goals 2026'!B:B,Smry!D121,'Goals 2026'!C:C,Smry!F121,'Goals 2026'!E:E,Smry!$B$110) -> 4 | N121: =SUM(O121:R121) -> 4.1876863 | O121: =SUMIFS('Goals 2026'!H:H,'Goals 2026'!B:B,Smry!D121,'Goals 2026'!C:C,Smry!F121,'Goals 2026'!E:E,Smry!$B$110) -> 1.18 | P121: =SUMIFS('Goals 2026'!I:I,'Goals 2026'!B:B,Smry!D121,'Goals 2026'!C:C,Smry!F121,'Goals 2026'!E:E,Smry!$B$110) -> 0.91 | Q121: =SUMIFS('Goals 2026'!J:J,'Goals 2026'!B:B,Smry!D121,'Goals 2026'!C:C,Smry!F121,'Goals 2026'!E:E,Smry!$B$110) -> 0.5163675 | R121: =SUMIFS('Goals 2026'!K:K,'Goals 2026'!B:B,Smry!D121,'Goals 2026'!C:C,Smry!F121,'Goals 2026'!E:E,Smry!$B$110) -> 1.5813188
B122: Cijey M | D122: Srjp - Res | F122: Srjp - Res | H122: =SUM(I122:L122) -> 25 | I122: =SUMIFS('Goals 2026'!M:M,'Goals 2026'!B:B,Smry!D122,'Goals 2026'!C:C,Smry!F122,'Goals 2026'!E:E,Smry!$B$110) -> 4 | J122: =SUMIFS('Goals 2026'!N:N,'Goals 2026'!B:B,Smry!D122,'Goals 2026'!C:C,Smry!F122,'Goals 2026'!E:E,Smry!$B$110) -> 3 | K122: =SUMIFS('Goals 2026'!O:O,'Goals 2026'!B:B,Smry!D122,'Goals 2026'!C:C,Smry!F122,'Goals 2026'!E:E,Smry!$B$110) -> 6 | L122: =SUMIFS('Goals 2026'!P:P,'Goals 2026'!B:B,Smry!D122,'Goals 2026'!C:C,Smry!F122,'Goals 2026'!E:E,Smry!$B$110) -> 12 | N122: =SUM(O122:R122) -> 26.904134 | O122: =SUMIFS('Goals 2026'!H:H,'Goals 2026'!B:B,Smry!D122,'Goals 2026'!C:C,Smry!F122,'Goals 2026'!E:E,Smry!$B$110) -> 13.81055 | P122: =SUMIFS('Goals 2026'!I:I,'Goals 2026'!B:B,Smry!D122,'Goals 2026'!C:C,Smry!F122,'Goals 2026'!E:E,Smry!$B$110) -> 7.1195105 | Q122: =SUMIFS('Goals 2026'!J:J,'Goals 2026'!B:B,Smry!D122,'Goals 2026'!C:C,Smry!F122,'Goals 2026'!E:E,Smry!$B$110) -> 2.0509 | R122: =SUMIFS('Goals 2026'!K:K,'Goals 2026'!B:B,Smry!D122,'Goals 2026'!C:C,Smry!F122,'Goals 2026'!E:E,Smry!$B$110) -> 3.9231735
B124: Om Prakash | H124: =SUM(I124:L124) -> 89 | I124: =SUM(I126:I138) -> 35 | J124: =SUM(J126:J138) -> 20 | K124: =SUM(K126:K138) -> 19 | L124: =SUM(L126:L138) -> 15 | N124: =SUM(O124:R124) -> 24.646343 | O124: =SUM(O126:O138) -> 10.209467 | P124: =SUM(P126:P138) -> 5.7478408 | Q124: =SUM(Q126:Q138) -> 5.1783119 | R124: =SUM(R126:R138) -> 3.5107237
B126: Om Prakash | D126: TuiG | F126: TuiG | H126: =SUM(I126:L126) -> 5 | I126: =SUMIFS('Goals 2026'!M:M,'Goals 2026'!B:B,Smry!D126,'Goals 2026'!C:C,Smry!F126,'Goals 2026'!E:E,Smry!$B$124) -> 2 | J126: =SUMIFS('Goals 2026'!N:N,'Goals 2026'!B:B,Smry!D126,'Goals 2026'!C:C,Smry!F126,'Goals 2026'!E:E,Smry!$B$124) -> 3 | K126: =SUMIFS('Goals 2026'!O:O,'Goals 2026'!B:B,Smry!D126,'Goals 2026'!C:C,Smry!F126,'Goals 2026'!E:E,Smry!$B$124) -> 0 | L126: =SUMIFS('Goals 2026'!P:P,'Goals 2026'!B:B,Smry!D126,'Goals 2026'!C:C,Smry!F126,'Goals 2026'!E:E,Smry!$B$124) -> 0 | N126: =SUM(O126:R126) -> 1.5477548 | O126: =SUMIFS('Goals 2026'!H:H,'Goals 2026'!B:B,Smry!D126,'Goals 2026'!C:C,Smry!F126,'Goals 2026'!E:E,Smry!$B$124) -> 0.30955095 | P126: =SUMIFS('Goals 2026'!I:I,'Goals 2026'!B:B,Smry!D126,'Goals 2026'!C:C,Smry!F126,'Goals 2026'!E:E,Smry!$B$124) -> 1.2382038 | Q126: =SUMIFS('Goals 2026'!J:J,'Goals 2026'!B:B,Smry!D126,'Goals 2026'!C:C,Smry!F126,'Goals 2026'!E:E,Smry!$B$124) -> 0 | R126: =SUMIFS('Goals 2026'!K:K,'Goals 2026'!B:B,Smry!D126,'Goals 2026'!C:C,Smry!F126,'Goals 2026'!E:E,Smry!$B$124) -> 0
B127: Om Prakash | D127: DBTW | F127: DBTW | H127: =SUM(I127:L127) -> 13 | I127: =SUMIFS('Goals 2026'!M:M,'Goals 2026'!B:B,Smry!D127,'Goals 2026'!C:C,Smry!F127,'Goals 2026'!E:E,Smry!$B$124) -> 10 | J127: =SUMIFS('Goals 2026'!N:N,'Goals 2026'!B:B,Smry!D127,'Goals 2026'!C:C,Smry!F127,'Goals 2026'!E:E,Smry!$B$124) -> 0 | K127: =SUMIFS('Goals 2026'!O:O,'Goals 2026'!B:B,Smry!D127,'Goals 2026'!C:C,Smry!F127,'Goals 2026'!E:E,Smry!$B$124) -> 3 | L127: =SUMIFS('Goals 2026'!P:P,'Goals 2026'!B:B,Smry!D127,'Goals 2026'!C:C,Smry!F127,'Goals 2026'!E:E,Smry!$B$124) -> 0 | N127: =SUM(O127:R127) -> 6.1030133 | O127: =SUMIFS('Goals 2026'!H:H,'Goals 2026'!B:B,Smry!D127,'Goals 2026'!C:C,Smry!F127,'Goals 2026'!E:E,Smry!$B$124) -> 5.8780133 | P127: =SUMIFS('Goals 2026'!I:I,'Goals 2026'!B:B,Smry!D127,'Goals 2026'!C:C,Smry!F127,'Goals 2026'!E:E,Smry!$B$124) -> 0 | Q127: =SUMIFS('Goals 2026'!J:J,'Goals 2026'!B:B,Smry!D127,'Goals 2026'!C:C,Smry!F127,'Goals 2026'!E:E,Smry!$B$124) -> 0.225 | R127: =SUMIFS('Goals 2026'!K:K,'Goals 2026'!B:B,Smry!D127,'Goals 2026'!C:C,Smry!F127,'Goals 2026'!E:E,Smry!$B$124) -> 0
B128: Om Prakash | D128: SftW | F128: SftW | H128: =SUM(I128:L128) -> 14 | I128: =SUMIFS('Goals 2026'!M:M,'Goals 2026'!B:B,Smry!D128,'Goals 2026'!C:C,Smry!F128,'Goals 2026'!E:E,Smry!$B$124) -> 9 | J128: =SUMIFS('Goals 2026'!N:N,'Goals 2026'!B:B,Smry!D128,'Goals 2026'!C:C,Smry!F128,'Goals 2026'!E:E,Smry!$B$124) -> 5 | K128: =SUMIFS('Goals 2026'!O:O,'Goals 2026'!B:B,Smry!D128,'Goals 2026'!C:C,Smry!F128,'Goals 2026'!E:E,Smry!$B$124) -> 0 | L128: =SUMIFS('Goals 2026'!P:P,'Goals 2026'!B:B,Smry!D128,'Goals 2026'!C:C,Smry!F128,'Goals 2026'!E:E,Smry!$B$124) -> 0 | N128: =SUM(O128:R128) -> 1.7047642 | O128: =SUMIFS('Goals 2026'!H:H,'Goals 2026'!B:B,Smry!D128,'Goals 2026'!C:C,Smry!F128,'Goals 2026'!E:E,Smry!$B$124) -> 0.85178143 | P128: =SUMIFS('Goals 2026'!I:I,'Goals 2026'!B:B,Smry!D128,'Goals 2026'!C:C,Smry!F128,'Goals 2026'!E:E,Smry!$B$124) -> 0.85298281 | Q128: =SUMIFS('Goals 2026'!J:J,'Goals 2026'!B:B,Smry!D128,'Goals 2026'!C:C,Smry!F128,'Goals 2026'!E:E,Smry!$B$124) -> 0 | R128: =SUMIFS('Goals 2026'!K:K,'Goals 2026'!B:B,Smry!D128,'Goals 2026'!C:C,Smry!F128,'Goals 2026'!E:E,Smry!$B$124) -> 0
B129: Om Prakash | D129: LGCE Campus | F129: LGCE Campus | H129: =SUM(I129:L129) -> 8 | I129: =SUMIFS('Goals 2026'!M:M,'Goals 2026'!B:B,Smry!D129,'Goals 2026'!C:C,Smry!F129,'Goals 2026'!E:E,Smry!$B$124) -> 2 | J129: =SUMIFS('Goals 2026'!N:N,'Goals 2026'!B:B,Smry!D129,'Goals 2026'!C:C,Smry!F129,'Goals 2026'!E:E,Smry!$B$124) -> 2 | K129: =SUMIFS('Goals 2026'!O:O,'Goals 2026'!B:B,Smry!D129,'Goals 2026'!C:C,Smry!F129,'Goals 2026'!E:E,Smry!$B$124) -> 3 | L129: =SUMIFS('Goals 2026'!P:P,'Goals 2026'!B:B,Smry!D129,'Goals 2026'!C:C,Smry!F129,'Goals 2026'!E:E,Smry!$B$124) -> 1 | N129: =SUM(O129:R129) -> 1.4455876 | O129: =SUMIFS('Goals 2026'!H:H,'Goals 2026'!B:B,Smry!D129,'Goals 2026'!C:C,Smry!F129,'Goals 2026'!E:E,Smry!$B$124) -> 0.3804178 | P129: =SUMIFS('Goals 2026'!I:I,'Goals 2026'!B:B,Smry!D129,'Goals 2026'!C:C,Smry!F129,'Goals 2026'!E:E,Smry!$B$124) -> 0.30433424 | Q129: =SUMIFS('Goals 2026'!J:J,'Goals 2026'!B:B,Smry!D129,'Goals 2026'!C:C,Smry!F129,'Goals 2026'!E:E,Smry!$B$124) -> 0.56917532 | R129: =SUMIFS('Goals 2026'!K:K,'Goals 2026'!B:B,Smry!D129,'Goals 2026'!C:C,Smry!F129,'Goals 2026'!E:E,Smry!$B$124) -> 0.19166028
B130: Om Prakash | D130: Srjp - Res | F130: Srjp - Res | H130: =SUM(I130:L130) -> 4 | I130: =SUMIFS('Goals 2026'!M:M,'Goals 2026'!B:B,Smry!D130,'Goals 2026'!C:C,Smry!F130,'Goals 2026'!E:E,Smry!$B$124) -> 2 | J130: =SUMIFS('Goals 2026'!N:N,'Goals 2026'!B:B,Smry!D130,'Goals 2026'!C:C,Smry!F130,'Goals 2026'!E:E,Smry!$B$124) -> 1 | K130: =SUMIFS('Goals 2026'!O:O,'Goals 2026'!B:B,Smry!D130,'Goals 2026'!C:C,Smry!F130,'Goals 2026'!E:E,Smry!$B$124) -> 1 | L130: =SUMIFS('Goals 2026'!P:P,'Goals 2026'!B:B,Smry!D130,'Goals 2026'!C:C,Smry!F130,'Goals 2026'!E:E,Smry!$B$124) -> 0 | N130: =SUM(O130:R130) -> 1.2318 | O130: =SUMIFS('Goals 2026'!H:H,'Goals 2026'!B:B,Smry!D130,'Goals 2026'!C:C,Smry!F130,'Goals 2026'!E:E,Smry!$B$124) -> 0.51325 | P130: =SUMIFS('Goals 2026'!I:I,'Goals 2026'!B:B,Smry!D130,'Goals 2026'!C:C,Smry!F130,'Goals 2026'!E:E,Smry!$B$124) -> 0.4106 | Q130: =SUMIFS('Goals 2026'!J:J,'Goals 2026'!B:B,Smry!D130,'Goals 2026'!C:C,Smry!F130,'Goals 2026'!E:E,Smry!$B$124) -> 0.30795 | R130: =SUMIFS('Goals 2026'!K:K,'Goals 2026'!B:B,Smry!D130,'Goals 2026'!C:C,Smry!F130,'Goals 2026'!E:E,Smry!$B$124) -> 0
B131: Om Prakash | D131: OTF | F131: OTF | H131: =SUM(I131:L131) -> 4 | I131: =SUMIFS('Goals 2026'!M:M,'Goals 2026'!B:B,Smry!D131,'Goals 2026'!C:C,Smry!F131,'Goals 2026'!E:E,Smry!$B$124) -> 3 | J131: =SUMIFS('Goals 2026'!N:N,'Goals 2026'!B:B,Smry!D131,'Goals 2026'!C:C,Smry!F131,'Goals 2026'!E:E,Smry!$B$124) -> 0 | K131: =SUMIFS('Goals 2026'!O:O,'Goals 2026'!B:B,Smry!D131,'Goals 2026'!C:C,Smry!F131,'Goals 2026'!E:E,Smry!$B$124) -> 1 | L131: =SUMIFS('Goals 2026'!P:P,'Goals 2026'!B:B,Smry!D131,'Goals 2026'!C:C,Smry!F131,'Goals 2026'!E:E,Smry!$B$124) -> 0 | N131: =SUM(O131:R131) -> 0.4275 | O131: =SUMIFS('Goals 2026'!H:H,'Goals 2026'!B:B,Smry!D131,'Goals 2026'!C:C,Smry!F131,'Goals 2026'!E:E,Smry!$B$124) -> 0.285 | P131: =SUMIFS('Goals 2026'!I:I,'Goals 2026'!B:B,Smry!D131,'Goals 2026'!C:C,Smry!F131,'Goals 2026'!E:E,Smry!$B$124) -> 0 | Q131: =SUMIFS('Goals 2026'!J:J,'Goals 2026'!B:B,Smry!D131,'Goals 2026'!C:C,Smry!F131,'Goals 2026'!E:E,Smry!$B$124) -> 0.1425 | R131: =SUMIFS('Goals 2026'!K:K,'Goals 2026'!B:B,Smry!D131,'Goals 2026'!C:C,Smry!F131,'Goals 2026'!E:E,Smry!$B$124) -> 0
B132: Om Prakash | D132: Harohalli [Plotted] | F132: Ph 1 | H132: =SUM(I132:L132) -> 3 | I132: =SUMIFS('Goals 2026'!M:M,'Goals 2026'!B:B,Smry!D132,'Goals 2026'!C:C,Smry!F132,'Goals 2026'!E:E,Smry!$B$124) -> 0 | J132: =SUMIFS('Goals 2026'!N:N,'Goals 2026'!B:B,Smry!D132,'Goals 2026'!C:C,Smry!F132,'Goals 2026'!E:E,Smry!$B$124) -> 1 | K132: =SUMIFS('Goals 2026'!O:O,'Goals 2026'!B:B,Smry!D132,'Goals 2026'!C:C,Smry!F132,'Goals 2026'!E:E,Smry!$B$124) -> 1 | L132: =SUMIFS('Goals 2026'!P:P,'Goals 2026'!B:B,Smry!D132,'Goals 2026'!C:C,Smry!F132,'Goals 2026'!E:E,Smry!$B$124) -> 1 | N132: =SUM(O132:R132) -> 0.915 | O132: =SUMIFS('Goals 2026'!H:H,'Goals 2026'!B:B,Smry!D132,'Goals 2026'!C:C,Smry!F132,'Goals 2026'!E:E,Smry!$B$124) -> 0 | P132: =SUMIFS('Goals 2026'!I:I,'Goals 2026'!B:B,Smry!D132,'Goals 2026'!C:C,Smry!F132,'Goals 2026'!E:E,Smry!$B$124) -> 0.305 | Q132: =SUMIFS('Goals 2026'!J:J,'Goals 2026'!B:B,Smry!D132,'Goals 2026'!C:C,Smry!F132,'Goals 2026'!E:E,Smry!$B$124) -> 0.305 | R132: =SUMIFS('Goals 2026'!K:K,'Goals 2026'!B:B,Smry!D132,'Goals 2026'!C:C,Smry!F132,'Goals 2026'!E:E,Smry!$B$124) -> 0.305
B133: Om Prakash | D133: Shreegaon [70a] | F133: Ph 1 | H133: =SUM(I133:L133) -> 4 | I133: =SUMIFS('Goals 2026'!M:M,'Goals 2026'!B:B,Smry!D133,'Goals 2026'!C:C,Smry!F133,'Goals 2026'!E:E,Smry!$B$124) -> 1 | J133: =SUMIFS('Goals 2026'!N:N,'Goals 2026'!B:B,Smry!D133,'Goals 2026'!C:C,Smry!F133,'Goals 2026'!E:E,Smry!$B$124) -> 1 | K133: =SUMIFS('Goals 2026'!O:O,'Goals 2026'!B:B,Smry!D133,'Goals 2026'!C:C,Smry!F133,'Goals 2026'!E:E,Smry!$B$124) -> 1 | L133: =SUMIFS('Goals 2026'!P:P,'Goals 2026'!B:B,Smry!D133,'Goals 2026'!C:C,Smry!F133,'Goals 2026'!E:E,Smry!$B$124) -> 1 | N133: =SUM(O133:R133) -> 0.40111323 | O133: =SUMIFS('Goals 2026'!H:H,'Goals 2026'!B:B,Smry!D133,'Goals 2026'!C:C,Smry!F133,'Goals 2026'!E:E,Smry!$B$124) -> 0.089136274 | P133: =SUMIFS('Goals 2026'!I:I,'Goals 2026'!B:B,Smry!D133,'Goals 2026'!C:C,Smry!F133,'Goals 2026'!E:E,Smry!$B$124) -> 0.089136274 | Q133: =SUMIFS('Goals 2026'!J:J,'Goals 2026'!B:B,Smry!D133,'Goals 2026'!C:C,Smry!F133,'Goals 2026'!E:E,Smry!$B$124) -> 0.089136274 | R133: =SUMIFS('Goals 2026'!K:K,'Goals 2026'!B:B,Smry!D133,'Goals 2026'!C:C,Smry!F133,'Goals 2026'!E:E,Smry!$B$124) -> 0.13370441
B134: Om Prakash | D134: Violet hill | F134: Ph 1 | H134: =SUM(I134:L134) -> 8 | I134: =SUMIFS('Goals 2026'!M:M,'Goals 2026'!B:B,Smry!D134,'Goals 2026'!C:C,Smry!F134,'Goals 2026'!E:E,Smry!$B$124) -> 1 | J134: =SUMIFS('Goals 2026'!N:N,'Goals 2026'!B:B,Smry!D134,'Goals 2026'!C:C,Smry!F134,'Goals 2026'!E:E,Smry!$B$124) -> 2 | K134: =SUMIFS('Goals 2026'!O:O,'Goals 2026'!B:B,Smry!D134,'Goals 2026'!C:C,Smry!F134,'Goals 2026'!E:E,Smry!$B$124) -> 1 | L134: =SUMIFS('Goals 2026'!P:P,'Goals 2026'!B:B,Smry!D134,'Goals 2026'!C:C,Smry!F134,'Goals 2026'!E:E,Smry!$B$124) -> 4 | N134: =SUM(O134:R134) -> 0.46573481 | O134: =SUMIFS('Goals 2026'!H:H,'Goals 2026'!B:B,Smry!D134,'Goals 2026'!C:C,Smry!F134,'Goals 2026'!E:E,Smry!$B$124) -> 0.058216851 | P134: =SUMIFS('Goals 2026'!I:I,'Goals 2026'!B:B,Smry!D134,'Goals 2026'!C:C,Smry!F134,'Goals 2026'!E:E,Smry!$B$124) -> 0.1164337 | Q134: =SUMIFS('Goals 2026'!J:J,'Goals 2026'!B:B,Smry!D134,'Goals 2026'!C:C,Smry!F134,'Goals 2026'!E:E,Smry!$B$124) -> 0.087325276 | R134: =SUMIFS('Goals 2026'!K:K,'Goals 2026'!B:B,Smry!D134,'Goals 2026'!C:C,Smry!F134,'Goals 2026'!E:E,Smry!$B$124) -> 0.20375898
B135: Om Prakash | D135: Ambegaon | F135: Ph 1 | H135: =SUM(I135:L135) -> 3 | I135: =SUMIFS('Goals 2026'!M:M,'Goals 2026'!B:B,Smry!D135,'Goals 2026'!C:C,Smry!F135,'Goals 2026'!E:E,Smry!$B$124) -> 0 | J135: =SUMIFS('Goals 2026'!N:N,'Goals 2026'!B:B,Smry!D135,'Goals 2026'!C:C,Smry!F135,'Goals 2026'!E:E,Smry!$B$124) -> 0 | K135: =SUMIFS('Goals 2026'!O:O,'Goals 2026'!B:B,Smry!D135,'Goals 2026'!C:C,Smry!F135,'Goals 2026'!E:E,Smry!$B$124) -> 2 | L135: =SUMIFS('Goals 2026'!P:P,'Goals 2026'!B:B,Smry!D135,'Goals 2026'!C:C,Smry!F135,'Goals 2026'!E:E,Smry!$B$124) -> 1 | N135: =SUM(O135:R135) -> 0.57 | O135: =SUMIFS('Goals 2026'!H:H,'Goals 2026'!B:B,Smry!D135,'Goals 2026'!C:C,Smry!F135,'Goals 2026'!E:E,Smry!$B$124) -> 0 | P135: =SUMIFS('Goals 2026'!I:I,'Goals 2026'!B:B,Smry!D135,'Goals 2026'!C:C,Smry!F135,'Goals 2026'!E:E,Smry!$B$124) -> 0 | Q135: =SUMIFS('Goals 2026'!J:J,'Goals 2026'!B:B,Smry!D135,'Goals 2026'!C:C,Smry!F135,'Goals 2026'!E:E,Smry!$B$124) -> 0.38 | R135: =SUMIFS('Goals 2026'!K:K,'Goals 2026'!B:B,Smry!D135,'Goals 2026'!C:C,Smry!F135,'Goals 2026'!E:E,Smry!$B$124) -> 0.19
B136: Om Prakash | D136: Mall of Asia | F136: Mall of Asia | H136: =SUM(I136:L136) -> 9 | I136: =SUMIFS('Goals 2026'!M:M,'Goals 2026'!B:B,Smry!D136,'Goals 2026'!C:C,Smry!F136,'Goals 2026'!E:E,Smry!$B$124) -> 1 | J136: =SUMIFS('Goals 2026'!N:N,'Goals 2026'!B:B,Smry!D136,'Goals 2026'!C:C,Smry!F136,'Goals 2026'!E:E,Smry!$B$124) -> 4 | K136: =SUMIFS('Goals 2026'!O:O,'Goals 2026'!B:B,Smry!D136,'Goals 2026'!C:C,Smry!F136,'Goals 2026'!E:E,Smry!$B$124) -> 2 | L136: =SUMIFS('Goals 2026'!P:P,'Goals 2026'!B:B,Smry!D136,'Goals 2026'!C:C,Smry!F136,'Goals 2026'!E:E,Smry!$B$124) -> 2 | N136: =SUM(O136:R136) -> 7.26345 | O136: =SUMIFS('Goals 2026'!H:H,'Goals 2026'!B:B,Smry!D136,'Goals 2026'!C:C,Smry!F136,'Goals 2026'!E:E,Smry!$B$124) -> 1.6141 | P136: =SUMIFS('Goals 2026'!I:I,'Goals 2026'!B:B,Smry!D136,'Goals 2026'!C:C,Smry!F136,'Goals 2026'!E:E,Smry!$B$124) -> 2.42115 | Q136: =SUMIFS('Goals 2026'!J:J,'Goals 2026'!B:B,Smry!D136,'Goals 2026'!C:C,Smry!F136,'Goals 2026'!E:E,Smry!$B$124) -> 1.6141 | R136: =SUMIFS('Goals 2026'!K:K,'Goals 2026'!B:B,Smry!D136,'Goals 2026'!C:C,Smry!F136,'Goals 2026'!E:E,Smry!$B$124) -> 1.6141
B137: Om Prakash | D137: OTR-Ph02 | F137: Ph 2 | H137: =SUM(I137:L137) -> 8 | I137: =SUMIFS('Goals 2026'!M:M,'Goals 2026'!B:B,Smry!D137,'Goals 2026'!C:C,Smry!F137,'Goals 2026'!E:E,Smry!$B$124) -> 2 | J137: =SUMIFS('Goals 2026'!N:N,'Goals 2026'!B:B,Smry!D137,'Goals 2026'!C:C,Smry!F137,'Goals 2026'!E:E,Smry!$B$124) -> 0 | K137: =SUMIFS('Goals 2026'!O:O,'Goals 2026'!B:B,Smry!D137,'Goals 2026'!C:C,Smry!F137,'Goals 2026'!E:E,Smry!$B$124) -> 3 | L137: =SUMIFS('Goals 2026'!P:P,'Goals 2026'!B:B,Smry!D137,'Goals 2026'!C:C,Smry!F137,'Goals 2026'!E:E,Smry!$B$124) -> 3 | N137: =SUM(O137:R137) -> 2.400625 | O137: =SUMIFS('Goals 2026'!H:H,'Goals 2026'!B:B,Smry!D137,'Goals 2026'!C:C,Smry!F137,'Goals 2026'!E:E,Smry!$B$124) -> 0.17 | P137: =SUMIFS('Goals 2026'!I:I,'Goals 2026'!B:B,Smry!D137,'Goals 2026'!C:C,Smry!F137,'Goals 2026'!E:E,Smry!$B$124) -> 0 | Q137: =SUMIFS('Goals 2026'!J:J,'Goals 2026'!B:B,Smry!D137,'Goals 2026'!C:C,Smry!F137,'Goals 2026'!E:E,Smry!$B$124) -> 1.420625 | R137: =SUMIFS('Goals 2026'!K:K,'Goals 2026'!B:B,Smry!D137,'Goals 2026'!C:C,Smry!F137,'Goals 2026'!E:E,Smry!$B$124) -> 0.81
B138: Om Prakash | D138: DonaPaula | F138: DP | H138: =SUM(I138:L138) -> 6 | I138: =SUMIFS('Goals 2026'!M:M,'Goals 2026'!B:B,Smry!D138,'Goals 2026'!C:C,Smry!F138,'Goals 2026'!E:E,Smry!$B$124) -> 2 | J138: =SUMIFS('Goals 2026'!N:N,'Goals 2026'!B:B,Smry!D138,'Goals 2026'!C:C,Smry!F138,'Goals 2026'!E:E,Smry!$B$124) -> 1 | K138: =SUMIFS('Goals 2026'!O:O,'Goals 2026'!B:B,Smry!D138,'Goals 2026'!C:C,Smry!F138,'Goals 2026'!E:E,Smry!$B$124) -> 1 | L138: =SUMIFS('Goals 2026'!P:P,'Goals 2026'!B:B,Smry!D138,'Goals 2026'!C:C,Smry!F138,'Goals 2026'!E:E,Smry!$B$124) -> 2 | N138: =SUM(O138:R138) -> 0.17 | O138: =SUMIFS('Goals 2026'!H:H,'Goals 2026'!B:B,Smry!D138,'Goals 2026'!C:C,Smry!F138,'Goals 2026'!E:E,Smry!$B$124) -> 0.06 | P138: =SUMIFS('Goals 2026'!I:I,'Goals 2026'!B:B,Smry!D138,'Goals 2026'!C:C,Smry!F138,'Goals 2026'!E:E,Smry!$B$124) -> 0.01 | Q138: =SUMIFS('Goals 2026'!J:J,'Goals 2026'!B:B,Smry!D138,'Goals 2026'!C:C,Smry!F138,'Goals 2026'!E:E,Smry!$B$124) -> 0.0375 | R138: =SUMIFS('Goals 2026'!K:K,'Goals 2026'!B:B,Smry!D138,'Goals 2026'!C:C,Smry!F138,'Goals 2026'!E:E,Smry!$B$124) -> 0.0625
B140: Manik G | H140: =SUM(I140:L140) -> 33 | I140: =SUM(I142:I145) -> 15 | J140: =SUM(J142:J145) -> 10 | K140: =SUM(K142:K145) -> 8 | L140: =SUM(L142:L145) -> 0 | N140: =SUM(O140:R140) -> 2.5445163 | O140: =SUM(O142:O145) -> 0.85280447 | P140: =SUM(P142:P145) -> 0.96170694 | Q140: =SUM(Q142:Q145) -> 0.73000493 | R140: =SUM(R142:R145) -> 0
B142: Manik G | D142: Ooty Res | F142: Ooty Res | H142: =SUM(I142:L142) -> 0 | I142: =SUMIFS('Goals 2026'!M:M,'Goals 2026'!B:B,Smry!D142,'Goals 2026'!C:C,Smry!F142,'Goals 2026'!E:E,Smry!$B$140) -> 0 | J142: =SUMIFS('Goals 2026'!N:N,'Goals 2026'!B:B,Smry!D142,'Goals 2026'!C:C,Smry!F142,'Goals 2026'!E:E,Smry!$B$140) -> 0 | K142: =SUMIFS('Goals 2026'!O:O,'Goals 2026'!B:B,Smry!D142,'Goals 2026'!C:C,Smry!F142,'Goals 2026'!E:E,Smry!$B$140) -> 0 | L142: =SUMIFS('Goals 2026'!P:P,'Goals 2026'!B:B,Smry!D142,'Goals 2026'!C:C,Smry!F142,'Goals 2026'!E:E,Smry!$B$140) -> 0 | N142: =SUM(O142:R142) -> 0 | O142: =SUMIFS('Goals 2026'!H:H,'Goals 2026'!B:B,Smry!D142,'Goals 2026'!C:C,Smry!F142,'Goals 2026'!E:E,Smry!$B$140) -> 0 | P142: =SUMIFS('Goals 2026'!I:I,'Goals 2026'!B:B,Smry!D142,'Goals 2026'!C:C,Smry!F142,'Goals 2026'!E:E,Smry!$B$140) -> 0 | Q142: =SUMIFS('Goals 2026'!J:J,'Goals 2026'!B:B,Smry!D142,'Goals 2026'!C:C,Smry!F142,'Goals 2026'!E:E,Smry!$B$140) -> 0 | R142: =SUMIFS('Goals 2026'!K:K,'Goals 2026'!B:B,Smry!D142,'Goals 2026'!C:C,Smry!F142,'Goals 2026'!E:E,Smry!$B$140) -> 0
B143: Manik G | D143: MT Plano | F143: MT Plano | H143: =SUM(I143:L143) -> 21 | I143: =SUMIFS('Goals 2026'!M:M,'Goals 2026'!B:B,Smry!D143,'Goals 2026'!C:C,Smry!F143,'Goals 2026'!E:E,Smry!$B$140) -> 8 | J143: =SUMIFS('Goals 2026'!N:N,'Goals 2026'!B:B,Smry!D143,'Goals 2026'!C:C,Smry!F143,'Goals 2026'!E:E,Smry!$B$140) -> 7 | K143: =SUMIFS('Goals 2026'!O:O,'Goals 2026'!B:B,Smry!D143,'Goals 2026'!C:C,Smry!F143,'Goals 2026'!E:E,Smry!$B$140) -> 6 | L143: =SUMIFS('Goals 2026'!P:P,'Goals 2026'!B:B,Smry!D143,'Goals 2026'!C:C,Smry!F143,'Goals 2026'!E:E,Smry!$B$140) -> 0 | N143: =SUM(O143:R143) -> 2.1239859 | O143: =SUMIFS('Goals 2026'!H:H,'Goals 2026'!B:B,Smry!D143,'Goals 2026'!C:C,Smry!F143,'Goals 2026'!E:E,Smry!$B$140) -> 0.69534587 | P143: =SUMIFS('Goals 2026'!I:I,'Goals 2026'!B:B,Smry!D143,'Goals 2026'!C:C,Smry!F143,'Goals 2026'!E:E,Smry!$B$140) -> 0.80026162 | Q143: =SUMIFS('Goals 2026'!J:J,'Goals 2026'!B:B,Smry!D143,'Goals 2026'!C:C,Smry!F143,'Goals 2026'!E:E,Smry!$B$140) -> 0.62837837 | R143: =SUMIFS('Goals 2026'!K:K,'Goals 2026'!B:B,Smry!D143,'Goals 2026'!C:C,Smry!F143,'Goals 2026'!E:E,Smry!$B$140) -> 0
B144: Manik G | D144: Indiranagar Res | F144: Indrng Res | H144: =SUM(I144:L144) -> 4 | I144: =SUMIFS('Goals 2026'!M:M,'Goals 2026'!B:B,Smry!D144,'Goals 2026'!C:C,Smry!F144,'Goals 2026'!E:E,Smry!$B$140) -> 4 | J144: =SUMIFS('Goals 2026'!N:N,'Goals 2026'!B:B,Smry!D144,'Goals 2026'!C:C,Smry!F144,'Goals 2026'!E:E,Smry!$B$140) -> 0 | K144: =SUMIFS('Goals 2026'!O:O,'Goals 2026'!B:B,Smry!D144,'Goals 2026'!C:C,Smry!F144,'Goals 2026'!E:E,Smry!$B$140) -> 0 | L144: =SUMIFS('Goals 2026'!P:P,'Goals 2026'!B:B,Smry!D144,'Goals 2026'!C:C,Smry!F144,'Goals 2026'!E:E,Smry!$B$140) -> 0 | N144: =SUM(O144:R144) -> 0.004 | O144: =SUMIFS('Goals 2026'!H:H,'Goals 2026'!B:B,Smry!D144,'Goals 2026'!C:C,Smry!F144,'Goals 2026'!E:E,Smry!$B$140) -> 0.004 | P144: =SUMIFS('Goals 2026'!I:I,'Goals 2026'!B:B,Smry!D144,'Goals 2026'!C:C,Smry!F144,'Goals 2026'!E:E,Smry!$B$140) -> 0 | Q144: =SUMIFS('Goals 2026'!J:J,'Goals 2026'!B:B,Smry!D144,'Goals 2026'!C:C,Smry!F144,'Goals 2026'!E:E,Smry!$B$140) -> 0 | R144: =SUMIFS('Goals 2026'!K:K,'Goals 2026'!B:B,Smry!D144,'Goals 2026'!C:C,Smry!F144,'Goals 2026'!E:E,Smry!$B$140) -> 0
B145: Manik G | D145: OTR OOTA | F145: OTR OOTA | H145: =SUM(I145:L145) -> 8 | I145: =SUMIFS('Goals 2026'!M:M,'Goals 2026'!B:B,Smry!D145,'Goals 2026'!C:C,Smry!F145,'Goals 2026'!E:E,Smry!$B$140) -> 3 | J145: =SUMIFS('Goals 2026'!N:N,'Goals 2026'!B:B,Smry!D145,'Goals 2026'!C:C,Smry!F145,'Goals 2026'!E:E,Smry!$B$140) -> 3 | K145: =SUMIFS('Goals 2026'!O:O,'Goals 2026'!B:B,Smry!D145,'Goals 2026'!C:C,Smry!F145,'Goals 2026'!E:E,Smry!$B$140) -> 2 | L145: =SUMIFS('Goals 2026'!P:P,'Goals 2026'!B:B,Smry!D145,'Goals 2026'!C:C,Smry!F145,'Goals 2026'!E:E,Smry!$B$140) -> 0 | N145: =SUM(O145:R145) -> 0.41653046 | O145: =SUMIFS('Goals 2026'!H:H,'Goals 2026'!B:B,Smry!D145,'Goals 2026'!C:C,Smry!F145,'Goals 2026'!E:E,Smry!$B$140) -> 0.15345859 | P145: =SUMIFS('Goals 2026'!I:I,'Goals 2026'!B:B,Smry!D145,'Goals 2026'!C:C,Smry!F145,'Goals 2026'!E:E,Smry!$B$140) -> 0.16144531 | Q145: =SUMIFS('Goals 2026'!J:J,'Goals 2026'!B:B,Smry!D145,'Goals 2026'!C:C,Smry!F145,'Goals 2026'!E:E,Smry!$B$140) -> 0.10162656 | R145: =SUMIFS('Goals 2026'!K:K,'Goals 2026'!B:B,Smry!D145,'Goals 2026'!C:C,Smry!F145,'Goals 2026'!E:E,Smry!$B$140) -> 0
B147: Atul P | H147: =SUM(I147:L147) -> 11 | I147: =SUM(I149:I153) -> 11 | J147: =SUM(J149:J153) -> 0 | K147: =SUM(K149:K153) -> 0 | L147: =SUM(L149:L153) -> 0 | N147: =SUM(O147:R147) -> 0 | O147: =SUM(O149:O153) -> 0 | P147: =SUM(P149:P153) -> 0 | Q147: =SUM(Q149:Q153) -> 0 | R147: =SUM(R149:R153) -> 0
B149: Atul P | D149: TuiG | F149: FKH | H149: =SUM(I149:L149) -> 3 | I149: =SUMIFS('Goals 2026'!M:M,'Goals 2026'!B:B,Smry!D149,'Goals 2026'!C:C,Smry!F149,'Goals 2026'!E:E,Smry!$B$147) -> 3 | J149: =SUMIFS('Goals 2026'!N:N,'Goals 2026'!B:B,Smry!D149,'Goals 2026'!C:C,Smry!F149,'Goals 2026'!E:E,Smry!$B$147) -> 0 | K149: =SUMIFS('Goals 2026'!O:O,'Goals 2026'!B:B,Smry!D149,'Goals 2026'!C:C,Smry!F149,'Goals 2026'!E:E,Smry!$B$147) -> 0 | L149: =SUMIFS('Goals 2026'!P:P,'Goals 2026'!B:B,Smry!D149,'Goals 2026'!C:C,Smry!F149,'Goals 2026'!E:E,Smry!$B$147) -> 0 | N149: =SUM(O149:R149) -> 0 | O149: =SUMIFS('Goals 2026'!H:H,'Goals 2026'!B:B,Smry!D149,'Goals 2026'!C:C,Smry!F149,'Goals 2026'!E:E,Smry!$B$147) -> 0 | P149: =SUMIFS('Goals 2026'!I:I,'Goals 2026'!B:B,Smry!D149,'Goals 2026'!C:C,Smry!F149,'Goals 2026'!E:E,Smry!$B$147) -> 0 | Q149: =SUMIFS('Goals 2026'!J:J,'Goals 2026'!B:B,Smry!D149,'Goals 2026'!C:C,Smry!F149,'Goals 2026'!E:E,Smry!$B$147) -> 0 | R149: =SUMIFS('Goals 2026'!K:K,'Goals 2026'!B:B,Smry!D149,'Goals 2026'!C:C,Smry!F149,'Goals 2026'!E:E,Smry!$B$147) -> 0
B150: Atul P | D150: Harohalli | F150: FKH | H150: =SUM(I150:L150) -> 3 | I150: =SUMIFS('Goals 2026'!M:M,'Goals 2026'!B:B,Smry!D150,'Goals 2026'!C:C,Smry!F150,'Goals 2026'!E:E,Smry!$B$147) -> 3 | J150: =SUMIFS('Goals 2026'!N:N,'Goals 2026'!B:B,Smry!D150,'Goals 2026'!C:C,Smry!F150,'Goals 2026'!E:E,Smry!$B$147) -> 0 | K150: =SUMIFS('Goals 2026'!O:O,'Goals 2026'!B:B,Smry!D150,'Goals 2026'!C:C,Smry!F150,'Goals 2026'!E:E,Smry!$B$147) -> 0 | L150: =SUMIFS('Goals 2026'!P:P,'Goals 2026'!B:B,Smry!D150,'Goals 2026'!C:C,Smry!F150,'Goals 2026'!E:E,Smry!$B$147) -> 0 | N150: =SUM(O150:R150) -> 0 | O150: =SUMIFS('Goals 2026'!H:H,'Goals 2026'!B:B,Smry!D150,'Goals 2026'!C:C,Smry!F150,'Goals 2026'!E:E,Smry!$B$147) -> 0 | P150: =SUMIFS('Goals 2026'!I:I,'Goals 2026'!B:B,Smry!D150,'Goals 2026'!C:C,Smry!F150,'Goals 2026'!E:E,Smry!$B$147) -> 0 | Q150: =SUMIFS('Goals 2026'!J:J,'Goals 2026'!B:B,Smry!D150,'Goals 2026'!C:C,Smry!F150,'Goals 2026'!E:E,Smry!$B$147) -> 0 | R150: =SUMIFS('Goals 2026'!K:K,'Goals 2026'!B:B,Smry!D150,'Goals 2026'!C:C,Smry!F150,'Goals 2026'!E:E,Smry!$B$147) -> 0
B151: Atul P | D151: Violet Hill | F151: FKH | H151: =SUM(I151:L151) -> 2 | I151: =SUMIFS('Goals 2026'!M:M,'Goals 2026'!B:B,Smry!D151,'Goals 2026'!C:C,Smry!F151,'Goals 2026'!E:E,Smry!$B$147) -> 2 | J151: =SUMIFS('Goals 2026'!N:N,'Goals 2026'!B:B,Smry!D151,'Goals 2026'!C:C,Smry!F151,'Goals 2026'!E:E,Smry!$B$147) -> 0 | K151: =SUMIFS('Goals 2026'!O:O,'Goals 2026'!B:B,Smry!D151,'Goals 2026'!C:C,Smry!F151,'Goals 2026'!E:E,Smry!$B$147) -> 0 | L151: =SUMIFS('Goals 2026'!P:P,'Goals 2026'!B:B,Smry!D151,'Goals 2026'!C:C,Smry!F151,'Goals 2026'!E:E,Smry!$B$147) -> 0 | N151: =SUM(O151:R151) -> 0 | O151: =SUMIFS('Goals 2026'!H:H,'Goals 2026'!B:B,Smry!D151,'Goals 2026'!C:C,Smry!F151,'Goals 2026'!E:E,Smry!$B$147) -> 0 | P151: =SUMIFS('Goals 2026'!I:I,'Goals 2026'!B:B,Smry!D151,'Goals 2026'!C:C,Smry!F151,'Goals 2026'!E:E,Smry!$B$147) -> 0 | Q151: =SUMIFS('Goals 2026'!J:J,'Goals 2026'!B:B,Smry!D151,'Goals 2026'!C:C,Smry!F151,'Goals 2026'!E:E,Smry!$B$147) -> 0 | R151: =SUMIFS('Goals 2026'!K:K,'Goals 2026'!B:B,Smry!D151,'Goals 2026'!C:C,Smry!F151,'Goals 2026'!E:E,Smry!$B$147) -> 0
B152: Atul P | D152: Shreegaon | F152: FKH | H152: =SUM(I152:L152) -> 1 | I152: =SUMIFS('Goals 2026'!M:M,'Goals 2026'!B:B,Smry!D152,'Goals 2026'!C:C,Smry!F152,'Goals 2026'!E:E,Smry!$B$147) -> 1 | J152: =SUMIFS('Goals 2026'!N:N,'Goals 2026'!B:B,Smry!D152,'Goals 2026'!C:C,Smry!F152,'Goals 2026'!E:E,Smry!$B$147) -> 0 | K152: =SUMIFS('Goals 2026'!O:O,'Goals 2026'!B:B,Smry!D152,'Goals 2026'!C:C,Smry!F152,'Goals 2026'!E:E,Smry!$B$147) -> 0 | L152: =SUMIFS('Goals 2026'!P:P,'Goals 2026'!B:B,Smry!D152,'Goals 2026'!C:C,Smry!F152,'Goals 2026'!E:E,Smry!$B$147) -> 0 | N152: =SUM(O152:R152) -> 0 | O152: =SUMIFS('Goals 2026'!H:H,'Goals 2026'!B:B,Smry!D152,'Goals 2026'!C:C,Smry!F152,'Goals 2026'!E:E,Smry!$B$147) -> 0 | P152: =SUMIFS('Goals 2026'!I:I,'Goals 2026'!B:B,Smry!D152,'Goals 2026'!C:C,Smry!F152,'Goals 2026'!E:E,Smry!$B$147) -> 0 | Q152: =SUMIFS('Goals 2026'!J:J,'Goals 2026'!B:B,Smry!D152,'Goals 2026'!C:C,Smry!F152,'Goals 2026'!E:E,Smry!$B$147) -> 0 | R152: =SUMIFS('Goals 2026'!K:K,'Goals 2026'!B:B,Smry!D152,'Goals 2026'!C:C,Smry!F152,'Goals 2026'!E:E,Smry!$B$147) -> 0
B153: Atul P | D153: OTF | F153: FKH | H153: =SUM(I153:L153) -> 2 | I153: =SUMIFS('Goals 2026'!M:M,'Goals 2026'!B:B,Smry!D153,'Goals 2026'!C:C,Smry!F153,'Goals 2026'!E:E,Smry!$B$147) -> 2 | J153: =SUMIFS('Goals 2026'!N:N,'Goals 2026'!B:B,Smry!D153,'Goals 2026'!C:C,Smry!F153,'Goals 2026'!E:E,Smry!$B$147) -> 0 | K153: =SUMIFS('Goals 2026'!O:O,'Goals 2026'!B:B,Smry!D153,'Goals 2026'!C:C,Smry!F153,'Goals 2026'!E:E,Smry!$B$147) -> 0 | L153: =SUMIFS('Goals 2026'!P:P,'Goals 2026'!B:B,Smry!D153,'Goals 2026'!C:C,Smry!F153,'Goals 2026'!E:E,Smry!$B$147) -> 0 | N153: =SUM(O153:R153) -> 0 | O153: =SUMIFS('Goals 2026'!H:H,'Goals 2026'!B:B,Smry!D153,'Goals 2026'!C:C,Smry!F153,'Goals 2026'!E:E,Smry!$B$147) -> 0 | P153: =SUMIFS('Goals 2026'!I:I,'Goals 2026'!B:B,Smry!D153,'Goals 2026'!C:C,Smry!F153,'Goals 2026'!E:E,Smry!$B$147) -> 0 | Q153: =SUMIFS('Goals 2026'!J:J,'Goals 2026'!B:B,Smry!D153,'Goals 2026'!C:C,Smry!F153,'Goals 2026'!E:E,Smry!$B$147) -> 0 | R153: =SUMIFS('Goals 2026'!K:K,'Goals 2026'!B:B,Smry!D153,'Goals 2026'!C:C,Smry!F153,'Goals 2026'!E:E,Smry!$B$147) -> 0
B155: NA | H155: =SUM(I155:L155) -> 0 | I155: =SUM(I157:I160) -> 0 | J155: =SUM(J157:J160) -> 0 | K155: =SUM(K157:K160) -> 0 | L155: =SUM(L157:L160) -> 0 | N155: =SUM(O155:R155) -> 0 | O155: =SUM(O157:O160) -> 0 | P155: =SUM(P157:P160) -> 0 | Q155: =SUM(Q157:Q160) -> 0 | R155: =SUM(R157:R160) -> 0
B157: NA | D157: TR Mills | F157: TR Mills | H157: =SUM(I157:L157) -> 0 | I157: =SUMIFS('Goals 2026'!M:M,'Goals 2026'!B:B,Smry!D157,'Goals 2026'!C:C,Smry!F157,'Goals 2026'!E:E,Smry!$B$155) -> 0 | J157: =SUMIFS('Goals 2026'!N:N,'Goals 2026'!B:B,Smry!D157,'Goals 2026'!C:C,Smry!F157,'Goals 2026'!E:E,Smry!$B$155) -> 0 | K157: =SUMIFS('Goals 2026'!O:O,'Goals 2026'!B:B,Smry!D157,'Goals 2026'!C:C,Smry!F157,'Goals 2026'!E:E,Smry!$B$155) -> 0 | L157: =SUMIFS('Goals 2026'!P:P,'Goals 2026'!B:B,Smry!D157,'Goals 2026'!C:C,Smry!F157,'Goals 2026'!E:E,Smry!$B$155) -> 0 | N157: =SUM(O157:R157) -> 0 | O157: =SUMIFS('Goals 2026'!H:H,'Goals 2026'!B:B,Smry!D157,'Goals 2026'!C:C,Smry!F157,'Goals 2026'!E:E,Smry!$B$155) -> 0 | P157: =SUMIFS('Goals 2026'!I:I,'Goals 2026'!B:B,Smry!D157,'Goals 2026'!C:C,Smry!F157,'Goals 2026'!E:E,Smry!$B$155) -> 0 | Q157: =SUMIFS('Goals 2026'!J:J,'Goals 2026'!B:B,Smry!D157,'Goals 2026'!C:C,Smry!F157,'Goals 2026'!E:E,Smry!$B$155) -> 0 | R157: =SUMIFS('Goals 2026'!K:K,'Goals 2026'!B:B,Smry!D157,'Goals 2026'!C:C,Smry!F157,'Goals 2026'!E:E,Smry!$B$155) -> 0

Sheet 26Q1 Actuals Smry
B1: Design Lead | C1: Design Packages | D1: 26Q1 Fee | E1: Actuals | F1: Actual Fees | G1: Remarks
D2: =SUM(D3:D115) -> 112.68299 | E2: =SUM(E3:E112) -> 55 | F2: =SUM(F3:F112) -> 3.5166917
B3: Saji | C3: PoaRR [T8-GFC except Penthouse products, T1-7-GFC] [Pkgs 26] | D3: 10.4
B4: Saji | C4: AtR [1,2a,2b,2c-GFC, P3 Structure] [Pkgs 19] | D4: 2.2 | G4: LoD 350 - Clubhouse + Amenities - Clubhouse—Interiors and Facilities
B5: Cijey | C5: itQE [P2a GFC, 2b-Basements, 2c-Foundations/ Parking, P3-Approvals & Exp Homes][Pkgs 12] | D5: 11.71 | G5: Ph2a -LoD 350 - Master Plan | Site Development, LoD 350 -Experience Home + Project Experience [ V35 ], Ph2b - LoD 350 - L25 Default and it's variants, LoD 350 - ISS 5&6 | Structural Slab 01 [Basement] LoD 350 - ISS 7 | Structrural Slab 01 [Basement], Ph 2c - I20, I25 Experience Homes
B6: Cijey | C6: OtR [P1-GFC, Museum-LOD 200][Pkgs 7] | D6: 1.4 | G6: Ph1 - LoD 350 - Individual Homes | V25 Default & its Variant, LoD 350 - Villa Block | Building Envelope + Plot Development, Museum - Lod 100 - Design Brief
B7: Cijey | C7: Homestay NH GFC [Pkgs 4] | D7: 0.78
B8: Cijey | C8: Sarjapur Road [LOD 200, Approval, Experience Homes] [Pkgs 4] | D8: 13.81 | G8: LoD 100 - Contract + Design Brief
B9: Cijey | C9: Meena Sai [LOD 200, Approvals] [Pkgs 2] | D9: 0.11
B10: Cijey | C10: OtR P2 [LOD 200, Approval] [Pkgs 3] | D10: 1.18 | G10: LoD 100 - Contract + Design Brief
B11: Naveen | C11: AtR Commercial [Complete GFCs] [Pkgs 3] | D11: 0.36
B12: Naveen | C12: TMFT P3 [LOD 200, Approvals] [Pkgs 3] | D12: 0.62
B13: Naveen | C13: Sarjapur C [LOD 200, Approvals] [Pkgs 19] | D13: 14.74 | G13: LoD 100 - Contract + Design Brief
B14: Naveen | C14: OtF [LOD 300, Approvals, Marketing and Proj Exp] [Pkgs 6] | D14: 2.75 | G14: LoD 100 - Contract + Design Brief [Commercial]; LoD 200 - Schematic Concept
B15: Naveen | C15: Imagine [LOD 200, Approvals] [Pkgs 3] | D15: 1.61
B16: OP | C16: DbtW [Complete GFCs-except Clubhouse Interiors and Community spaces] [Pkgs 10] | D16: 5.88 | G16: LoD 350 - ISS - Podium Slab, Home Products - I20 and I25 Default and it's variants, Master Plan - Site Development
B17: OP | C17: SftW [Complete GFCs-except Clubhouse Interiors and Community spaces] [Pkgs 09] | D17: 0.85
B18: OP | C18: TuiG [Clubhouse Outdoor and Community Spaces] [Pkgs 3] | D18: 0.33 | G18: LoD 350 - Clubhouse structure & envelope, Sporting facility
B19: OP | C19: LGCE [LOD 200] [Pkgs 2] | D19: 0.38
B20: OP | C20: OtR P2 [Clubhouse LOD 200 and Approvals] [Pkgs 2] | D20: 0.17
B21: OP | C21: Violet Hill [Clubhouse LOD 200] [Pkgs 1] | D21: 0.06 | G21: LoD 200 - Schematic Concept
B22: OP | C22: OtF [Clubhouse LOD 200 and Approvals] [Pkgs 3] | D22: 0.29 | G22: LoD 200 - Schematic Concept - CH
B23: OP | C23: Sarjapur Rd [Clubhouse LOD 200 and Approvals] [Pkgs 2] | D23: 0.51
B24: Manik | C24: Indiranagar Resi GFCs [Pkgs 4] | D24: 0.004
B25: Manik | C25: MT Plano [LOD 200 and Approvals] [Pkgs 8] | D25: 0.7
B26: Manik | C26: Ooty Resi [LOD 200 and Approvals] [Pkgs 26] [ON HOLD]
B27: Manik | C27: OtR-Oota [LOD 200 and Approvals] [Pkgs 3] | D27: 0.15
B29: Atul L | C29: Total Packages [11 Pkgs] | D29: =SUM(D30:D34) -> 0
B30: Atul P | C30: TuiG FKH [V20, V30 and V40] [Pkgs 3] | G30: LoD 350 - V20, V30 and V40
B31: Atul P | C31: Harohalli FKH [V30, V40 and V50] [Pkgs 3] | G31: LoD 350 - V30, V40
B32: Atul P | C32: Violet Hill FKH [P-1 D & P-2 U][Pkgs 2] | G32: LoD 100 - Concept to be finalized for product brochure & walkthrough
B33: Atul P | C33: Shreegaon FKH [V50 C] [Pkgs 1]
B34: Atul P | C34: OTF FKH V50 C and V50 D [Pkgs 2]
B36: Prakash C | C36: AtR Ph 1, 2a, 2b [LOD 350] [Pkgs 1] | D36: 0.01
B37: Prakash C | C37: AtR Ph 2c [LOD 350] [Pkgs 2] | D37: 0.02
B38: Prakash C | C38: AtR Ph 3 [LOD 350] except Villa block 33[Pkgs 15] | D38: 0.36 | E38: 2 | F38: 0.01
B39: Prakash C | C39: AtR - C [LOD 350] [Pkgs 4] | D39: 0.41 | E39: 1 | F39: 0.13
B40: Prakash C | C40: PoaRR-Res [LOD 350] [Pkgs 3] | D40: 0.36
B41: Prakash C | C41: PoaRR-T08 [LOD 350] [Pkgs 8] | D41: 2.1
B42: Prakash C | C42: ITQE-Ph1 [LOD 350] [Pkgs 3] | D42: 0.08 | G42: LoD 350 - Master Plan | Site Development, LoD 350 - Amenities & Facilities | Community spaces
B43: Prakash C | C43: ITQE-Ph2a [LOD 350] [Pkgs 3] | D43: 0.17 | G43: LoD 350 -Experience Home + Project Experience [ V35 ], LoD 350 - Master Plan | Site Development, LoD 350 - Master Plan | Site MEP
B44: Prakash C | C44: ITQE-Ph2b [LOD 350] except terrace level [Pkgs 11] | D44: 1.12 | E44: 2 | F44: 0.14 | G44: LoD 350 - Tower 06 | Habitable Level - Even, LoD 350 - Tower 06 | Habitable Level - Odd, LoD 350 - Tower 07 | Habitable Level - Even, LoD 350 - Tower 07 | Habitable Level - Odd, LoD 350 - ISS5&6 | Structrural Slab 01 [Basement], LoD 350 - ISS 7 | Structrural Slab 01 [Basement]
B45: Prakash C | C45: ItQE-Ph2c [LOD 350] [T9] Till Parking level subgrade [Pkgs 4] | D45: 0.28
B46: Prakash C | C46: ItQE-Ph3a [T10-12 & 31 Villas] [LOD 350] [Pkgs 2] | D46: 3.26
B47: Prakash C | C47: OTR-Ph01 [LOD 350] [Pkgs 5] | D47: 0.38 | G47: LoD 350 - LoD 350 -Experience Home + Project Experience [ V35 ], LoD 350 - Villa Block | Super Structure
B48: Prakash C | C48: TuiG [LOD 350] [Pkgs 4] | D48: 0.8 | E48: 1 | F48: 0.061981661
B49: Prakash C | C49: TMFT-Ph 2 [LOD 350] [Pkgs 1] | D49: 0.03 | G49: LoD 350 - Master Plan - Site Development
B50: Prakash C | C50: DBTW [LOD 350] except odd level ,Terrace [Pkgs 15] | D50: 3.64 | E50: 1 | F50: 2.25 | G50: LoD 300 - Pre Construction Set [Podium], LoD 350 - Tower-2-Habitable Level 01
B51: Prakash C | C51: SftW [LOD 350] except community spaces[Pkgs 6] | D51: 0.35
B52: Prakash C | C52: LGCE Campus [Pkgs 0] | D52: 0
B53: Prakash C | C53: Ooty Res [Pkgs 0] | D53: 0
B54: Prakash C | C54: MeenaSai Res [LOD 200] [Pkgs 1] | D54: 0.02
B55: Prakash C | C55: NH Homestay [LOD 350] [Pkgs 3] | D55: 0.22
B56: Prakash C | C56: OTR Museum [LOD 350] [Pkgs 0] | D56: 0
B57: Prakash C | C57: KIADB - Mys [LOD 350] [Pkgs 1] | D57: 0
B58: Prakash C | C58: Imagine Campus [LOD 200] [Pkgs 1] | D58: 0.19
B59: Prakash C | C59: OTR-Ph02 [LOD 200] [Pkgs 1] | D59: 0.17
B60: Prakash C | C60: TMFT-Ph 3 [LOD 200] [Pkgs 1] | D60: 0.08
B61: Prakash C | C61: Srjp - Res [LOD 200], experience home [Pkgs 2] | D61: 2.02
B62: Prakash C | C62: Srjp - C - SB [LOD 200] [Pkgs 1] | D62: 1.56
... B66: Prakash C | C66: Shreegaon [70a] [LOD 200] [Pkgs 1] | D66: 0.2
B67: Prakash C | C67: Violet hill [LOD 300][Pkgs 4] | D67: 0.57 | G67: LoD 350 - Infra Grading LoD 350 - Infra MEP LoD 350 - BOQ & Tech Specs
B68: Prakash C | C68: Ambegaon [Pkgs 0] | D68: 0
B69: Prakash C | C69: Mall of Asia [Pkgs 0] | D69: 0
B70: Prakash C | C70: TR Mills [Pkgs 0] | D70: 0
B71: Prakash C | C71: Indiranagar Res [LOD 350] [Pkgs 1] | D71: 0 | G71: [LOD 350] - Building Envelope + Common area - Gym Spiral staircase
B72: Prakash C | C72: OTR OOTA [LOD 200] [Pkgs 1] | D72: 0.02
B74: Gaganjit S | C74: AtR Ph 2c [LOD 350] - Site MEP [Pkgs 1] | D74: 0.014336873 | G74: LoD 350 - Site MEP
B75: Gaganjit S | C75: AtR Ph 3 [LOD 350] except villa block 33, VAT Default [Pkgs 12] | D75: 0.36573176 | G75: LoD 350 - Foundations and Sub-Grade Structure [Block 31, 32, 34]
B76: Gaganjit S | C76: AtR - Com [LOD 350] [Pkgs 2] | D76: 0.16750548
B77: Gaganjit S | C77: PoaRR-Res [LOD 350] [Pkgs 4] | D77: 0.4032745
B78: Gaganjit S | C78: PoaRR-T08 [LOD 350] except penthouse products [Pkgs 3] | D78: 0.14
B79: Gaganjit S | C79: ITQE-Ph2b [LOD 350] - ISS 5,6,7 [Pkgs 2] | D79: 0.031655887 | G79: LoD 350 - ISS -5 & 6 | Structrural Slab 01 [Basement], LoD 350 - ISS -7 | Structrural Slab 01 [Basement]
B80: Gaganjit S | C80: ItQE-Ph2c [T9] [LOD 350 -ISS 9, T9 Foundation and grade slab] [Pkgs 3] | D80: 0.04712278
B81: Gaganjit S | C81: ItQE-Ph3a [T10-12 & 31 Villas] [LOD 300], experience home [Pkgs 8] | D81: 2.1646138
B82: Gaganjit S | C82: OTR-Ph01 [LOD 350] Site MEP [Pkgs 1] | D82: 0.04
B83: Gaganjit S | C83: TuiG [LOD 350] , Clubhouse except interiors[Pkgs 7] | D83: 0.32 | E83: 1 | F83: 0.02 | G83: LoD 350 - CH structure & envelope [MEP ] , CH interior & facilities [MEP+LS]
B84: Gaganjit S | C84: DBTW [LOD 350] Master plan [Pkgs 3] | D84: 0.036853335
B85: Gaganjit S | C85: SftW [LOD 350] Site MEP , Sporting facilities [Pkgs 4] | D85: 0.021397858
B86: Gaganjit S | C86: LGCE Campus [Pkgs 0] | D86: 0
B87: Gaganjit S | C87: Ooty Res [Pkgs 0] | D87: 0.0033
B88: Gaganjit S | C88: MeenaSai Res [LOD 200][Pkgs 2] | D88: 0.0168
B89: Gaganjit S | C89: NH Homestay [LOD 350] [Pkgs 7] | D89: 0.230268 | E89: 1 | F89: 0.02 | G89: LoD 200-LS Schm Dsgn completed.
B90: Gaganjit S | C90: Indiranagar Res [LOD 350] [Pkgs 1] | D90: 0.000113 | G90: LOD 350- LS Building envelope + Common area
B91: Gaganjit S | C91: OTR Museum [Pkgs 0] | D91: 0
B92: Gaganjit S | C92: KIADB - Mys [LOD 200] , Approvals[Pkgs 2] | D92: 0 | G92: LoD 100 - Design concept
B93: Gaganjit S | C93: Imagine Campus [LOD 200], Approvals [Pkgs 3] | D93: 0.15
B94: Gaganjit S | C94: OTR-Ph02 [LOD 200], Approvals [Pkgs 4] | D94: 0.16686
B95: Gaganjit S | C95: TMFT-Ph 3 [LOD 200], Approvals [Pkgs 4] | D95: 0.07640952
B96: Gaganjit S | C96: Srjp - Res [LOD 200], Approvals, experience home [Pkgs 5] | D96: 1.7570528
B97: Gaganjit S | C97: Srjp - C - SB [LOD 200], Approvals [Pkgs 2] | D97: 0.86951285
B98: Gaganjit S | C98: Srjp - C - NB [LOD 200], Approvals[Pkgs 2] | D98: 0.28983762
B99: Gaganjit S | C99: OTF [LOD 300], experience home [Pkgs 7] | D99: 0.32805
B100: Gaganjit S | C100: Harohalli [Plotted] [LOD 200], Approvals [Pkgs 10] | D100: 5.26214 | G100: LoD 100 - Design concept
B101: Gaganjit S | C101: Shreegaon [70a] [LOD 200], Approvals [Pkgs 7] | D101: 2.5074144
B102: Gaganjit S | C102: Violet hill [LOD 300] [Pkgs 16] - MEP | D102: 2.7927694 | G102: LoD 350 - Infra MEP LoD 350 - BOQ & Tech Specs
B103: Gaganjit S | C103: Violet hill [LOD 300] [Pkgs 16] - LS | D103: 0 | G103: LoD 350 - Infra MEP LoD 350 - BOQ & Tech Specs
B104: Gaganjit S | C104: Mall of Asia [Pkgs 0] | D104: 0
B105: Gaganjit S | C105: TR Mills [Pkgs 0] | D105: 0
B106: Gaganjit S | C106: OTR OOTA [Pkgs 4]
...

Sheet Goal Summary 25Q4
H1: =SUBTOTAL(3,H10:H1427)/2 -> 353 | I1: =SUBTOTAL(3,I10:I1427)/2 -> 0 | J1: =SUBTOTAL(3,J10:J1427)/2 -> 0 | K1: =SUBTOTAL(3,K10:K1427)/2 -> 0 | O1: =SUM(O8) -> 157.0698 | P1: =SUM(P8) -> 0 | Q1: =SUM(Q8) -> 0 | R1: =SUM(R8) -> 0
B2: Design Goals 2026 | H2: Design Packages | I2: Design Packages | J2: Design Packages | K2: Design Packages | O2: Design Fees | P2: Design Fees | Q2: Design Fees | R2: Design Fees
B4: Project Design | H4: Q1 | I4: Q2 | J4: Q3 | K4: Q4 | O4: Q1 | P4: Q2 | Q4: Q3 | R4: Q4
H8: =SUM(H10+H22+H113+H235+H308+H415+H809+H354) -> 582 | I8: =SUM(I10+I22+I113+I235+I308+I415+I809+I354) -> 0 | J8: =SUM(J10+J22+J113+J235+J308+J415+J809+J354) -> 0 | K8: =SUM(K10+K22+K113+K235+K308+K415+K809+K354) -> 0 | O8: =SUM(O10+O22+O113+O235+O308+O415+O809+O354) -> 157.0698 | P8: =SUM(P10+P22+P113+P235+P308+P415+P809+P354) -> 0 | Q8: =SUM(Q10+Q22+Q113+Q235+Q308+Q415+Q809+Q354) -> 0 | R8: =SUM(R10+R22+R113+R235+R308+R415+R809+R354) -> 0
B10: Atul | C10: Design [FKH, Units] | D10: Architecture | H10: =SUM(H12+H19) -> 16 | O10: =SUM(O12+O19) -> 0.45
B12: FKH | C12: [Experience Homes] | H12: =SUM(H13:H17) -> 10 | O12: =SUM(O13:O17) -> 0
B13: Saji | C13: TuiG | D13: Architecture | H13: 3
B14: Saji | C14: Harohalli | D14: Architecture | H14: 2
C15: Violet Hill | D15: Architecture | H15: 1
C16: Shreegaon | D16: Architecture | H16: 2
C17: One Tiny Flower | D17: Architecture | H17: 2
B19: Individual Units GFC | H19: =SUM(H20:H20) -> 6 | O19: =SUM(O20:O20) -> 0.45
C20: Units - Personalised | D20: Architecture | H20: 6 | O20: 0.45
B22: Cijey | C22: Design [ITQE | Srjp | NH | OTR] | D22: Architecture | H22: =SUM(H24+H55+H63+H70+H84+H90+H101+H105+H110+H66+H94) -> 65 | O22: =SUM(O24+O55+O63+O70+O84+O90+O101+O105+O110+O66+O94) -> 51.697725
B24: ITQE | H24: =COUNTA(H25:H53) -> 29 | O24: =SUM(O25:O53) -> 7.6
C25: ITQE Ph 1 | D25: Architecture | H25: Amenities & Facilities | Clubhouse—Interiors and Facilities | O25: 0.26
C26: ITQE Ph 2a | D26: Architecture | H26: Master Plan | Site Development | O26: 0.07
C27: ITQE Ph 2a | D27: Architecture | H27: Experience Home + Project Experience [ V35 ] | O27: 0.18
C28: ITQE Ph 2b | D28: Architecture | H28: Tower—05 | Habitable Level 01 | O28: 0.13
C29: ITQE Ph 2b | D29: Architecture | H29: Tower—06 | Habitable Level 01 | O29: 0.13
C30: ITQE Ph 2b | D30: Architecture | H30: Tower—07 | Habitable Level 01 | O30: 0.13
C31: ITQE Ph 2b | D31: Architecture | H31: Tower—05 | Terrace Level | O31: 0.08
C32: ITQE Ph 2b | D32: Architecture | H32: Tower—05 | Building Envelope and Common Areas [Penthouse Levels And Terrace Level] | O32: 0.22
C33: ITQE Ph 2b | D33: Architecture | H33: Tower—06 | Terrace Level | O33: 0.08
C34: ITQE Ph 2b | D34: Architecture | H34: Tower—06 | Building Envelope and Common Areas [Penthouse Levels And Terrace Level] | O34: 0.22
C35: ITQE Ph 2b | D35: Architecture | H35: Tower—07 | Terrace Level | O35: 0.08
C36: ITQE Ph 2b | D36: Architecture | H36: Tower—07 | Building Envelope and Common Areas [Penthouse Levels And Terrace Level] | O36: 0.22
... C53: ITQE Ph 2c | D53: Architecture | H53: ISS 9|Foundations & Sub-Grade | O53: 0.1
B55: Sarjapur [Inspira] | H55: =COUNTA(H56:H61) -> 6 | O55: =SUM(O56:O61) -> 36.066825
C56: Sarjapur | D56: Architecture | H56: Contract + Design Brief | O56: 8.22015
C57: Sarjapur | D57: Architecture | H57: Schematic Concept | O57: 7.80955
C58: Sarjapur | D58: Architecture | H58: Preconstruction Set | O58: 7.80955
C59: Sarjapur | D59: Architecture | H59: Approvals | O59: 4.007425
C60: Sarjapur | D60: Architecture | H60: Experience Home + Project Experience | O60: 4.110075
C61: Sarjapur | D61: Architecture | H61: Marketing and Sales | O61: 4.110075
B63: 37a Nandi Hiils [V] Hoysala | H63: =COUNTA(H64:H64) -> 1 | O63: =SUM(O64:O64) -> 1.2875
C64: NH37a [V] | D64: Architecture | H64: Contract + Design Brief | O64: 1.2875
B66: 36a Nandi Hills [V] Madukosanahalli | H66: =COUNTA(H67:H68) -> 2 | O66: =SUM(O67:O68) -> 3.0034
C67: NH36a [V] | D67: Architecture | H67: Contract + Design Brief | O67: 1.51805
C68: NH36a [V] | D68: Architecture | H68: Schematic Concept | O68: 1.48535
B70: OtR | H70: =COUNTA(H71:H82) -> 12 | O70: =SUM(O71:O82) -> 2.43
C71: OtR Ph1 | D71: Architecture | H71: Pre Construction Set | O71: 0.31
C72: OtR Ph1 | D72: Architecture | H72: Individual Homes | V25 Default & its Variant | O72: 0.3
C73: OtR Ph1 | D73: Architecture | H73: Villa Block | Super Structure | O73: 0.3
C74: OtR Ph1 | D74: Architecture | H74: Villa Block | Building Envelope + Plot Development | O74: 0.14
C75: OtR Ph1 | D75: Architecture | H75: Master Plan | O75: 0.09
C76: OtR Ph1 | D76: Architecture | H76: Site Development | O76: 0.03
C77: OtR Ph1 | D77: Architecture | H77: Site MEP | O77: 0.03
C78: OtR Ph1 | D78: Architecture | H78: Landscaping | O78: 0.15
C79: OtR Ph2 | D79: Architecture | H79: Contract + Design Brief | O79: 0.31
C80: OtR Ph2 | D80: Architecture | H80: Schematic Concept | O80: 0.31
C81: OtR Ph2 | D81: Architecture | H81: Approvals | O81: 0.31
C82: OtR Ph2 | D82: Architecture | H82: Marketing and Sales | O82: 0.15
B84: Meena & Krishnasai Residence | H84: =COUNTA(H85:H88) -> 4 | O84: =SUM(O85:O88) -> 0.27
C85: MeenaSai Res | D85: Architecture | H85: Design Brief | O85: 0.27
C86: MeenaSai Res | D86: Architecture | H86: Schematic Concept
C87: MeenaSai Res | D87: Architecture | H87: Pre Construction Set
C88: MeenaSai Res | D88: Architecture | H88: Approvals
B90: 10a Nandi Hills [V] Sltnpt | O90: =SUM(O91:O92) -> 0
C91: NH10a [V] | D91: Architecture
B94: NH Homestay | H94: =COUNTA(H95:H99) -> 5 | O94: =SUM(O95:O99) -> 0.995
C95: NH Homestay | D95: Architecture | H95: Schematic Concept | O95: 0.19
C96: NH Homestay | D96: Architecture | H96: Preconstruction | O96: 0.19
C97: NH Homestay | D97: Architecture | H97: Foundation + Subgrade | O97: 0.246
C98: NH Homestay | D98: Architecture | H98: Building envelope + Plot development | O98: 0.246
C99: NH Homestay | D99: Architecture | H99: Interiors | O99: 0.123
B101: OtR -Museum | H101: =COUNTA(H102:H103) -> 2 | O101: =SUM(O102:O103) -> 0
C102: OtR -Museum | D102: Architecture | H102: Contract + Design Brief
C103: OtR -Museum | D103: Architecture | H103: Schematic Concept
B105: Vaderahalli | H105: =COUNTA(H106:H108) -> 3 | O105: =SUM(O108:O108) -> 0
C106: Vaderahalli | D106: Architecture | H106: Contract + Design Brief
C107: Vaderahalli | D107: Architecture | H107: Schematic Concept
C108: Vaderahalli | D108: Architecture | H108: Approvals
B110: Individual Units GFC | H110: =COUNTA(H111) -> 1 | O110: =SUM(O111:O111) -> 0.045
C111: Units | D111: Architecture | H111: OtR | Villa -22- Personalised design | O111: =(3000*150)/10000000 -> 0.045
B113: OP | C113: Design [TMFT | SFTW | DBTW | TUIG] | D113: Architecture | H113: =SUM(H115,H119,H131,H168,H177,H179,H181,H183,H187,H189,H193,H197,H199,H203,H206,H212,H216,H220,H226,H228,H230,H232) -> 67 | O113: =SUM(O115,O119,O131,O168,O177,O179,O181,O183,O187,O189,O193,O197,O199,O203,O206,O212,O216,O220,O226,O228,O230,O232) -> 13.623554
B115: TMFT - Ph3 | H115: =COUNTA(H116:H117) -> 2 | O115: =SUM(O116:O117) -> 0
B116: OP | C116: TMFT - Ph3 | D116: Architecture | H116: Contract + Design Brief
B117: OP | C117: TMFT - Ph3 | D117: Architecture | H117: Schematic Concept
B119: SFTW | H119: =COUNTA(H120:H129) -> 10 | O119: =SUM(O120:O129) -> 0.90157259
B120: OP | C120: SFTW | D120: Architecture | H120: ISS 01 - Podium Slab | O120: 0.25575333
B121: OP | C121: SFTW | D121: Architecture | H121: Clubhouse—Structure and Envelope | O121: 0.081564148
B122: OP | C122: SFTW | D122: Architecture | H122: Master Plan | O122: 0.18696938
C123: SFTW | D123: Architecture | H123: Clubhouse—Outdoor Spaces and Pool | O123: 0.027188049
C124: SFTW | D124: Architecture | H124: Master Plan - Site Development | O124: 0.11218163
C125: SFTW | D125: Architecture | H125: Master Plan - Site MEP | O125: 0.037393876
C126: SFTW | D126: Architecture | H126: Master Plan - Landscaping | O126: 0.037393876
C127: SFTW | D127: Architecture | H127: Clubhouse—Interiors and Facilities | O127: 0.1087522
C128: SFTW | D128: Architecture | H128: Clubhouse + Amenities - Community spaces [Board Walk, Children play area] | O128: 0.027188049
C129: SFTW | D129: Architecture | H129: Clubhouse + Amenities - Sporting Facilities | O129: 0.027188049
B131: DBTW | H131: =COUNTA(H132:H166) -> 35 | O131: =SUM(O132:O166) -> 9.88
B132: OP | C132: DBTW | D132: Architecture | H132: Master Plan - Site MEP | O132: 0.07
B133: OP | C133: DBTW | D133: Architecture | H133: Master Plan - Landscaping | O133: 0.07
B134: OP | C134: DBTW | D134: Architecture | H134: Clubhouse—Interiors and Facilities | O134: 0.15
C135: DBTW | D135: Architecture | H135: Community spaces [Board Walk, Children play area,OAT] | O135: 0.04
C136: DBTW | D136: Architecture | H136: Sporting Facilities | O136: 0.04
C137: DBTW | D137: Architecture | H137: Tower 06 - Foundation and Grade Slab | O137: 0.06
C138: DBTW | D138: Architecture | H138: Tower 06 -Parking Level-Sub grade | O138: 0.03
C139: DBTW | D139: Architecture | H139: Tower 06 - Building Envelope and Common Areas [Basement] | O139: 0.06
B140: OP | C140: DBTW | D140: Architecture | H140: Tower 06 - Habitable Level 01 | O140: 0.06
...

Sheet Data sheet
B2: Project | C2: Phase | D2: Leader | E2: Discipline | F2: Package | G2: Billing value | H2: Plan | I2: Actual | J2: Status
B3: ATR | C3: 1 | D3: Saji | E3: Architecture | F3: Site MEP | G3: 1 | H3: 45717 | I3: 45809 | J3: Actual
B4: NH Homestay | C4: 1 | D4: Cijey | E4: Architecture | F4: GFC | G4: 1 | H4: 45809 | I4: 45809 | J4: Plan
B5: NH Homestay | C5: 1 | D5: Cijey | E5: Architecture | F5: Archives | G5: 2 | H5: 45901 | I5: 45992 | J5: Plan

Sheet Sheet1
B2: Suresh goals
B3: Approved [Plan Sanction + RERA] | C3: Designer assigned | F3: Types | G3: Imagine Campus | H3: 5.6 | I3: 0.2 | J3: SD
A4: 1 | B4: Vaderahalli[63.5A] | C4: Cijey | D4: Apt +V+C | G4: The Magic Faraway Tree | H4: 11 | I4: 1.22 | J4: JD | K4: 841 | L4: Apt
B5: Dona Paula, Goa [12A] | C5: Naveen Y | D5: Apt+C | G5: The Meadow Dance | H5: 20 | I5: 0.49 | J5: JD | K5: 326 | L5: V
B6: After the Rain Phase 3 [7.83A] | C6: Saji | D6: V | G6: Songs from the Wood | H6: 5.14 | I6: 0.81 | J6: JD | K6: 618 | L6: Apt
B7: Ambegaon Phase 1 [60A] | C7: Gagan | D7: P | G7: Pursuit of a Radical Rhapsody | H7: 37 | I7: 4.88 | J7: SD | K7: 5083 | L7: Apt +V
B8: Sarjapura [Iinspira] [18.92A] | C8: Cijey | D8: Apt +V+C | E8: Srjp-C [NY] | G8: A Saucerful of Secrets | H8: 20 | I8: 0.25 | J8: SD | K8: 300
B9: Harohalli - Phase 1 Plotted [40 A] | C9: Gagan | D9: P | G9: In That Quiet Earth | H9: 75.5 | I9: 7.29 | J9: SD | K9: 7939 | L9: Apt +V
A10: 1 | B10: Harohalli - Phase 2 Villas [42 A] | C10: Saji | G10: Learning to Fly | H10: 3.77 | I10: 0.73 | J10: SD | K10: 870 | L10: Apt
B11: Vijayapura - Phase 1 [40 A] | C11: Gagan | D11: P | G11: After the Rain | H11: 49.4 | I11: 1.12 | J11: SD | K11: 1372 | L11: V
B12: Alibagh [70 A] | C12: Gagan | D12: P | G12: Campus @ KIADB Mysore | H12: 176 | I12: 1.5 | J12: SD | K12: -
B13: Talshet [30A] | C13: Gagan | D13: P | G13: Over the Rainbow | H13: 24 | I13: 0.3 | J13: DM | K13: 232 | L13: V
A14: 1 | B14: Acharlahalli, Nandi Hills Phase 1 [Hoysala -12A] | C14: Cijey | D14: V | G14: Down by the Water | H14: 18 | I14: 1.94 | J14: JD | K14: 2181 | L14: Apt
A15: 1 | B15: In That Quiet Earth Phase 3 [38.3A] | C15: Cijey | D15: Apt +V | G15: Sunticoppa | H15: 72.7 | I15: 0.54 | J15: JD | K15: 819 | L15: V
B16: Suntikoppa - Phase 1 [33A] | C16: Naveen Y | D16: V | G16: Sarjpr Rd Iinspira | H16: 24 | I16: 3.62 | J16: DM | K16: 1088 | L16: Apt +V+C
B17: Suntikoppa - Phase 2 [39 A] | C17: Naveen Y | D17: V | G17: Acharahalli, Nandi Hills | H17: 37 | I17: 0.89 | J17: JD | K17: 961 | L17: V
B18: Poinciana Phase1 [20.575A] | C18: Gagan | D18: P | G18: Harohalli | H18: 40 | I18: 4.21 | J18: SD | K18: 6819 | L18: Apt
B19: Poinciana Phase 2 [42A] | C19: Gagan | D19: P | G19: Vaderahalli | H19: 63.5 | I19: 4.67 | J19: JD | K19: 6923 | L19: Apt +V+C
A20: 1 | B20: Mysore - KIADB Phase 1[130.55A] | C20: Naveen Y | G20: Sultanpet | H20: 10 | I20: 0.23 | J20: DM | K20: 27 | L20: Apt
A21: 1 | B21: Over the Rainbow Phase 2 [16.575 A] | C21: Cijey | D21: V | G21: Dona Paula | H21: 11.64 | I21: 2.14 | J21: JD | K21: 2038 | L21: Apt+C
A22: 1 | B22: Sultanpet, Nandi Hills [10A] | C22: Cijey | D22: Apt | G22: Madakuhosanahalli, Nandi Hills | H22: 35 | I22: 0.42 | J22: JD | K22: 819 | L22: V
G23: Kashmir Projects | H23: 36.8 | I23: 0.69 | J23: JD | K23: 1313 | L23: Apt+V
G24: Chikkajala | H24: 40 | I24: 4.7 | J24: JD | K24: 5544 | L24: Apt+V
G25: Thubarahalli [Varthur Lake] | H25: 45 | I25: 6.13 | J25: JD | K25: 9170 | L25: Apt+V
G26: ECR Chennai | H26: 400 | I26: 8.98 | J26: JD | K26: 4332 | L26: Apt+C
G27: Pallavaram | H27: 80 | I27: 12.15 | J27: DM | K27: 3007 | L27: Apt+V+C
G28: Ooty | H28: 46 | I28: 0.32 | J28: JD | K28: 587 | L28: V
G29: Yadgarpalle | H29: 60 | I29: 1.57 | J29: JD | K29: 2007 | L29: V
G30: Financial disrtict, Gachibowli | H30: 15 | I30: 4.5 | J30: SD | K30: 6084
G31: Dabolim | H31: 12.5 | I31: 0.26 | J31: JD | K31: 479 | L31: V
G32: Panvel, Mumbai | H32: 192 | I32: 7.96 | J32: JD | K32: 9140 | L32: Apt +V+C
G33: Worli, Mumbai | H33: 1.42 | I33: 0.33 | J33: DM | K33: 539 | L33: Apt
G34: Naya Raipur | H34: 20 | I34: 0.74 | J34: DM | K34: 144 | L34: V
G35: Aronda | H35: 200 | I35: 2.74 | J35: DM | K35: 659 | L35: V
G39: Poinciana | H39: 93 | I39: 2.22 | J39: SD | K39: 665 | L39: P
G40: Tangled up in Green | H40: 120 | I40: 2.64 | J40: DM | K40: 209 | L40: P
G41: Coimbatore | H41: 60 | I41: 6.53 | J41: DM | K41: 1529
G42: Alibaug | H42: 70 | I42: 1.68 | J42: JD | K42: 688 | L42: P
G43: Talshet | H43: 30 | I43: 0.72 | J43: JD | K43: 295 | L43: P
G44: Ambegaon | H44: 150 | I44: 3.59 | J44: JD | K44: 1405 | L44: P
G45: Savakanahalli | H45: 120 | I45: 2.87 | J45: JD | K45: 1869 | L45: P
G46: Vijayapura | H46: 100 | I46: 2.4 | J46: JD | K46: 1497 | L46: P
G47: Sarjapur [Koothaganahalli] | H47: 300 | I47: 7.19 | J47: SD | K47: 5750 | L47: P
G48: Yadgarpalle | H48: 185 | I48: 4.43 | J48: JD | K48: 1551 | L48: P
G49: Harohalli | H49: 40 | I49: 0.96 | J49: SD | K49: 575 | L49: P
G50: Naya Raipur [Plots] | H50: 40 | I50: 0.96 | J50: DM | K50: 77 | L50: P
G51: Aronda | H51: 200 | I51: 4.79 | J51: DM | K51: 383 | L51: P

Sheet Breakup-MP+MEP+LS
G2: Pkgs | K2: Design Packages | R2: Fees | V2: Design Fees
G3: =SUM(K3:N3) -> 539 | K3: =K10 -> 146 | L3: =L10 -> 158 | M3: =M10 -> 123 | N3: =N10 -> 112 | R3: =SUM(V3:Y3) -> 136.94638 | V3: =V10 -> 26.639196 | W3: =W10 -> 45.068301 | X3: =X10 -> 31.884182 | Y3: =Y10 -> 33.354697
B5: Marathon 2025 | G5: 2025 | K5: Q1 | L5: Q2 | M5: Q3 | N5: Q4 | R5: 2025 | V5: Q1 | W5: Q2 | X5: Q3 | Y5: Q4
B10: Gagan | C10: Design [MP+MEP+LS] | G10: =SUM(K10:N10) -> 539 | K10: =SUM(K12,K80,K344) -> 146 | L10: =SUM(L12,L80,L344) -> 158 | M10: =SUM(M12,M80,M344) -> 123 | N10: =SUM(N12,N80,N344) -> 112 | R10: =SUM(V10:Y10) -> 136.94638 | V10: =SUM(V12,V80,V344) -> 26.639196 | W10: =SUM(W12,W80,W344) -> 45.068301 | X10: =SUM(X12,X80,X344) -> 31.884182 | Y10: =SUM(Y12,Y80,Y344) -> 33.354697
B12: Masterplanning | C12: MP | G12: =SUM(K12:N12) -> 81 | K12: =SUM(K14,K19,K22,K26,K32,K37,K41,K45,K49,K53,K57,K62,K66,K69,K72,K76) -> 20 | L12: =SUM(L14,L19,L22,L26,L32,L37,L41,L45,L49,L53,L57,L62,L66,L69,L72,L76) -> 23 | M12: =SUM(M14,M19,M22,M26,M32,M37,M41,M45,M49,M53,M57,M62,M66,M69,M72,M76) -> 21 | N12: =SUM(N14,N19,N22,N26,N32,N37,N41,N45,N49,N53,N57,N62,N66,N69,N72,N76) -> 17 | R12: =SUM(V12:Y12) -> 86.583581 | V12: =SUM(V14,V19,V22,V26,V32,V37,V41,V45,V49,V53,V57,V62,V66,V69,V72,V76) -> 17.01992 | W12: =SUM(W14,W19,W22,W26,W32,W37,W41,W45,W49,W53,W57,W62,W66,W69,W72,W76) -> 26.526083 | X12: =SUM(X14,X19,X22,X26,X32,X37,X41,X45,X49,X53,X57,X62,X66,X69,X72,X76) -> 21.481618 | Y12: =SUM(Y14,Y19,Y22,Y26,Y32,Y37,Y41,Y45,Y49,Y53,Y57,Y62,Y66,Y69,Y72,Y76) -> 21.55596
A14: 1 | B14: TUIG | G14: =SUM(K14:N14) -> 2 | K14: =COUNTA(K15:K17) -> 2 | L14: =COUNTA(L15:L17) -> 0 | M14: =COUNTA(M15:M17) -> 0 | N14: =COUNTA(N15:N17) -> 0 | R14: =SUM(V14:Y14) -> 1.21 | V14: =SUM(V15:V17) -> 1.21 | W14: =SUM(W15:W17) -> 0 | X14: =SUM(X15:X17) -> 0 | Y14: =SUM(Y15:Y17) -> 0
G15: MP | K15: Site MEP | R15: MP | V15: 0.3
K16: Site Development | R16: MP | V16: 0.91
A19: 1 | B19: Sarjapur | G19: =SUM(K19:N19) -> 2 | K19: =COUNTA(K20:K20) -> 0 | L19: =COUNTA(L20:L20) -> 1 | M19: =COUNTA(M20:M20) -> 1 | N19: =COUNTA(N20:N20) -> 0 | R19: =SUM(V19:Y19) -> 1.5999778 | V19: =SUM(V20:V20) -> 0 | W19: =SUM(W20:W20) -> 0.79998891 | X19: =SUM(X20:X20) -> 0.79998891 | Y19: =SUM(Y20:Y20) -> 0
G20: MP | L20: Schematic Concept | M20: Pre-construction set | R20: MP | W20: 0.79998891 | X20: 0.79998891
A22: 1 | B22: 36a Nandi Hills[V] | G22: =SUM(K22:N22) -> 6 | K22: =COUNTA(K23:K24) -> 1 | L22: =COUNTA(L23:L24) -> 2 | M22: =COUNTA(M23:M24) -> 2 | N22: =COUNTA(N23:N24) -> 1 | R22: =SUM(V22:Y22) -> 6.0675 | V22: =SUM(V23:V24) -> 1.365 | W22: =SUM(W23:W24) -> 2.0175 | X22: =SUM(X23:X24) -> 2.0175 | Y22: =SUM(Y23:Y24) -> 0.6675
G23: MP | K23: Contract + Design Brief | L23: Schematic Concept | M23: Pre-construction set | N23: Experience Home + Project Experience | R23: MP | V23: 1.365 | W23: 1.335 | X23: 1.335 | Y23: 0.6675
G24: MP | L24: Approvals | M24: Marketing and Sales | R24: MP | W24: 0.6825 | X24: 0.6825
A26: 1 | B26: Poinciana | G26: =SUM(K26:N26) -> 8 | K26: =COUNTA(K27:K30) -> 4 | L26: =COUNTA(L27:L30) -> 2 | M26: =COUNTA(M27:M30) -> 1 | N26: =COUNTA(N27:N30) -> 1 | R26: =SUM(V26:Y26) -> 4.5575782 | V26: =SUM(V27:V30) -> 1.6699455 | W26: =SUM(W27:W30) -> 1.6686945 | X26: =SUM(X27:X30) -> 0.91420372 | Y26: =SUM(Y27:Y30) -> 0.30473457
G27: MP | K27: Schematic Concept | L27: Pre-construction set | M27: Site Development | N27: Site MEP | R27: MP | V27: 0.45100717 | W27: 0.44975618 | X27: 0.91420372 | Y27: 0.30473457
G28: MP | K28: Approvals | L28: Master Plan | R28: MP | V28: 0.60946915 | W28: 1.2189383
G29: MP | K29: Project Experience+ Entrance portal | R29: MP | V29: 0.30473457
G30: MP | K30: Marketing and Sales | R30: MP | V30: 0.30473457
A32: 1 | B32: Ambegn | G32: =SUM(K32:N32) -> 6 | K32: =COUNTA(K33:K35) -> 1 | L32: =COUNTA(L33:L35) -> 2 | M32: =COUNTA(M33:M35) -> 2 | N32: =COUNTA(N33:N35) -> 1 | R32: =SUM(V32:Y32) -> 6.45625 | V32: =SUM(V33:V35) -> 1.0225 | W32: =SUM(W33:W35) -> 2.045 | X32: =SUM(X33:X35) -> 1.53375 | Y32: =SUM(Y33:Y35) -> 1.855
G33: MP | K33: Contract + Design Brief | L33: Schematic Concept | M33: Experience Home + Project Experience | N33: Pre-construction set | R33: MP | V33: 1.0225 | W33: 1.0225 | X33: 0.51125 | Y33: 1.855
G34: MP | L34: Approvals | M34: Marketing and Sales | R34: MP | W34: 1.0225 | X34: 1.0225
G35: MP | R35: MP
A37: 1 | B37: Savakanhli | G37: =SUM(K37:N37) -> 6 | K37: =COUNTA(K38:K39) -> 1 | L37: =COUNTA(L38:L39) -> 2 | M37: =COUNTA(M38:M39) -> 2 | N37: =COUNTA(N38:N39) -> 1 | R37: =SUM(V37:Y37) -> 6.30875 | V37: =SUM(V38:V40) -> 0.7775 | W37: =SUM(W38:W40) -> 2.96 | X37: =SUM(X38:X40) -> 2.1825 | Y37: =SUM(Y38:Y40) -> 0.38875
G38: MP | K38: Contract + Design Brief | L38: Schematic Concept | M38: Pre-construction set | N38: Experience Home + Project Experience | R38: MP | V38: 0.7775 | W38: 1.405 | X38: 1.405 | Y38: 0.38875
G39: MP | L39: Approvals | M39: Marketing and Sales | R39: MP | W39: 1.555 | X39: 0.7775
A41: 1 | B41: Harohalli | G41: =SUM(K41:N41) -> 6 | K41: =COUNTA(K42:K43) -> 1 | L41: =COUNTA(L42:L43) -> 2 | M41: =COUNTA(M42:M43) -> 2 | N41: =COUNTA(N42:N43) -> 1 | R41: =SUM(V41:Y41) -> 2.204775 | V41: =SUM(V42:V44) -> 0.244975 | W41: =SUM(W42:W44) -> 0.9799 | X41: =SUM(X42:X44) -> 0.734925 | Y41: =SUM(Y42:Y44) -> 0.244975
G42: MP | K42: Contract + Design Brief | L42: Schematic Concept | M42: Pre-construction set | N42: Experience Home + Project Experience | R42: MP | V42: 0.244975 | W42: 0.48995 | X42: 0.48995 | Y42: 0.244975
L43: Approvals | M43: Marketing and Sales | W43: 0.48995 | X43: 0.244975
A45: 1 | B45: 37a Nandi Hills [V] | G45: =SUM(K45:N45) -> 2 | K45: =COUNTA(K46:K47) -> 0 | L45: =COUNTA(L46:L47) -> 0 | M45: =COUNTA(M46:M47) -> 1 | N45: =COUNTA(N46:N47) -> 1 | R45: =SUM(V45:Y45) -> 0.8 | V45: =SUM(V46:V47) -> 0 | W45: =SUM(W46:W47) -> 0 | X45: =SUM(X46:X47) -> 0.4 | Y45: =SUM(Y46:Y47) -> 0.4
G46: MP | M46: Schematic Concept | N46: Pre Construction Set | R46: MP | X46: 0.4 | Y46: 0.4
G47: MP
A49: 1 | B49: Alibaug | G49: =SUM(K49:N49) -> 6 | K49: =COUNTA(K50:K51) -> 2 | L49: =COUNTA(L50:L51) -> 2 | M49: =COUNTA(M50:M51) -> 1 | N49: =COUNTA(N50:N51) -> 1 | R49: =SUM(V49:Y49) -> 3.815 | V49: =SUM(V50:V51) -> 1.32 | W49: =SUM(W50:W51) -> 1.41 | X49: =SUM(X50:X51) -> 0.85 | Y49: =SUM(Y50:Y51) -> 0.235
G50: MP | K50: Contract + Design Brief | L50: Marketing and Sales | M50: Pre Construction Set | N50: Project Experience | R50: MP | V50: 0.47 | W50: 0.47 | X50: 0.85 | Y50: 0.235
G51: MP | K51: Schematic Concept | L51: Approvals | R51: MP | V51: 0.85 | W51: 0.94
A53: 1 | B53: Talashet | G53: =SUM(K53:N53) -> 6 | K53: =COUNTA(K54:K55) -> 2 | L53: =COUNTA(L54:L55) -> 2 | M53: =COUNTA(M54:M55) -> 1 | N53: =COUNTA(N54:N55) -> 1 | R53: =SUM(V53:Y53) -> 1.63 | V53: =SUM(V54:V55) -> 0.565 | W53: =SUM(W54:W55) -> 0.6 | X53: =SUM(X54:X55) -> 0.365 | Y53: =SUM(Y54:Y55) -> 0.1
G54: MP | K54: Contract + Design Brief | L54: Marketing and Sales | M54: Pre Construction Set | N54: Project Experience | R54: MP | V54: 0.2 | W54: 0.2 | X54: 0.365 | Y54: 0.1
G55: MP | K55: Schematic Concept | L55: Approvals | R55: MP | V55: 0.365 | W55: 0.4
A57: 1 | B57: Sarjpr [P] | G57: =SUM(K57:N57) -> 5 | K57: =COUNTA(K58:K60) -> 0 | L57: =COUNTA(L58:L60) -> 1 | M57: =COUNTA(M58:M59) -> 2 | N57: =COUNTA(N58:N59) -> 2 | R57: =SUM(V57:Y57) -> 15.84 | V57: =SUM(V58:V60) -> 0 | W57: =SUM(W58:W60) -> 3.52 | X57: =SUM(X58:X60) -> 5.28 | Y57: =SUM(Y58:Y60) -> 7.04
G58: MP | L58: Contract + Design Brief | M58: Schematic Concept | N58: Pre Construction Set | W58: 3.52 | X58: 3.52 | Y58: 3.52
M59: Approvals | N59: Marketing and Sales | X59: 1.76 | Y59: 1.76
G60: MP | N60: Project Experience | Y60: 1.76
A62: 1 | B62: Vijayapura | G62: =SUM(K62:N62) -> 7 | K62: =COUNTA(K63:K64) -> 2 | L62: =COUNTA(L63:L64) -> 2 | M62: =COUNTA(M63:M64) -> 2 | N62: =COUNTA(N63:N64) -> 1 | R62: =SUM(V62:Y62) -> 6.40125 | V62: =SUM(V63:V64) -> 1.42 | W62: =SUM(W63:W64) -> 1.57 | X62: =SUM(X63:X64) -> 1.16125 | Y62: =SUM(Y63:Y64) -> 2.25
G63: MP | K63: Contract + Design Brief | L63: Marketing and Sales | M63: Pre Construction Set | N63: Master Plan | R63: MP | V63: 0.52 | W63: 0.52 | X63: 0.9 | Y63: 2.25
G64: MP | K64: Schematic Concept | L64: Approvals | M64: Project Experience | R64: MP | V64: 0.9 | W64: 1.05 | X64: 0.26125
A66: 1 | B66: Lal Bazar | G66: =SUM(K66:N66) -> 4 | K66: =COUNTA(K67:K67) -> 1 | L66: =COUNTA(L67:L67) -> 1 | M66: =COUNTA(M67:M67) -> 1 | N66: =COUNTA(N67:N67) -> 1 | R66: =SUM(V66:Y66) -> 3.78 | V66: =SUM(V67:V67) -> 1.08 | W66: =SUM(W67:W67) -> 1.08 | X66: =SUM(X67:X67) -> 0.54 | Y66: =SUM(Y67:Y67) -> 1.08
G67: MP | K67: Contract + Design Brief | L67: Schematic Concept | M67: Approvals | N67: Pre Construction Set | R67: MP | V67: 1.08 | W67: 1.08 | X67: 0.54 | Y67: 1.08
A69: 1 | B69: Dani Hama | G69: =SUM(K69:N69) -> 4 | K69: =COUNTA(K70:K70) -> 1 | L69: =COUNTA(L70:L70) -> 1 | M69: =COUNTA(M70:M70) -> 1 | N69: =COUNTA(N70:N70) -> 1 | R69: =SUM(V69:Y69) -> 6.9825 | V69: =SUM(V70:V70) -> 1.995 | W69: =SUM(W70:W70) -> 1.995 | X69: =SUM(X70:X70) -> 0.9975 | Y69: =SUM(Y70:Y70) -> 1.995
G70: MP | K70: Contract + Design Brief | L70: Schematic Concept | M70: Approvals | N70: Pre Construction Set | R70: MP | V70: 1.995 | W70: 1.995 | X70: 0.9975 | Y70: 1.995
A72: 1 | B72: Bellandur | G72: =SUM(K72:N72) -> 6 | K72: =COUNTA(K73:K74) -> 1 | L72: =COUNTA(L73:L74) -> 2 | M72: =COUNTA(M73:M74) -> 1 | N72: =COUNTA(N73:N74) -> 2 | R72: =SUM(V72:Y72) -> 13.77 | V72: =SUM(V73:V74) -> 3.06 | W72: =SUM(W73:W74) -> 4.59 | X72: =SUM(X73:X74) -> 3.06 | Y72: =SUM(Y73:Y74) -> 3.06
G73: MP | K73: Contract + Design Brief | L73: Schematic Concept | M73: Pre Construction Set | N73: Marketing and Sales | R73: MP | V73: 3.06 | W73: 3.06 | X73: 3.06 | Y73: 1.53
G74: MP | L74: Approvals | N74: Experience Home + Project Experience | W74: 1.53 | Y74: 1.53
A76: 1 | B76: Vaderahalli | G76: =SUM(K76:N76) -> 5 | K76: =COUNTA(K77:K78) -> 1 | L76: =COUNTA(L77:L78) -> 1 | M76: =COUNTA(M77:M78) -> 1 | N76: =COUNTA(N77:N78) -> 2 | R76: =SUM(V76:Y76) -> 5.16 | V76: =SUM(V77:V78) -> 1.29 | W76: =SUM(W77:W78) -> 1.29 | X76: =SUM(X77:X78) -> 0.645 | Y76: =SUM(Y77:Y78) -> 1.935
G77: MP | K77: Contract+Design Brief | L77: Schematic Concept | M77: Project Experience | N77: Pre Construction Set | R77: MP | V77: 1.29 | W77: 1.29 | X77: 0.645 | Y77: 1.29
N78: Marketing and Sales | Y78: 0.645
B80: MEP Services | C80: MEP | G80: =SUM(K80:N80) -> 287 | K80: =SUM(K82,K88,K98,K101,K109,K139,K143,K198,K201,K204,K207,K210,K213,K227,K242,K248,K252,K256,K261,K265,K269,K273,K277,K281,K286,K294,K299,K302,K306,K310,K314,K318,K322,K326,K330,K333,K336,K340) -> 87 | L80: =SUM(L82,L88,L98,L101,L109,L139,L143,L198,L201,L204,L207,L210,L213,L227,L242,L248,L252,L256,L261,L265,L269,L273,L277,L281,L286,L294,L299,L302,L306,L310,L314,L318,L322,L326,L330,L333,L336,L340) -> 79 | M80: =SUM(M82,M88,M98,M101,M109,M139,M143,M198,M201,M204,M207,M210,M213,M227,M242,M248,M252,M256,M261,M265,M269,M273,M277,M281,M286,M294,M299,M302,M306,M310,M314,M318,M322,M326,M330,M333,M336,M340) -> 62 | N80: =SUM(N82,N88,N98,N101,N109,N139,N143,N198,N201,N204,N207,N210,N213,N227,N242,N248,N252,N256,N261,N265,N269,N273,N277,N281,N286,N294,N299,N302,N306,N310,N314,N318,N322,N326,N330,N333,N336,N340) -> 59 | R80: =SUM(V80:Y80) -> 32.018305 | V80: =SUM(V82,V88,V98,V101,V109,V139,V143,V198,V201,V204,V207,V210,V213,V227,V242,V248,V252,V256,V261,V265,V269,V273,V277,V281,V286,V294,V299,V302,V306,V310,V314,V318,V322,V326,V330,V333,V336,V340) -> 7.1261141 | W80: =SUM(W82,W88,W98,W101,W109,W139,W143,W198,W201,W204,W207,W210,W213,W227,W242,W248,W252,W256,W261,W265,W269,W273,W277,W281,W286,W294,W299,W302,W306,W310,W314,W318,W322,W326,W330,W333,W336,W340) -> 10.935118 | X80: =SUM(X82,X88,X98,X101,X109,X139,X143,X198,X201,X204,X207,X210,X213,X227,X242,X248,X252,X256,X261,X265,X269,X273,X277,X281,X286,X294,X299,X302,X306,X310,X314,X318,X322,X326,X330,X333,X336,X340) -> 6.8101078 | Y80: =SUM(Y82,Y88,Y98,Y101,Y109,Y139,Y143,Y198,Y201,Y204,Y207,Y210,Y213,Y227,Y242,Y248,Y252,Y256,Y261,Y265,Y269,Y273,Y277,Y281,Y286,Y294,Y299,Y302,Y306,Y310,Y314,Y318,Y322,Y326,Y330,Y333,Y336,Y340) -> 7.1469654
A82: 1 | B82: AtR Ph 1, 2a, 2b, 2c | G82: =SUM(K82:N82) -> 4 | K82: =COUNTA(K83:K86) -> 3 | L82: =COUNTA(L83:L86) -> 1 | M82: =COUNTA(M83:M86) -> 0 | N82: =COUNTA(N83:N86) -> 0 | R82: =SUM(V82:Y82) -> 0.07807012 | V82: =SUM(V83:V86) -> 0.072082274 | W82: =SUM(W83:W86) -> 0.0059878466 | X82: =SUM(X83:X86) -> 0 | Y82: =SUM(Y83:Y86) -> 0
B83: Gagan | C83: AtR Ph 1, 2a, 2b | G83: MEP | K83: MEP | Master Archives | R83: MEP | V83: 0.055695754
B85: Gagan | C85: AtR Ph 2c | G85: MEP | K85: MEP | Clubhouse + Amenities - Sporting Facilities | L85: MEP | Master Archives | R85: MEP | V85: 0.0020496468 | W85: 0.0059878466
B86: Gagan | C86: AtR Ph 2c | G86: MEP | K86: MEP | Master Plan - Site MEP | R86: MEP | V86: 0.014336873
A88: 1 | B88: AtR Com | G88: =SUM(K88:N88) -> 9 | K88: =COUNTA(K89:K96) -> 8 | L88: =COUNTA(L89:L96) -> 1 | M88: =COUNTA(M89:M96) -> 0 | N88: =COUNTA(N89:N96) -> 0 | R88: =SUM(V88:Y88) -> 0.5587291 | V88: =SUM(V89:V96) -> 0.48263555 | W88: =SUM(W89:W96) -> 0.076093551 | X88: =SUM(X89:X96) -> 0 | Y88: =SUM(Y89:Y96) -> 0
B89: Gagan | C89: AtR Com | G89: MEP | K89: Preconstruction set [Loading signoff] | L89: MEP | Master Archives | R89: MEP | V89: 0.076093551 | W89: 0.076093551
B90: Gagan | C90: AtR Com | G90: MEP | K90: MEP | Tower-[Commercial] - Building Envelope and Common Areas [Basement] | R90: MEP | V90: 0.050323477
B91: Gagan | C91: AtR Com | G91: MEP | K91: MEP | Tower-[Commercial] - Habitable Level 1-2 | R91: MEP | V91: 0.050323477
B92: Gagan | C92: AtR Com | G92: MEP | K92: MEP | Tower-[Commercial] - Habitable Level 3-5 | R92: MEP | V92: 0.050323477
B93: Gagan | C93: AtR Com | G93: MEP | K93: MEP | Tower-[Commercial] - Habitable Level 6-10 | R93: MEP | V93: 0.050323477
B94: Gagan | C94: AtR Com | G94: MEP | K94: MEP | Tower-[Commercial] - Terrace Level | R94: MEP | V94: 0.037742607
B95: Gagan | C95: AtR Com | G95: MEP | K95: MEP | Master Plan - Master Plan | R95: MEP | V95: 0.038655112
C96: AtR Com | G96: MEP | K96: MEP | Master Plan - Site MEP | R96: MEP | V96: 0.12885037
A98: 1 | B98: TMFT -2 | G98: =SUM(K98:N98) -> 1 | K98: =COUNTA(K99:K99) -> 1 | L98: =COUNTA(L99:L99) -> 0 | M98: =COUNTA(M99:M99) -> 0 | N98: =COUNTA(N99:N99) -> 0 | R98: =SUM(V98:Y98) -> 0.059954281 | V98: =SUM(V99:V99) -> 0.059954281 | W98: =SUM(W99:W99) -> 0 | X98: =SUM(X99:X99) -> 0 | Y98: =SUM(Y99:Y99) -> 0
B99: Gagan | C99: TMFT -2 | G99: MEP | K99: MEP | Master Archives | R99: MEP | V99: 0.059954281
B101: SFTW | G101: =SUM(K101:N101) -> 6 | K101: =COUNTA(K102:K107) -> 3 | L101: =COUNTA(L102:L107) -> 3 | M101: =COUNTA(M102:M107) -> 0 | N101: =COUNTA(N102:N107) -> 0 | R101: =SUM(V101:Y101) -> 0.14474535 | V101: =SUM(V102:V107) -> 0.036500409 | W101: =SUM(W102:W107) -> 0.10824494 | X101: =SUM(X102:X107) -> 0 | Y101: =SUM(Y102:Y107) -> 0
B102: Gagan | C102: SFTW | G102: MEP | K102: MEP | ISS 01 - Foundations & Grade Slab | L102: MEP | Clubhouse—Interiors and Facilities | R102: MEP | V102: 0.0020340503 | W102: 0.0016660071
B103: Gagan | C103: SFTW | G103: MEP | K103: MEP | Master Plan - Site MEP | L103: MEP | Clubhouse—Sporting Facilities | R103: MEP | V103: 0.0023730586 | W103: 0.0005553357
B104: Gagan | C104: SFTW | G104: MEP | L104: MEP | Master Archives | R104: MEP | V104: 0.0062527566 | W104: 0.1060236
B105: Gagan | C105: SFTW | G105: MEP | K105: MEP | Clubhouse—Outdoor Spaces and Pool | R105: MEP | V105: 0.020842522
B106: Gagan | C106: SFTW | R106: MEP | V106: 0.0038873499
R107: MEP | V107: 0.0011106714
B109: PoaRR | G109: =SUM(K109:N109) -> 31 | K109: =COUNTA(K110:K137) -> 23 | L109: =COUNTA(L110:L137) -> 7 | M109: =COUNTA(M110:M137) -> 1 | N109: =COUNTA(N110:N137) -> 0 | R109: =SUM(V109:Y109) -> 2.3154 | V109: =SUM(V110:V137) -> 1.874 | W109: =SUM(W110:W137) -> 0.3614 | X109: =SUM(X110:X137) -> 0.08 | Y109: =SUM(Y110:Y137) -> 0
B110: Gagan | C110: PoaRR Res | G110: MEP | K110: ISS [Tower 1-7] - Podium Slab | R110: MEP | V110: 0.06
B111: Gagan | C111: PoaRR Res | G111: MEP | K111: Individual Homes - R11 Default and it's variants | R111: MEP | V111: 0.16
B112: Gagan | C112: PoaRR Res | G112: MEP | K112: Individual Homes - R22 Default and it's variants | R112: MEP | V112: 0.16
B113: Gagan | C113: PoaRR Res | G113: MEP | K113: Residential - Master Plan | R113: MEP | V113: 0.11
B114: Gagan | C114: PoaRR Res | G114: MEP | K114: MEP | Master Archives - Res | R114: MEP | V114: 0.24
B115: Gagan | C115: PoaRR Res | G115: MEP | R115: MEP
B116: Gagan | C116: PoaRR Res | G116: MEP | K116: Villa Cluster 3 - All Levels | R116: MEP | V116: 0.004
B117: Gagan | C117: PoaRR Res | G117: MEP | K117: Villa Cluster 3 - Building Envelope and Common Areas | R117: MEP | V117: 0.003
B118: Gagan | C118: PoaRR Res | G118: MEP | K118: V40 Default and it's variants | R118: MEP | V118: 0.16
B119: Gagan | C119: PoaRR Res | G119: MEP | R119: MEP
B120: Gagan | C120: PoaRR Res | G120: MEP | R120: MEP
C121: PoaRR Res | G121: MEP | R121: MEP
C122: PoaRR Res | G122: MEP | K122: Residential - Site MEP | R122: MEP | V122: 0.36
C123: PoaRR Res | G123: MEP | K123: Clubhouse—Outdoor Spaces and Pool | R123: MEP | V123: 0.002
C124: PoaRR Res | G124: MEP | K124: Sporting Facilities | R124: MEP | V124: 0.001
B126: Gagan | C126: PoaRR T08 | G126: MEP | K126: T08 - Foundation and Grade Slab | L126: T08 - R25 P Default and it's variants | M126: MEP | Master Archives - T08 | R126: MEP | V126: 0.09 | W126: 0.06 | X126: 0.08
B127: Gagan | C127: PoaRR T08 | G127: MEP | K127: T08 - Habitable Level 01 | L127: T08 - L20 P Default and it's variants | R127: MEP | V127: 0.11 | W127: 0.06
B128: Gagan | C128: PoaRR T08 | G128: MEP | K128: T08 - Penthouse Levels | L128: T08 - D35 P Default and it's variants | R128: MEP | V128: 0.09 | W128: 0.06
B129: Gagan | C129: PoaRR T08 | G129: MEP | K129: T08 - Terrace Level | L129: T08 - L22 P Default and it's variants | R129: MEP | V129: 0.09 | W129: 0.06
B130: Gagan | C130: PoaRR T08 | G130: MEP | K130: T08 - ISS - Foundations & Grade Slab | L130: T08 - Sporting Facilities | R130: MEP | V130: 0.01 | W130: 0.0004
B131: Gagan | C131: PoaRR T08 | G131: MEP | K131: T08 - ISS - Podium Slab | L131: T08 - Clubhouse—Outdoor Spaces and Pool | R131: MEP | V131: 0.01 | W131: 0.001
B132: Gagan | C132: PoaRR T08 | G132: MEP | K132: T08 - ISS - Parking Level Subgrade | L132: T08 - Site MEP | R132: MEP | V132: 0.03 | W132: 0.12
...

Sheet Prj List
B2: =COUNTA(B3:B103) -> 62 | C2: =COUNTA(C3:C103) -> 53
A3: Ongoing | B3: AtR | C3: 1
B4: AtR - 03 | C4: 1
B5: AtR - C | C5: 1
B6: PoaRR-Res | C6: 1
B7: PoaRR-T08 | C7: 1
B8: PoaRR-T09
B9: PoaRR-Workcations | C9: 1
B10: ITQE-Ph1 | C10: 1
B11: ITQE-Ph2a | C11: 1
B12: ITQE-Ph2b | C12: 1
B13: ITQE-Ph2c | C13: 1
B14: OTR-Ph01 | C14: 1
B15: OTR-Ph02 | C15: 1
B16: TMFT | C16: 1
B17: DBTW | C17: 1
B18: TMD | C18: 1
B19: LTF | C19: 1
B20: SftW | C20: 1
B21: 22a Sarjapur | C21: 1
B22: DonaPaula
B23: OtF
B24: KIADB - MC
A26: New Prj | B26: Vaderahalli | C26: 1
B27: NH37a - Acharalahalli | C27: 1
B28: NH 30a - Madakuhosahalli
B29: NH 10a
B30: TuiG | C30: 1
B31: Poinciana | C31: 1 | D31: On Hold
B32: Harohalli | C32: 1
B33: Violet hill | C33: 1
B34: Vijayapura | C34: 1
B35: Ambegaon | C35: 1
B36: Savakanahalli | C36: 1
B37: Aundh 3a | C37: 1
B38: Shreegaon | C38: 1
B39: Yadgarpalle | C39: 1
B40: Varthur 52a
B41: TR Mills Chamarajpet | C41: 1
B42: Lonavala | C42: 1
B43: Jhanjh Lake [Mayfair] | C43: 1
B44: Tumkur 33a | C44: 1
B45: Sarjapur - Plotted | C45: 1
B46: Mall of Asia | C46: 1
A48: DsgnBld | B48: MeenaSai Res | C48: 1
B49: NH Homestay | C49: 1
B50: OTR Museum | C50: 1
B51: Indiranagar Res | C51: 1
B52: Swisstown | C52: 1 | D52: On Hold
B53: Imagine | C53: 1
B54: LGCE | C54: 1
B55: Ooty Res | C55: 1
B56: MT Plano | C56: 1
B57: Saideep reddy Res,Hyd | C57: 1 | E57: New
B58: 5a GTC Indrngr | C58: 1 | E58: New
A60: HPL | B60: Tapestry
B61: Windmils, Hyd | C61: 1
B62: Windmils, Sftw
B63: TEHPL-OTR | C63: 1
A65: CSR | B65: Aud-Malleswaram | C65: 1
B66: tFS-2 | C66: 1
B67: PDC | C67: 1
B68: KPS-Mall | C68: 1

Sheet Sheet2
B2: Tracking mechanism for small scale design revision [eg. Partition mesh between Villas]
B5: Harohalli include package

Sheet 0099 OTF & 0098 BiG FY 26-27Q3
B2: OTF | Design package release FY26-27 Q3 | L2: =SUBTOTAL(9,L7:L87) -> 0 | M2: =SUBTOTAL(9,M7:M87) -> 0
B4: Project | C4: Description | D4: Release date | E4: Responsible | F4: Remarks | J4: Plan - Billing [Cr.] | K4: Plan - Pkgs | L4: Actuals - Billing [Cr.] | M4: Actuals - Pkgs | Q4: Design Lead | R4: Lead | S4: Person 1 | T4: Person 2 | U4: Person 3 | V4: Draftperson
B6: OTF | C6: Package Release | J6: =SUBTOTAL(9,J7:J87) -> 4.5893873 | K6: =SUBTOTAL(9,K7:K87) -> 23 | L6: =SUBTOTAL(9,L7:L87) -> 0 | M6: =SUBTOTAL(9,M7:M87) -> 0
B7: Master Planning | C7: LOD 350 - MP Pkg 1, BB02 Pkg 1, Project Entrance | J7: =SUBTOTAL(9,J8:J40) -> 3.3861433 | K7: =SUBTOTAL(9,K8:K40) -> 8 | L7: =SUBTOTAL(9,L8:L40) -> 0 | M7: =SUBTOTAL(9,M8:M40) -> 0
B8: OTF | C8: LoD 100 - Contract + Design Brief [Commercial] | D8: 46293 | E8: Naveen Y | J8: 0.3375 | K8: 1 | L8: =IF(M8=1,J8,0) -> 0 | Q8: Naveen Y | R8: Naveen Y | S8: Aswin J
B9: Step 1 | C9: Consultant contract- Site infrastructure (AUM) | F9: Advance Payment
B10: Step 2 | C10: Design Brief | F10: Sign off
B11: Step 3 | C11: LoD 100 - Architectural Concept | F11: Sign off
B12: OTF | C12: LoD 200 - Schematic Concept | D12: 46328 | E12: Naveen Y | J12: 0.58 | K12: 1 | L12: =IF(M12=1,J12,0) -> 0 | Q12: Naveen Y | R12: Naveen Y | S12: Aswin J
B13: Step 1 | C13: Site Grading, Traffic, Stormwater, Site infrastructure (PHE, Electrical) - Schematic design | E13: AUM Consultants
B14: Step 2 | C14: Landscape - Irrigation plans, Planting layouts | E14: Lajja
B15: Step 3 | C15: LoD 200 - Arch Schematic | E15: Aswin J | F15: Coordinated Masterplan
B16: OTF | C16: Approvals | D16: 46332 | E16: Naveen Y | J16: 0.58 | K16: 1 | L16: =IF(M16=1,J16,0) -> 0 | Q16: Naveen Y | R16: Aswin J | S16: Mithoon
B17: Step 1 | C17: Development Plan and CFE (Rework based on new ADLR Sketch) | E17: Aswin J/Bhavya / Eranna
B18: Step 2 | C18: RERA (Based on CFE approvals) | E18: Aswin J/ Chandan
B19: OTF | C19: LoD 300 - Pre Construction Set (Phase 1a & Phase 1) | D19: 46364 | E19: Naveen Y | F19: Phase 1a- Project Entrance, Exp homes, Sales lounge, Site office Phase 1- To be decided | J19: 0.58 | K19: 1 | L19: =IF(M19=1,J19,0) -> 0 | Q19: Naveen Y | R19: Aswin J | S19: Mithoon
B20: Step 1 | C20: Phase 1- Phasing to be decided | E20: Paul
B21: Step 2 | C21: Phase 1a- Site Infrastructure - Masterplan | E21: AUM Consultants | F21: Road Grading, Retaining walls, Infra layouts, Chamber details, Storm drain network & sewer layout and traffic circulations.
B22: Step 3 | C22: Phase 1a- PHE and Electrical layout | E22: Eranna | F22: Equipement and cable routing layout, feeder pilars and earthing
B23: Step 4 | C23: LoD 300 | Phase 1a - Masterplan | E23: Aswin J
B24: Step 5 | C24: LoD 300 | Phase 1a - General Arrangment plan | E24: Aswin J
B25: Step 6 | C25: LoD 300 | Phase 1a - Setting out plan | E25: Aswin J
B26: Step 7 | C26: LoD 300 | Phase 1a - Internal Signages, Street Fixtures | E26: Aswin J
B27: Step 8 | C27: LoD 300 | Phase 1a - Driveway Layouts | E27: Aswin J
B28: OTF | C28: LoD 200 - Marketing and Sales | D28: 46352 | E28: Naveen Y | J28: 0.3375 | K28: 1 | L28: =IF(M28=1,J28,0) -> 0 | Q28: Naveen Y | R28: Aswin J | S28: Mithoon
B29: Step 1 | C29: Rendered Masterplan based on new MP layout | E29: Aswin J
B30: Step 2 | C30: Visualization | E30: Sijo/Ashwin/ Aswin J | F30: Festival Street- 8 Views; Residential area- 5 views; Aerial Views- 3
C31: Walkthroughs
B32: OTF | C32: LoD 350 - Project Entrance & Phase 1a | D32: 46295 | E32: Naveen Y | J32: 0.3375 | K32: 1 | L32: =IF(M32=1,J32,0) -> 0 | Q32: Naveen Y | R32: Aswin J | S32: Mithoon
B33: Step 1 | C33: GFCs- Security cabin, Boundary wall, Project signage and Driveways (Phase 1a) | E33: Mithoon A/ Ojas V/ Aswin J
B34: Step 2 | C34: GFC- MP Phase 1a (Setting out plans, signages, survey nos, setbacks and plot dimensions) - Dependency on AUM | E34: Aswin J/ AUM Consultants
B35: OTF | C35: LoD 350 - BB02 | Festival Street - Retail Shops - Foundation and Structure | D35: 46380 | E35: Naveen Y | J35: 0.053643324 | K35: 1 | L35: =IF(M35=1,J35,0) -> 0 | Q35: Naveen Y | R35: Aswin J
B36: Step 1 | C36: Reviewing retail Module sketch with Shibanee ma'am (LoD100) | E36: Naveen Y/ Aswin J
B37: Step 2 | C37: Structure Coordination | E37: Lincy R
B38: Step 3 | C38: LoD 200- Developing the form, structure and internal layouts | E38: Aswin J
B39: Step 4 | C39: Lod 350- GFCs | E39: Aswin J
B40: OTF | C40: LoD 350 - Infra - Grading | D40: 46400 | E40: Naveen Y | J40: 0.58 | K40: 1 | L40: =IF(M40=1,J40,0) -> 0 | Q40: Naveen Y | R40: Aswin J
B41: Step 1 | C41: Coordinatiin with site infrastructure, MEP & traffic circulation | E41: AUM Consultants
B42: Step 2 | C42: Coordinated GFCs based on shop drawings | E42: Aswin J/ AUM Consultants
B43: Architecture | C43: LoD 300 - Pre Construction set - CH | J43: =SUBTOTAL(9,J44:J50) -> 0.285 | K43: =SUBTOTAL(9,K44:K50) -> 3 | L43: =SUBTOTAL(9,L44:L50) -> 0 | M43: =SUBTOTAL(9,M44:M50) -> 0
B44: OTF | C44: LoD 200 - Schematic Concept - CH | D44: 46310 | E44: Om Prakash | J44: 0.095 | K44: 1 | L44: =IF(M44=1,J44,0) -> 0 | Q44: Om Prakash | R44: Aparna S
B45: Step 1 | C45: Task Description | E45: User 1
B46: Step 2 | C46: Task Description | E46: User 2
B47: OTF | C47: Approvals - CH | D47: 46317 | E47: Om Prakash | J47: 0.095 | K47: 1 | L47: =IF(M47=1,J47,0) -> 0 | Q47: Om Prakash | R47: Aparna S
B48: Step 1 | C48: Task Description | E48: User 1
B49: Step 2 | C49: Task Description | E49: User 2
B50: OTF | C50: LoD 300 - Pre Construction set - CH | D50: 46367 | E50: Om Prakash | J50: 0.095 | K50: 1 | L50: =IF(M50=1,J50,0) -> 0 | Q50: Om Prakash | R50: Aparna S
B51: Step 1 | C51: Task Description | E51: User 1
B52: Step 2 | C52: Task Description | E52: User 2
B53: Structural | C53: LOD 350 - MP Pkg 1, BB02 Pkg 1, Project Entrance | J53: =SUBTOTAL(9,J54:J60) -> 0.5724 | K53: =SUBTOTAL(9,K54:K60) -> 3 | L53: =SUBTOTAL(9,L54:L60) -> 0 | M53: =SUBTOTAL(9,M54:M60) -> 0
B54: OTF | C54: LoD 200 - Schematic Concept | D54: 46329 | E54: Prakash C | J54: 0.1431 | K54: 1 | L54: =IF(M54=1,J54,0) -> 0 | Q54: Prakash C | R54: Satish | S54: Alwin | T54: Raghav | U54: Darshan
B55: Step 1 | C55: Task Description | E55: User 1
B56: Step 2 | C56: Task Description | E56: User 2
B57: OTF | C57: LoD 300 - Pre Construction Set | D57: 46365 | E57: Prakash C | J57: 0.2862 | K57: 1 | L57: =IF(M57=1,J57,0) -> 0 | Q57: Prakash C | R57: Satish | S57: Alwin | T57: Raghav | U57: Darshan
B58: Step 1 | C58: Task Description | E58: User 1
B59: Step 2 | C59: Task Description | E59: User 2
B60: OTF | C60: LoD 350 - Project Entrance | D60: 46295 | E60: Prakash C | J60: 0.1431 | K60: 1 | L60: =IF(M60=1,J60,0) -> 0 | Q60: Prakash C | R60: Lincy | S60: Charan
B61: Step 1 | C61: Security cabin | E61: User 1 | F61: approval on drawings awaited (25 days for GFC)
B62: Step 2 | C62: Sales lounge ? | E62: User 2 | F62: Standard drawings available (20 days GFC)
B63: OTF | C63: LoD 350 - BB02 | Festival Street - Retail Shops - Foundation and Structure | D63: 46380 | E63: Prakash C | J63: 0.032337546 | K63: 1 | L63: =IF(M63=1,J63,0) -> 0 | Q63: Prakash C | R63: Lincy | S63: Subrahmanya
B64: Step 1 | C64: Modules - form and material to be finalised | E64: User 1 | F64: Details awaited (est duration after receving detials)
B65: Step 2 | E65: User 2
B66: OTF | C66: LoD 350 - Infra - Grading | D66: 46400 | E66: Prakash C | J66: 0.06 | K66: 1 | L66: =IF(M66=1,J66,0) -> 0 | Q66: Prakash C | R66: Satish | S66: Alwin | T66: Raghav | U66: Darshan
B67: Step 1 | C67: Task Description | E67: User 1
B68: Step 2 | C68: Task Description | E68: User 2
B69: MEP | C69: LoD 350 - BB02 Pkg 1, Project Entrance | J69: =SUBTOTAL(9,J70:J79) -> 0.1644064 | K69: =SUBTOTAL(9,K70:K79) -> 4 | L69: =SUBTOTAL(9,L70:L79) -> 0 | M69: =SUBTOTAL(9,M70:M79) -> 0
B70: OTF | C70: LoD 200 - Schematic Concept | D70: 46329 | E70: Gagan | J70: 0.039825 | K70: 1 | L70: =IF(M70=1,J70,0) -> 0 | Q70: Gagan | R70: Salomi | S70: Eranna Bhavya Hareesha | T70: Avinash Prem Matsarambabu
B71: Step 1 | C71: Task Description | E71: User 1
B72: Step 2 | C72: Task Description | E72: User 2
B73: OTF | C73: LoD 300 - Pre Construction Set | D73: 46365 | E73: Gagan | J73: 0.07965 | K73: 1 | L73: =IF(M73=1,J73,0) -> 0 | Q73: Gagan | R73: Salomi | S73: Eranna Bhavya Hareesha | T73: Avinash Prem Matsarambabu
B74: Step 1 | C74: Task Description | E74: User 1
B75: Step 2 | C75: Task Description | E75: User 2
B76: OTF | C76: LoD 350 - BB02 | Festival Street - Retail Shops - Foundation and Structure | D76: 46380 | E76: Gagan | J76: 0.0051063975 | K76: 1 | L76: =IF(M76=1,J76,0) -> 0 | Q76: Gagan | R76: Salomi | S76: Eranna Bhavya Hareesha | T76: Avinash Prem Matsarambabu
B77: Step 1 | C77: Task Description | E77: User 1
B78: Step 2 | C78: Task Description | E78: User 2
B79: OTF | C79: LoD 350 - Project Entrance | D79: 46295 | E79: Gagan | J79: 0.039825 | K79: 1 | L79: =IF(M79=1,J79,0) -> 0 | Q79: Gagan | R79: Salomi | S79: Eranna Bhavya Hareesha | T79: Avinash Prem Matsarambabu
B80: Step 1 | C80: Task Description | E80: User 1
B81: Step 2 | C81: Task Description | E81: User 2
B82: Landscape | C82: LoD 350 - Project Entrance | J82: =SUBTOTAL(9,J83:J87) -> 0.0891 | K82: =SUBTOTAL(9,K83:K87) -> 3 | L82: =SUBTOTAL(9,L83:L87) -> 0 | M82: =SUBTOTAL(9,M83:M87) -> 0
B83: OTF | C83: LoD 200 - Schematic Concept | D83: 46329 | E83: Gagan | J83: 0.04455 | K83: 1 | L83: =IF(M83=1,J83,0) -> 0 | Q83: Gagan | R83: Lajja | S83: Aproova | T83: Chetan
B84: Step 1 | C84: Schematic concept | E84: Nihareeka
B85: OTF | C85: LoD 300 - Pre Construction Set | D85: 46365 | E85: Gagan | J85: 0.022275 | K85: 1 | L85: =IF(M85=1,J85,0) -> 0 | Q85: Gagan | R85: Lajja | S85: Aproova | T85: Chetan
B86: Step 1 | C86: Pre construction set | E86: Nihareeka
B87: OTF | C87: LoD 350 - Project Entrance | D87: 46295 | E87: Gagan | J87: 0.022275 | K87: 1 | L87: =IF(M87=1,J87,0) -> 0 | Q87: Gagan | R87: Lajja | S87: Aproova | T87: Chetan
B88: Step 1 | C88: Project Entrance | E88: Nihareeka
B89: OTF [V35] | C89: OTF [V35] | K89: =SUBTOTAL(9,K90:K96) -> 3 | M89: =SUBTOTAL(9,M90:M96) -> 0
B90: OTF | C90: Shell + Interior GFC | D90: 46295 | E90: Atul P | K90: 1 | Q90: Atul P
B91: Step 1 | C91: Task Description | E91: User 1
B92: Step 2 | C92: Task Description | E92: User 2
B93: OTF | C93: Design Specs + GFC | D93: 46326 | E93: Atul P | K93: 1 | Q93: Atul P
B94: Step 1 | C94: Task Description | E94: User 1
B95: Step 2 | C95: Task Description | E95: User 2
B96: OTF | C96: Default Marketing BoQ | D96: 46326 | E96: Atul P | K96: 1 | Q96: Atul P
B97: Step 1 | C97: Task Description | E97: User 1
B98: Step 2 | C98: Task Description | E98: User 2
B99: OTF [V60] | C99: OTF [V60] | K99: 2 | M99: =SUBTOTAL(9,M100:M106) -> 0
B100: OTF | C100: Shell + Interior GFC | D100: 46295 | E100: Atul P | K100: 1 | Q100: Atul P
B101: Step 1 | C101: Task Description | E101: User 1
B102: Step 2 | C102: Task Description | E102: User 2
B103: OTF | C103: Design Specs + GFC | D103: 46326 | E103: Atul P | K103: 1 | Q103: Atul P
...

Sheet 0099 OTF -Pkgs Summary (Status)
C2: 0099 | One Tiny Flower | F2: AR | H2: ST | J2: MEP | L2: LS | O2: 1 | P2: Completed
D3: Scope | F3: =COUNTA(F$8:F$54) -> 29 | H3: =COUNTA(H$8:H$54) -> 22 | J3: =COUNTA(J$8:J$54) -> 25 | L3: =COUNTA(L$8:L$54) -> 21 | O3: -1 | P3: Pending
D4: Actuals | F4: =COUNTIF(F$8:F$54,1) -> 0 | H4: =COUNTIF(H$8:H$54,1) -> 0 | J4: =COUNTIF(J$8:J$54,1) -> 1 | L4: =COUNTIF(L$8:L$54,1) -> 1 | P4: NA
C8: DESIGN CONCEPT
B10: 1 | C10: 1 | D10: Contract + Design Brief | F10: -1
B11: 2 | C11: 2 | D11: Schematic Concept | F11: -1 | H11: -1 | J11: -1 | L11: -1
B12: 3 | C12: 3 | D12: Pre Construction Set | F12: -1 | H12: -1 | J12: -1 | L12: -1
B13: 4 | C13: 4 | D13: Approvals | F13: -1 | J13: 1 | L13: 1
B14: 5 | C14: 5 | D14: Experience Home + Project Experience | F14: -1 | H14: -1 | J14: -1 | L14: -1
B15: 6 | C15: 6 | D15: Marketing and Sales | F15: -1
C16: CONSTRUCTION DOCUMENTS
B18: 7 | C18: 1 | D18: GFC | Master Plan
B19: MP 01 | C19: 1 | D19: Infra - Grading | F19: -1 | H19: -1
B20: MP 02 | C20: 2 | D20: Infra - MEP | F20: -1 | H20: -1 | J20: -1 | L20: -1
B21: MP 03 | C21: 3 | D21: BOQ & Technical Specifications | F21: -1 | J21: -1 | L21: -1
B22: MP 04 | C22: 4 | D22: Infra - Coordinated | J22: -1 | L22: -1
B23: MP 05 | C23: 5 | D23: Structures - Security Cabin and Entrance | F23: -1 | H23: -1 | J23: -1 | L23: -1
B24: MP 06 | C24: 6 | D24: Infra - Plot Boundary & Enclosures | F24: -1 | H24: -1 | L24: -1
B25: MP 07 | C25: 7 | D25: Infra - Signage & Street Lighting | F25: -1 | H25: -1 | J25: -1 | L25: -1
B26: MP 08 | C26: 8 | D26: Structures - Electrical Room & Toilet Block | F26: -1 | H26: -1 | J26: -1 | L26: -1
B27: MP 09 | C27: 9 | D27: Structures - UGT | F27: -1 | H27: -1 | J27: -1 | L27: -1
B28: MP 10 | C28: 10 | D28: Structures - OHT | F28: -1 | H28: -1 | J28: -1 | L28: -1
B29: MP 11 | C29: 11 | D29: Structures - STP | F29: -1 | H29: -1 | J29: -1 | L29: -1
B30: MP 12 | C30: 12 | D30: Structures - OWC & other structure | F30: -1 | H30: -1 | J30: -1 | L30: -1
B31: 8 | C31: 2 | D31: GFC | Home Products [FKH]
A32: ="Amenities & Facilities - "&D32 -> Amenities & Facilities - V35 - Product Package [FKH] | B32: AR-V35 | C32: 1 | D32: V35 - Product Package [FKH]
A33: ="Amenities & Facilities - "&D33 -> Amenities & Facilities - V60 - Product Package [FKH] | B33: AR-V60 | C33: 2 | D33: V60 - Product Package [FKH]
B34: 9 | C34: 3 | D34: GFC | F&B Block
A35: ="Amenities & Facilities - "&D35 -> Amenities & Facilities - Foundation and Structure | B35: AR-BB1-1 | C35: 1 | D35: Foundation and Structure | F35: -1 | H35: -1 | J35: -1
A36: ="Amenities & Facilities - "&D36 -> Amenities & Facilities - Building Envelope + MEP | B36: AR-BB1-2 | C36: 2 | D36: Building Envelope + MEP | F36: -1 | H36: -1 | J36: -1 | L36: -1
A37: ="Amenities & Facilities - "&D37 -> Amenities & Facilities - Interiors | B37: AR-BB1-3 | C37: 3 | D37: Interiors | F37: -1 | J37: -1
B38: 10 | C38: 4 | D38: GFC | Festival Street - Retail Shops
A39: ="Amenities & Facilities - "&D39 -> Amenities & Facilities - Foundation and Structure | B39: AR-BB2-1 | C39: 1 | D39: Foundation and Structure | F39: -1 | H39: -1 | J39: -1
A40: ="Amenities & Facilities - "&D40 -> Amenities & Facilities - Building Envelope + MEP | B40: AR-BB2-2 | C40: 2 | D40: Building Envelope + MEP | F40: -1 | H40: -1 | J40: -1 | L40: -1
A41: ="Amenities & Facilities - "&D41 -> Amenities & Facilities - Interiors | B41: AR-BB2-3 | C41: 3 | D41: Interiors | F41: -1 | J41: -1
B42: 11 | C42: 5 | D42: GFC | Amenities & Facilities
A43: ="Amenities & Facilities - "&D43 -> Amenities & Facilities - Clubhouse—Structure and Envelope | B43: AM 01 | C43: 1 | D43: Clubhouse—Structure and Envelope | F43: -1 | H43: -1 | J43: -1
A44: ="Amenities & Facilities - "&D44 -> Amenities & Facilities - Clubhouse—Interiors and Facilities | B44: AM 02 | C44: 2 | D44: Clubhouse—Interiors and Facilities | F44: -1 | J44: -1 | L44: -1
A45: ="Amenities & Facilities - "&D45 -> Amenities & Facilities - Clubhouse—Outdoor Spaces and pool | B45: AM 03 | C45: 3 | D45: Clubhouse—Outdoor Spaces and pool | F45: -1 | H45: -1 | J45: -1 | L45: -1
A46: ="Amenities & Facilities - "&D46 -> Amenities & Facilities - Community spaces [Children play area, Open Park space] | B46: AM 04 | C46: 4 | D46: Community spaces [Children play area, Open Park space] | F46: -1 | H46: -1 | L46: -1
A47: ="Amenities & Facilities - "&D47 -> Amenities & Facilities - Sporting Facilities | B47: AM 05 | C47: 5 | D47: Sporting Facilities | F47: -1 | H47: -1 | J47: -1
C49: POST-CONSTRUCTION
B51: 12 | C51: 1 | D51: Master Archives
B52: MA | C52: 1 | D52: Complete set of "As-Built" drawings, final BoQ and project costs, | F52: -1 | H52: -1 | J52: -1 | L52: -1
C54: MAJOR REWORKS

Sheet 0098 BiG -Pkgs Summary (Status)
C2: 0098 | Blue in Green | F2: AR | H2: ST | J2: MEP | L2: LS | O2: 1 | P2: Completed
D3: Scope | F3: =COUNTA(F$8:F$120) -> 90 | H3: =COUNTA(H$8:H$120) -> 62 | J3: =COUNTA(J$8:J$120) -> 53 | L3: =COUNTA(L$8:L$120) -> 14 | O3: -1 | P3: Pending
D4: Actuals | F4: =COUNTIF(F$8:F$120,1) -> 1 | H4: =COUNTIF(H$8:H$120,1) -> 0 | J4: =COUNTIF(J$8:J$120,1) -> 0 | L4: =COUNTIF(L$8:L$120,1) -> 0 | P4: NA
C8: DESIGN CONCEPT
B10: 1 | C10: 1 | D10: Contract + Design Brief | F10: 1
B11: 2 | C11: 2 | D11: Schematic Concept | F11: -1 | H11: -1 | J11: -1 | L11: -1
B12: 3 | C12: 3 | D12: Pre Construction Set | F12: -1 | H12: -1 | J12: -1 | L12: -1
B13: 4 | C13: 4 | D13: Approvals | F13: -1 | J13: -1 | L13: -1
B14: 5 | C14: 5 | D14: Experience Home + Project Experience | F14: -1 | H14: -1 | J14: -1 | L14: -1
B15: 6 | C15: 6 | D15: Marketing and Sales | F15: -1
C16: CONSTRUCTION DOCUMENTS
B18: 7 | C18: 1 | D18: GFC | Tower -1
B19: BB01-1 | C19: 1 | D19: Foundation and Grade Slab | F19: -1 | H19: -1 | J19: -1
B20: BB01-2 | C20: 2 | D20: Parking Level-Sub grade | F20: -1 | H20: -1
B21: BB01-3 | C21: 3 | D21: Building Envelope and Common Areas [Basement] | F21: -1
B22: BB01-4 | C22: 4 | D22: Habitable Level 01 + Tower MEP | F22: -1 | H22: -1 | J22: -1
B23: BB01-5 | C23: 5 | D23: Habitable Level - 2-10 | F23: -1 | H23: -1
B24: BB01-6 | C24: 6 | D24: Habitable Level - 11-20 | F24: -1 | H24: -1
B25: BB01-7 | C25: 7 | D25: Building Envelope and Common Areas [Typical Tower Levels] | F25: -1 | J25: -1
B26: BB01-8 | C26: 8 | D26: Penthouse Levels | F26: -1 | H26: -1 | J26: -1
B27: BB01-9 | C27: 9 | D27: Terrace Level | F27: -1 | H27: -1 | J27: -1
B28: BB01-10 | C28: 10 | D28: Building Envelope and Common Areas [Penthouse Levels And Terrace Level] | F28: -1
B29: 8 | C29: 2 | D29: GFC | Tower -2
B30: BB02-1 | C30: 1 | D30: Foundation and Grade Slab | F30: -1 | H30: -1 | J30: -1
B31: BB02-2 | C31: 2 | D31: Parking Level-Sub grade | F31: -1 | H31: -1
B32: BB02-3 | C32: 3 | D32: Building Envelope and Common Areas [Basement] | F32: -1
B33: BB02-4 | C33: 4 | D33: Habitable Level 01 + Tower MEP | F33: -1 | H33: -1 | J33: -1
B34: BB02-5 | C34: 5 | D34: Habitable Level - 2-10 | F34: -1 | H34: -1
B35: BB02-6 | C35: 6 | D35: Habitable Level - 11-20 | F35: -1 | H35: -1
B36: BB02-7 | C36: 7 | D36: Building Envelope and Common Areas [Typical Tower Levels] | F36: -1 | J36: -1
B37: BB02-8 | C37: 8 | D37: Penthouse Levels | F37: -1 | H37: -1 | J37: -1
B38: BB02-9 | C38: 9 | D38: Terrace Level | F38: -1 | H38: -1 | J38: -1
B39: BB02-10 | C39: 10 | D39: Building Envelope and Common Areas [Penthouse Levels And Terrace Level] | F39: -1
B40: 9 | C40: 3 | D40: GFC | Tower -3
B41: BB03-1 | C41: 1 | D41: Foundation and Grade Slab | F41: -1 | H41: -1 | J41: -1
B42: BB03-2 | C42: 2 | D42: Parking Level-Sub grade | F42: -1 | H42: -1
B43: BB03-3 | C43: 3 | D43: Building Envelope and Common Areas [Basement] | F43: -1
B44: BB03-4 | C44: 4 | D44: Habitable Level 01 + Tower MEP | F44: -1 | H44: -1 | J44: -1
B45: BB03-5 | C45: 5 | D45: Habitable Level - 2-10 | F45: -1 | H45: -1
B46: BB03-6 | C46: 6 | D46: Habitable Level - 11-20 | F46: -1 | H46: -1
B47: BB03-7 | C47: 7 | D47: Building Envelope and Common Areas [Typical Tower Levels] | F47: -1 | J47: -1
B48: BB03-8 | C48: 8 | D48: Penthouse Levels | F48: -1 | H48: -1 | J48: -1
B49: BB03-9 | C49: 9 | D49: Terrace Level | F49: -1 | H49: -1 | J49: -1
B50: BB03-10 | C50: 10 | D50: Building Envelope and Common Areas [Penthouse Levels And Terrace Level] | F50: -1
B51: 10 | C51: 4 | D51: GFC | Tower -4
B52: BB04-1 | C52: 1 | D52: Foundation and Grade Slab | F52: -1 | H52: -1 | J52: -1
B53: BB04-2 | C53: 2 | D53: Parking Level-Sub grade | F53: -1 | H53: -1
B54: BB04-3 | C54: 3 | D54: Building Envelope and Common Areas [Basement] | F54: -1
B55: BB04-4 | C55: 4 | D55: Habitable Level 01 + Tower MEP | F55: -1 | H55: -1 | J55: -1
B56: BB04-5 | C56: 5 | D56: Habitable Level - 2-10 | F56: -1 | H56: -1
B57: BB04-6 | C57: 6 | D57: Habitable Level - 11-20 | F57: -1 | H57: -1
B58: BB04-7 | C58: 7 | D58: Building Envelope and Common Areas [Typical Tower Levels] | F58: -1 | J58: -1
B59: BB04-8 | C59: 8 | D59: Penthouse Levels | F59: -1 | H59: -1 | J59: -1
B60: BB04-9 | C60: 9 | D60: Terrace Level | F60: -1 | H60: -1 | J60: -1
B61: BB04-10 | C61: 10 | D61: Building Envelope and Common Areas [Penthouse Levels And Terrace Level] | F61: -1
B62: 11 | C62: 5 | D62: GFC | Tower -5
B63: BB05-1 | C63: 1 | D63: Foundation and Grade Slab | F63: -1 | H63: -1 | J63: -1
B64: BB05-2 | C64: 2 | D64: Parking Level-Sub grade | F64: -1 | H64: -1
B65: BB05-3 | C65: 3 | D65: Building Envelope and Common Areas [Basement] | F65: -1
B66: BB05-4 | C66: 4 | D66: Habitable Level 01 + Tower MEP | F66: -1 | H66: -1 | J66: -1
B67: BB05-5 | C67: 5 | D67: Habitable Level - 2-10 | F67: -1 | H67: -1
B68: BB05-6 | C68: 6 | D68: Habitable Level - 11-20 | F68: -1 | H68: -1
B69: BB05-7 | C69: 7 | D69: Building Envelope and Common Areas [Typical Tower Levels] | F69: -1 | J69: -1
B70: BB05-8 | C70: 8 | D70: Penthouse Levels | F70: -1 | H70: -1 | J70: -1
B71: BB05-9 | C71: 9 | D71: Terrace Level | F71: -1 | H71: -1 | J71: -1
B72: BB05-10 | C72: 10 | D72: Building Envelope and Common Areas [Penthouse Levels And Terrace Level] | F72: -1
B73: 12 | C73: 6 | D73: GFC | Tower -6
B74: BB06-1 | C74: 1 | D74: Foundation and Grade Slab | F74: -1 | H74: -1 | J74: -1
B75: BB06-2 | C75: 2 | D75: Parking Level-Sub grade | F75: -1 | H75: -1
B76: BB06-3 | C76: 3 | D76: Building Envelope and Common Areas [Basement] | F76: -1
B77: BB06-4 | C77: 4 | D77: Habitable Level 01 + Tower MEP | F77: -1 | H77: -1 | J77: -1
B78: BB06-5 | C78: 5 | D78: Habitable Level - 2-10 | F78: -1 | H78: -1
B79: BB06-6 | C79: 6 | D79: Habitable Level - 11-20 | F79: -1 | H79: -1
B80: BB06-7 | C80: 7 | D80: Building Envelope and Common Areas [Typical Tower Levels] | F80: -1 | J80: -1
B81: BB06-8 | C81: 8 | D81: Penthouse Levels | F81: -1 | H81: -1 | J81: -1
B82: BB06-9 | C82: 9 | D82: Terrace Level | F82: -1 | H82: -1 | J82: -1
B83: BB06-10 | C83: 10 | D83: Building Envelope and Common Areas [Penthouse Levels And Terrace Level] | F83: -1
B84: 13 | C84: 7 | D84: GFC | Independent Subgrade Structure - 1
A85: ="Amenities & Facilities - "&D85 -> Amenities & Facilities - Earthwork | B85: BB07-1 | C85: 1 | D85: Earthwork | H85: -1
A86: ="Amenities & Facilities - "&D86 -> Amenities & Facilities - Foundations & Grade Slab | B86: BB07-2 | C86: 2 | D86: Foundations & Grade Slab | F86: -1 | H86: -1 | J86: -1
A87: ="Amenities & Facilities - "&D87 -> Amenities & Facilities - Parking Level Slab - Sub grade | B87: BB07-3 | C87: 3 | D87: Parking Level Slab - Sub grade | F87: -1 | H87: -1 | J87: -1
A88: ="Amenities & Facilities - "&D88 -> Amenities & Facilities - Podium Slab | B88: BB07-4 | C88: 4 | D88: Podium Slab | F88: -1 | H88: -1 | J88: -1
A89: ="Amenities & Facilities - "&D89 -> Amenities & Facilities - Building Envelope and Common Areas | B89: BB07-5 | C89: 5 | D89: Building Envelope and Common Areas | F89: -1 | J89: -1
B90: 14 | C90: 8 | D90: GFC | Independent Subgrade Structure - 2
A91: ="Amenities & Facilities - "&D91 -> Amenities & Facilities - Earthwork | B91: BB08-1 | C91: 1 | D91: Earthwork | H91: -1
A92: ="Amenities & Facilities - "&D92 -> Amenities & Facilities - Foundations & Grade Slab | B92: BB08-2 | C92: 2 | D92: Foundations & Grade Slab | F92: -1 | H92: -1 | J92: -1
A93: ="Amenities & Facilities - "&D93 -> Amenities & Facilities - Parking Level Slab - Sub grade | B93: BB08-3 | C93: 3 | D93: Parking Level Slab - Sub grade | F93: -1 | H93: -1 | J93: -1
A94: ="Amenities & Facilities - "&D94 -> Amenities & Facilities - Podium Slab | B94: BB08-4 | C94: 4 | D94: Podium Slab | F94: -1 | H94: -1 | J94: -1
A95: ="Amenities & Facilities - "&D95 -> Amenities & Facilities - Building Envelope and Common Areas | B95: BB08-5 | C95: 5 | D95: Building Envelope and Common Areas | F95: -1 | J95: -1
B96: 15 | C96: 9 | D96: GFC | Master Plan
A97: ="Amenities & Facilities - "&D97 -> Amenities & Facilities - Master Plan | B97: MP 01 | C97: 1 | D97: Master Plan | F97: -1 | J97: -1 | L97: -1
A98: ="Amenities & Facilities - "&D98 -> Amenities & Facilities - Site Development- 02 Road works | B98: MP 02 | C98: 2 | D98: Site Development- 02 Road works | F98: -1 | H98: -1
A99: ="Amenities & Facilities - "&D99 -> Amenities & Facilities - Site MEP- 03 Utilities | B99: MP 03 | C99: 3 | D99: Site MEP- 03 Utilities | F99: -1 | H99: -1 | J99: -1
A100: ="Amenities & Facilities - "&D100 -> Amenities & Facilities - Site Development- 04 Site Structures | B100: MP 04 | C100: 4 | D100: Site Development- 04 Site Structures | F100: -1 | H100: -1 | J100: -1
A101: ="Amenities & Facilities - "&D101 -> Amenities & Facilities - Site Development- 05 Signages | B101: MP 05 | C101: 5 | D101: Site Development- 05 Signages | F101: -1 | H101: -1
A102: ="Amenities & Facilities - "&D102 -> Amenities & Facilities - Site Development- 06 Landscape | B102: MP 06 | C102: 6 | D102: Site Development- 06 Landscape | F102: -1 | L102: -1
B103: 16 | C103: 10 | D103: GFC | Amenities & Facilities
A104: ="Amenities & Facilities - "&D104 -> Amenities & Facilities - Clubhouse—Structure and Envelope | B104: AM 01 | C104: 1 | D104: Clubhouse—Structure and Envelope | F104: -1 | H104: -1 | J104: -1
A105: ="Amenities & Facilities - "&D105 -> Amenities & Facilities - Clubhouse—Interiors and Facilities | B105: AM 02 | C105: 2 | D105: Clubhouse—Interiors and Facilities | F105: -1 | J105: -1 | L105: -1
A106: ="Amenities & Facilities - "&D106 -> Amenities & Facilities - Clubhouse—Outdoor Spaces and pool | B106: AM 03 | C106: 3 | D106: Clubhouse—Outdoor Spaces and pool | F106: -1 | H106: -1 | L106: -1
...

Sheet Goals, Actuals 2026 Q1
H1: Plan 26Q1 | K1: Actual 26Q1 | O1: AR | P1: STR | Q1: MEP | R1: LDS
B2: 2026 | Design Goals + Billing | H2: Billing [Cr.] | I2: Pkgs | K2: Billing [Cr.] | L2: Pkgs | N2: =SUM(O2:R2) -> 419 | O2: 189 | P2: 115 | Q2: 73 | R2: 42
B4: Project | C4: Phase | D4: Discipline | E4: Design Lead | F4: Description | H4: =SUM(H6+H370) -> 115.6358 | I4: =SUM(I6+I370) -> 422 | K4: =SUM(K6+K370) -> 9.4373263 | L4: =SUM(L6+L370) -> 40 | N4: =SUM(O4:R4) -> 18 | O4: 4 | P4: 7 | Q4: 4 | R4: 3
B6: Ongoing Projects | H6: =SUM(H8,H20,H67,H82,H102,H135,H144,H154,H176,H189,H205,H224,H227,H258,H280,H287,H300,H313,H324,H344,H354,H361,H367,H80) -> 38.489201 | I6: =SUM(I8,I20,I67,I82,I102,I135,I144,I154,I176,I189,I205,I224,I227,I258,I280,,I287,I300,I313,I324,I344,I354,I361,I367,I80) -> 272 | K6: =SUM(K8,K20,K67,K82,K102,K135,K144,K154,K176,K189,K205,K224,K227,K258,K280,K287,K300,K313,K324,K344,K354,K361,K367,K80) -> 6.8334517 | L6: =SUM(L8,L20,L67,L82,L102,L135,L144,L154,L176,L189,L205,L224,L227,L258,L280,,L287,L300,L313,L324,L344,L354,L361,L367,L80) -> 32
B8: AtR | C8: Ph 1, 2a, 2b, 2c | F8: Package Release [Complete LoD 350 by Q1] | H8: =SUM(H9,H14,H18) -> 0.4327194 | I8: =SUM(I9,I14,I18) -> 8 | K8: =SUM(K9,K14,K18) -> 0 | L8: =SUM(L9,L14,L18) -> 0
B9: AtR | C9: Ph 1, 2a, 2b, 2c | D9: Architecture | F9: Package Release [Complete LoD 350 by Q1] | H9: =SUM(H10:H13) -> 0.39703158 | I9: =SUM(I10:I13) -> 4 | K9: =SUM(K10:K13) -> 0 | L9: =SUM(L10:L13) -> 0
B10: AtR | C10: Ph 1, 2a, 2b | D10: Architecture | E10: Saji A | F10: Clubhouse + Amenities - Clubhouse—Interiors and Facilities | H10: 0.27 | I10: 1 | K10: =IF(L10=1,H10,0) -> 0
B11: AtR | C11: Ph 1, 2a, 2b | D11: Architecture | E11: Saji A | F11: Clubhouse + Amenities - Community spaces [Staff Lounge, Children play area] | H11: 0.045377036 | I11: 1 | K11: =IF(L11=1,H11,0) -> 0
B12: AtR | C12: Ph 2c | D12: Architecture | E12: Saji A | F12: Master Plan - Site MEP | H12: 0.042238262 | I12: 1 | K12: =IF(L12=1,H12,0) -> 0
B13: AtR | C13: Ph 2c | D13: Architecture | E13: Saji A | F13: Clubhouse + Amenities - Sporting Facilities | H13: 0.039416284 | I13: 1 | K13: =IF(L13=1,H13,0) -> 0
B14: AtR | C14: Ph 1, 2a, 2b, 2c | D14: Structural | F14: Package Release [Complete LoD 350 by Q1] | H14: =SUM(H15:H17) -> 0.021350947 | I14: =SUM(I15:I17) -> 3 | K14: =SUM(K15:K17) -> 0 | L14: =SUM(L15:L17) -> 0
B15: AtR | C15: Ph 1, 2a, 2b | D15: Structural | E15: Prakash C | F15: Clubhouse + Amenities - Community spaces [Staff Lounge, Children play area] | H15: 0.0052867303 | I15: 1 | K15: =IF(L15=1,H15,0) -> 0
B16: AtR | C16: Ph 2c | D16: Structural | E16: Prakash C | F16: Master Plan - Site MEP | H16: 0.010861268 | I16: 1 | K16: =IF(L16=1,H16,0) -> 0
B17: AtR | C17: Ph 2c | D17: Structural | E17: Prakash C | F17: Clubhouse + Amenities - Sporting Facilities | H17: 0.0052029495 | I17: 1 | K17: =IF(L17=1,H17,0) -> 0
B18: AtR | C18: Ph 1, 2a, 2b, 2c | D18: MEP | F18: Package Release [Complete LoD 350 by Q1] | H18: =SUM(H19:H19) -> 0.014336873 | I18: =SUM(I19:I19) -> 1 | K18: =SUM(K19:K19) -> 0 | L18: =SUM(L19:L19) -> 0
B19: AtR | C19: Ph 2c | D19: MEP | E19: Gagan | F19: Master Plan - Site MEP | H19: 0.014336873 | I19: 1 | K19: =IF(L19=1,H19,0) -> 0
B20: AtR | C20: Ph 3 | F20: Package Release [Complete LoD 350 by Q1] | H20: =SUM(H21,H37,H53,H61) -> 2.5304736 | I20: =SUM(I21,I37,I53,I61) -> 42 | K20: =SUM(K21,K37,K53,K61) -> 0.89157135 | L20: =SUM(L21,L37,L53,L61) -> 12
B21: AtR | C21: Ph 3 | D21: Architecture | F21: Package Release [Complete LoD 350 by Q1] | G21: =SUM(G22:G36) -> 0 | H21: =SUM(H22:H36) -> 1.8087698 | I21: =SUM(I22:I36) -> 15 | J21: =SUM(J22:J36) -> 0 | K21: =SUM(K22:K36) -> 0.68495917 | L21: =SUM(L22:L36) -> 3 | M21: =SUM(M22:M36) -> 0
B22: AtR | C22: Ph 3 | D22: Architecture | E22: Saji A | F22: Contract + Design brief | H22: 0.27398367 | I22: 1 | K22: =IF(L22=1,H22,0) -> 0.27398367 | L22: 1
B23: AtR | C23: Ph 3 | D23: Architecture | E23: Saji A | F23: Schematic Concept | H23: 0.27398367 | I23: 1 | K23: =IF(L23=1,H23,0) -> 0.27398367 | L23: 1
B24: AtR | C24: Ph 3 | D24: Architecture | E24: Saji A | F24: Approvals | H24: 0.13699183 | I24: 1 | K24: =IF(L24=1,H24,0) -> 0.13699183 | L24: 1
B25: AtR | C25: Ph 3 | D25: Architecture | E25: Saji A | F25: Pre Construction Set | H25: 0.27398367 | I25: 1 | K25: =IF(L25=1,H25,0) -> 0
B26: AtR | C26: Ph 3 | D26: Architecture | E26: Saji A | F26: Home Products - V45 Default and it's variants | H26: 0.36 | I26: 1 | K26: =IF(L26=1,H26,0) -> 0
B27: AtR | C27: Ph 3 | D27: Architecture | E27: Saji A | F27: Villa Block 33 - Foundations and Sub-Grade Structure | H27: 0.043982696 | I27: 1 | K27: =IF(L27=1,H27,0) -> 0
B28: AtR | C28: Ph 3 | D28: Architecture | E28: Saji A | F28: Villa Block 34 - Foundations and Sub-Grade Structure | H28: 0.043982696 | I28: 1 | K28: =IF(L28=1,H28,0) -> 0
B29: AtR | C29: Ph 3 | D29: Architecture | E29: Saji A | F29: Villa Block 29 - Foundations and Sub-Grade Structure | H29: 0.065974043 | I29: 1 | K29: =IF(L29=1,H29,0) -> 0
B30: AtR | C30: Ph 3 | D30: Architecture | E30: Saji A | F30: Villa Block 29 - Building Envelope + Plot Development | H30: 0.065974043 | I30: 1 | K30: =IF(L30=1,H30,0) -> 0
B31: AtR | C31: Ph 3 | D31: Architecture | E31: Saji A | F31: Villa Block 30 - Foundations and Sub-Grade Structure | H31: 0.065974043 | I31: 1 | K31: =IF(L31=1,H31,0) -> 0
B32: AtR | C32: Ph 3 | D32: Architecture | E32: Saji A | F32: Villa Block 30 - Building Envelope + Plot Development | H32: 0.065974043 | I32: 1 | K32: =IF(L32=1,H32,0) -> 0
B33: AtR | C33: Ph 3 | D33: Architecture | E33: Saji A | F33: Villa Block 31 - Building Envelope + Plot Development | H33: 0.014660899 | I33: 1 | K33: =IF(L33=1,H33,0) -> 0
B34: AtR | C34: Ph 3 | D34: Architecture | E34: Saji A | F34: Villa Block 32 - Building Envelope + Plot Development | H34: 0.029321797 | I34: 1 | K34: =IF(L34=1,H34,0) -> 0
B35: AtR | C35: Ph 3 | D35: Architecture | E35: Saji A | F35: Villa Block 34 - Building Envelope + Plot Development | H35: 0.043982696 | I35: 1 | K35: =IF(L35=1,H35,0) -> 0
B36: AtR | C36: Ph 3 | D36: Architecture | E36: Saji A | F36: Master Plan - Master Plan | H36: 0.05 | I36: 1 | K36: =IF(L36=1,H36,0) -> 0
B37: AtR | C37: Ph 3 | D37: Structural | F37: Package Release [Complete LoD 350 by Q1] | H37: =SUM(H38:H52) -> 0.35597209 | I37: =SUM(I38:I52) -> 15 | K37: =SUM(K38:K52) -> 0.1044216 | L37: =SUM(L38:L52) -> 3
B38: AtR | C38: Ph 3 | D38: Structural | E38: Prakash C | F38: Schematic Concept | H38: 0.093421604 | I38: 1 | K38: =IF(L38=1,H38,0) -> 0.093421604 | L38: 1
B39: AtR | C39: Ph 3 | D39: Structural | E39: Prakash C | F39: Pre Construction Set | H39: 0.093421604 | I39: 1 | K39: =IF(L39=1,H39,0) -> 0
B40: AtR | C40: Ph 3 | D40: Structural | E40: Prakash C | F40: Villa Block 29 - Foundations and Sub-Grade Structure | H40: 0.021106865 | I40: 1 | K40: =IF(L40=1,H40,0) -> 0
B41: AtR | C41: Ph 3 | D41: Structural | E41: Prakash C | F41: Villa Block 29 - Super Structure | H41: 0.031660298 | I41: 1 | K41: =IF(L41=1,H41,0) -> 0
B42: AtR | C42: Ph 3 | D42: Structural | E42: Prakash C | F42: Villa Block 29 - Building Envelope + Plot Development | H42: 0.0052767164 | I42: 1 | K42: =IF(L42=1,H42,0) -> 0
B43: AtR | C43: Ph 3 | D43: Structural | E43: Prakash C | F43: Villa Block 30 - Foundations and Sub-Grade Structure | H43: 0.021106865 | I43: 1 | K43: =IF(L43=1,H43,0) -> 0
B44: AtR | C44: Ph 3 | D44: Structural | E44: Prakash C | F44: Villa Block 30 - Super Structure | H44: 0.031660298 | I44: 1 | K44: =IF(L44=1,H44,0) -> 0
B45: AtR | C45: Ph 3 | D45: Structural | E45: Prakash C | F45: Villa Block 30 - Building Envelope + Plot Development | H45: 0.0052767164 | I45: 1 | K45: =IF(L45=1,H45,0) -> 0
B46: AtR | C46: Ph 3 | D46: Structural | E46: Prakash C | F46: Villa Block 31 - Foundations and Sub-Grade Structure | H46: 0.004 | I46: 1 | K46: =IF(L46=1,H46,0) -> 0.004 | L46: 1
B47: AtR | C47: Ph 3 | D47: Structural | E47: Prakash C | F47: Villa Block 31 - Super Structure | H47: 0.007 | I47: 1 | K47: =IF(L47=1,H47,0) -> 0.007 | L47: 1
B48: AtR | C48: Ph 3 | D48: Structural | E48: Prakash C | F48: Villa Block 31 - Building Envelope + Plot Development | H48: 0.001 | I48: 1 | K48: =IF(L48=1,H48,0) -> 0
B49: AtR | C49: Ph 3 | D49: Structural | E49: Prakash C | F49: Villa Block 32 - Building Envelope + Plot Development | H49: 0.0023452073 | I49: 1 | K49: =IF(L49=1,H49,0) -> 0
B50: AtR | C50: Ph 3 | D50: Structural | E50: Prakash C | F50: Villa Block 34 - Foundations and Sub-Grade Structure | H50: 0.014071244 | I50: 1 | K50: =IF(L50=1,H50,0) -> 0
B51: AtR | C51: Ph 3 | D51: Structural | E51: Prakash C | F51: Villa Block 34 - Super Structure | H51: 0.021106865 | I51: 1 | K51: =IF(L51=1,H51,0) -> 0
B52: AtR | C52: Ph 3 | D52: Structural | E52: Prakash C | F52: Villa Block 34 - Building Envelope + Plot Development | H52: 0.0035178109 | I52: 1 | K52: =IF(L52=1,H52,0) -> 0
B53: AtR | C53: Ph 3 | D53: MEP | F53: Package Release [Complete LoD 350 by Q1] | H53: =SUM(H54:H60) -> 0.19360007 | I53: =SUM(I54:I60) -> 7 | K53: =SUM(K54:K60) -> 0.024327053 | L53: =SUM(L54:L60) -> 3
B54: AtR | C54: Ph 3 | D54: MEP | E54: Gagan | F54: Schematic Concept [V80] | H54: 0.021499694 | I54: 1 | K54: =IF(L54=1,H54,0) -> 0.021499694 | L54: 1
B55: AtR | C55: Ph 3 | D55: MEP | E55: Gagan | F55: PreConstruction Set | H55: 0.021499694 | I55: 1 | K55: =IF(L55=1,H55,0) -> 0
B56: AtR | C56: Ph 3 | D56: MEP | E56: Gagan | F56: Villa Block 31 - Foundations and Sub-Grade Structure | H56: 0.00094245303 | I56: 1 | K56: =IF(L56=1,H56,0) -> 0.00094245303 | L56: 1
B57: AtR | C57: Ph 3 | D57: MEP | E57: Gagan | F57: Villa Block 32 - Foundations and Sub-Grade Structure | H57: 0.0018849061 | I57: 1 | K57: =IF(L57=1,H57,0) -> 0.0018849061 | L57: 1
B58: AtR | C58: Ph 3 | D58: MEP | E58: Gagan | F58: Villa Block 34 - Foundations and Sub-Grade Structure | H58: 0.0028273591 | I58: 1 | K58: =IF(L58=1,H58,0) -> 0
B59: AtR | C59: Ph 3 | D59: MEP | E59: Gagan | F59: Home Products - V45 Default and it's variants | H59: 0.10494597 | I59: 1 | K59: =IF(L59=1,H59,0) -> 0
B60: AtR | C60: Ph 3 | D60: MEP | E60: Gagan | F60: Master Plan - Master Plan | H60: 0.04 | I60: 1 | K60: =IF(L60=1,H60,0) -> 0
B61: AtR | C61: Ph 3 | D61: Landscape | F61: Package Release [Complete LoD 350 by Q1] | H61: =SUM(H62:H66) -> 0.17213169 | I61: =SUM(I62:I66) -> 5 | K61: =SUM(K62:K66) -> 0.07786352 | L61: =SUM(L62:L66) -> 3
B62: AtR | C62: Ph 3 | D62: Landscape | E62: Gagan | F62: Schematic Concept | H62: 0.04786352 | I62: 1 | K62: =IF(L62=1,H62,0) -> 0.04786352 | L62: 1
B63: AtR | C63: Ph 3 | D63: Landscape | E63: Gagan | F63: Preconstruction Set | H63: 0.04786352 | I63: 1 | K63: =IF(L63=1,H63,0) -> 0
B64: AtR | C64: Ph 3 | D64: Landscape | E64: Gagan | F64: Home Products - V45 Default | H64: 0.046404646 | I64: 1 | K64: =IF(L64=1,H64,0) -> 0
